Workbook

Sheet Enero Ventas
A1: COSTANERA GRILL · ENERO 2026 · REGISTRO DE VENTAS (SIMULACIÓN)
A2: Datos inventados para ejercicio de capacitación. Sin validez fiscal ni contable. IVA calculado con fórmula sobre base imponible.
A4: Fecha | B4: Tipo comprobante | C4: Número | D4: Cliente | E4: CUIT cliente (ficticio) | F4: Concepto | G4: Cantidad | H4: Neto gravado | I4: Alícuota IVA | J4: IVA débito | K4: Total | L4: Medio de cobro
A5: 46023 | B5: Factura A | C5: 0001-00001001 | D5: Consumidor final | E5: 30-70051000-1 | F5: Parrilla y cortes | G5: 1 | H5: 128737 | I5: 0.21 | J5: =ROUND(H5*I5,2) -> 27034.77 | K5: =ROUND(H5+J5,2) -> 155771.77 | L5: Efectivo
A6: 46024 | B6: Factura B | C6: 0001-00001002 | D6: Hotel Dársena (FICTICIO) | F6: Menú ejecutivo | G6: 2 | H6: 51682 | I6: 0.21 | J6: =ROUND(H6*I6,2) -> 10853.22 | K6: =ROUND(H6+J6,2) -> 62535.22 | L6: Transferencia
A7: 46025 | B7: Factura B | C7: 0001-00001003 | D7: Consumidor final | F7: Cortes premium | G7: 3 | H7: 64628 | I7: 0.21 | J7: =ROUND(H7*I7,2) -> 13571.88 | K7: =ROUND(H7+J7,2) -> 78199.88 | L7: Tarjeta de débito
A8: 46026 | B8: Factura B | C8: 0001-00001004 | D8: Consultora Río (FICTICIA) | F8: Bebidas y cubiertos | G8: 4 | H8: 77574 | I8: 0.21 | J8: =ROUND(H8*I8,2) -> 16290.54 | K8: =ROUND(H8+J8,2) -> 93864.54 | L8: Mercado Pago
A9: 46027 | B9: Factura B | C9: 0001-00001005 | D9: Estudio Madero (FICTICIO) | F9: Parrilla y cortes | G9: 5 | H9: 90520 | I9: 0.21 | J9: =ROUND(H9*I9,2) -> 19009.2 | K9: =ROUND(H9+J9,2) -> 109529.2 | L9: Tarjeta de crédito
A10: 46028 | B10: Factura B | C10: 0001-00001006 | D10: Consumidor final | F10: Menú ejecutivo | G10: 6 | H10: 103466 | I10: 0.21 | J10: =ROUND(H10*I10,2) -> 21727.86 | K10: =ROUND(H10+J10,2) -> 125193.86 | L10: Efectivo
A11: 46029 | B11: Factura B | C11: 0001-00001007 | D11: Consumidor final | F11: Cortes premium | G11: 1 | H11: 116412 | I11: 0.21 | J11: =ROUND(H11*I11,2) -> 24446.52 | K11: =ROUND(H11+J11,2) -> 140858.52 | L11: Transferencia
A12: 46030 | B12: Factura B | C12: 0001-00001008 | D12: Consumidor final | F12: Bebidas y cubiertos | G12: 2 | H12: 129358 | I12: 0.21 | J12: =ROUND(H12*I12,2) -> 27165.18 | K12: =ROUND(H12+J12,2) -> 156523.18 | L12: Tarjeta de débito
A13: 46031 | B13: Factura B | C13: 0001-00001009 | D13: Consumidor final | F13: Parrilla y cortes | G13: 3 | H13: 52303 | I13: 0.21 | J13: =ROUND(H13*I13,2) -> 10983.63 | K13: =ROUND(H13+J13,2) -> 63286.63 | L13: Mercado Pago
A14: 46032 | B14: Factura B | C14: 0001-00001010 | D14: Empresa de Eventos Sur (FICTICIA) | F14: Menú ejecutivo | G14: 4 | H14: 65249 | I14: 0.21 | J14: =ROUND(H14*I14,2) -> 13702.29 | K14: =ROUND(H14+J14,2) -> 78951.29 | L14: Tarjeta de crédito
A15: 46033 | B15: Factura A | C15: 0001-00001011 | D15: Consumidor final | E15: 30-70053210-3 | F15: Cortes premium | G15: 5 | H15: 78195 | I15: 0.21 | J15: =ROUND(H15*I15,2) -> 16420.95 | K15: =ROUND(H15+J15,2) -> 94615.95 | L15: Efectivo
A16: 46034 | B16: Factura B | C16: 0001-00001012 | D16: Agencia Costera (FICTICIA) | F16: Bebidas y cubiertos | G16: 6 | H16: 91141 | I16: 0.21 | J16: =ROUND(H16*I16,2) -> 19139.61 | K16: =ROUND(H16+J16,2) -> 110280.61 | L16: Transferencia
A17: 46035 | B17: Factura B | C17: 0001-00001013 | D17: Consumidor final | F17: Parrilla y cortes | G17: 1 | H17: 104087 | I17: 0.21 | J17: =ROUND(H17*I17,2) -> 21858.27 | K17: =ROUND(H17+J17,2) -> 125945.27 | L17: Tarjeta de débito
A18: 46036 | B18: Factura B | C18: 0001-00001014 | D18: Hotel Dársena (FICTICIO) | F18: Menú ejecutivo | G18: 2 | H18: 117033 | I18: 0.21 | J18: =ROUND(H18*I18,2) -> 24576.93 | K18: =ROUND(H18+J18,2) -> 141609.93 | L18: Mercado Pago
A19: 46037 | B19: Factura B | C19: 0001-00001015 | D19: Consumidor final | F19: Cortes premium | G19: 3 | H19: 129979 | I19: 0.21 | J19: =ROUND(H19*I19,2) -> 27295.59 | K19: =ROUND(H19+J19,2) -> 157274.59 | L19: Tarjeta de crédito
A20: 46038 | B20: Factura B | C20: 0001-00001016 | D20: Consultora Río (FICTICIA) | F20: Bebidas y cubiertos | G20: 4 | H20: 52924 | I20: 0.21 | J20: =ROUND(H20*I20,2) -> 11114.04 | K20: =ROUND(H20+J20,2) -> 64038.04 | L20: Efectivo
A21: 46039 | B21: Factura B | C21: 0001-00001017 | D21: Estudio Madero (FICTICIO) | F21: Parrilla y cortes | G21: 5 | H21: 65870 | I21: 0.21 | J21: =ROUND(H21*I21,2) -> 13832.7 | K21: =ROUND(H21+J21,2) -> 79702.7 | L21: Transferencia
A22: 46040 | B22: Factura B | C22: 0001-00001018 | D22: Consumidor final | F22: Menú ejecutivo | G22: 6 | H22: 78816 | I22: 0.21 | J22: =ROUND(H22*I22,2) -> 16551.36 | K22: =ROUND(H22+J22,2) -> 95367.36 | L22: Tarjeta de débito
A23: 46041 | B23: Factura B | C23: 0001-00001019 | D23: Consumidor final | F23: Cortes premium | G23: 1 | H23: 91762 | I23: 0.21 | J23: =ROUND(H23*I23,2) -> 19270.02 | K23: =ROUND(H23+J23,2) -> 111032.02 | L23: Mercado Pago
A24: 46042 | B24: Factura B | C24: 0001-00001020 | D24: Consumidor final | F24: Bebidas y cubiertos | G24: 2 | H24: 104708 | I24: 0.21 | J24: =ROUND(H24*I24,2) -> 21988.68 | K24: =ROUND(H24+J24,2) -> 126696.68 | L24: Tarjeta de crédito
A25: 46043 | B25: Factura A | C25: 0001-00001021 | D25: Consumidor final | E25: 30-70055420-5 | F25: Parrilla y cortes | G25: 3 | H25: 117654 | I25: 0.21 | J25: =ROUND(H25*I25,2) -> 24707.34 | K25: =ROUND(H25+J25,2) -> 142361.34 | L25: Efectivo
A26: 46044 | B26: Factura B | C26: 0001-00001022 | D26: Empresa de Eventos Sur (FICTICIA) | F26: Menú ejecutivo | G26: 4 | H26: 130600 | I26: 0.21 | J26: =ROUND(H26*I26,2) -> 27426 | K26: =ROUND(H26+J26,2) -> 158026 | L26: Transferencia
A27: 46045 | B27: Factura B | C27: 0001-00001023 | D27: Consumidor final | F27: Cortes premium | G27: 5 | H27: 53545 | I27: 0.21 | J27: =ROUND(H27*I27,2) -> 11244.45 | K27: =ROUND(H27+J27,2) -> 64789.45 | L27: Tarjeta de débito
A28: 46046 | B28: Factura B | C28: 0001-00001024 | D28: Agencia Costera (FICTICIA) | F28: Bebidas y cubiertos | G28: 6 | H28: 66491 | I28: 0.21 | J28: =ROUND(H28*I28,2) -> 13963.11 | K28: =ROUND(H28+J28,2) -> 80454.11 | L28: Mercado Pago
A29: 46047 | B29: Factura B | C29: 0001-00001025 | D29: Consumidor final | F29: Parrilla y cortes | G29: 1 | H29: 79437 | I29: 0.21 | J29: =ROUND(H29*I29,2) -> 16681.77 | K29: =ROUND(H29+J29,2) -> 96118.77 | L29: Tarjeta de crédito
A30: 46048 | B30: Factura B | C30: 0001-00001026 | D30: Hotel Dársena (FICTICIO) | F30: Menú ejecutivo | G30: 2 | H30: 92383 | I30: 0.21 | J30: =ROUND(H30*I30,2) -> 19400.43 | K30: =ROUND(H30+J30,2) -> 111783.43 | L30: Efectivo
A31: 46049 | B31: Factura B | C31: 0001-00001027 | D31: Consumidor final | F31: Cortes premium | G31: 3 | H31: 105329 | I31: 0.21 | J31: =ROUND(H31*I31,2) -> 22119.09 | K31: =ROUND(H31+J31,2) -> 127448.09 | L31: Transferencia
A32: 46050 | B32: Factura B | C32: 0001-00001028 | D32: Consultora Río (FICTICIA) | F32: Bebidas y cubiertos | G32: 4 | H32: 118275 | I32: 0.21 | J32: =ROUND(H32*I32,2) -> 24837.75 | K32: =ROUND(H32+J32,2) -> 143112.75 | L32: Tarjeta de débito
A33: 46023 | B33: Factura B | C33: 0001-00001029 | D33: Estudio Madero (FICTICIO) | F33: Parrilla y cortes | G33: 5 | H33: 131221 | I33: 0.21 | J33: =ROUND(H33*I33,2) -> 27556.41 | K33: =ROUND(H33+J33,2) -> 158777.41 | L33: Mercado Pago
A34: 46024 | B34: Factura B | C34: 0001-00001030 | D34: Consumidor final | F34: Menú ejecutivo | G34: 6 | H34: 54166 | I34: 0.21 | J34: =ROUND(H34*I34,2) -> 11374.86 | K34: =ROUND(H34+J34,2) -> 65540.86 | L34: Tarjeta de crédito
A35: 46025 | B35: Factura A | C35: 0001-00001031 | D35: Consumidor final | E35: 30-70057630-7 | F35: Cortes premium | G35: 1 | H35: 67112 | I35: 0.21 | J35: =ROUND(H35*I35,2) -> 14093.52 | K35: =ROUND(H35+J35,2) -> 81205.52 | L35: Efectivo
A36: 46026 | B36: Factura B | C36: 0001-00001032 | D36: Consumidor final | F36: Bebidas y cubiertos | G36: 2 | H36: 80058 | I36: 0.21 | J36: =ROUND(H36*I36,2) -> 16812.18 | K36: =ROUND(H36+J36,2) -> 96870.18 | L36: Transferencia
A37: 46027 | B37: Factura B | C37: 0001-00001033 | D37: Consumidor final | F37: Parrilla y cortes | G37: 3 | H37: 93004 | I37: 0.21 | J37: =ROUND(H37*I37,2) -> 19530.84 | K37: =ROUND(H37+J37,2) -> 112534.84 | L37: Tarjeta de débito
A38: 46028 | B38: Factura B | C38: 0001-00001034 | D38: Empresa de Eventos Sur (FICTICIA) | F38: Menú ejecutivo | G38: 4 | H38: 105950 | I38: 0.21 | J38: =ROUND(H38*I38,2) -> 22249.5 | K38: =ROUND(H38+J38,2) -> 128199.5 | L38: Mercado Pago
A39: 46029 | B39: Factura B | C39: 0001-00001035 | D39: Consumidor final | F39: Cortes premium | G39: 5 | H39: 118896 | I39: 0.21 | J39: =ROUND(H39*I39,2) -> 24968.16 | K39: =ROUND(H39+J39,2) -> 143864.16 | L39: Tarjeta de crédito
A40: 46030 | B40: Factura B | C40: 0001-00001036 | D40: Agencia Costera (FICTICIA) | F40: Bebidas y cubiertos | G40: 6 | H40: 131842 | I40: 0.21 | J40: =ROUND(H40*I40,2) -> 27686.82 | K40: =ROUND(H40+J40,2) -> 159528.82 | L40: Efectivo
A41: 46031 | B41: Factura B | C41: 0001-00001037 | D41: Consumidor final | F41: Parrilla y cortes | G41: 1 | H41: 54787 | I41: 0.21 | J41: =ROUND(H41*I41,2) -> 11505.27 | K41: =ROUND(H41+J41,2) -> 66292.27 | L41: Transferencia
A42: 46032 | B42: Factura B | C42: 0001-00001038 | D42: Hotel Dársena (FICTICIO) | F42: Menú ejecutivo | G42: 2 | H42: 67733 | I42: 0.21 | J42: =ROUND(H42*I42,2) -> 14223.93 | K42: =ROUND(H42+J42,2) -> 81956.93 | L42: Tarjeta de débito
A43: 46033 | B43: Factura B | C43: 0001-00001039 | D43: Consumidor final | F43: Cortes premium | G43: 3 | H43: 80679 | I43: 0.21 | J43: =ROUND(H43*I43,2) -> 16942.59 | K43: =ROUND(H43+J43,2) -> 97621.59 | L43: Mercado Pago
A44: 46034 | B44: Factura B | C44: 0001-00001040 | D44: Consultora Río (FICTICIA) | F44: Bebidas y cubiertos | G44: 4 | H44: 93625 | I44: 0.21 | J44: =ROUND(H44*I44,2) -> 19661.25 | K44: =ROUND(H44+J44,2) -> 113286.25 | L44: Tarjeta de crédito
A45: 46035 | B45: Factura A | C45: 0001-00001041 | D45: Estudio Madero (FICTICIO) | E45: 30-70059840-1 | F45: Parrilla y cortes | G45: 5 | H45: 106571 | I45: 0.21 | J45: =ROUND(H45*I45,2) -> 22379.91 | K45: =ROUND(H45+J45,2) -> 128950.91 | L45: Efectivo
A46: 46036 | B46: Factura B | C46: 0001-00001042 | D46: Consumidor final | F46: Menú ejecutivo | G46: 6 | H46: 119517 | I46: 0.21 | J46: =ROUND(H46*I46,2) -> 25098.57 | K46: =ROUND(H46+J46,2) -> 144615.57 | L46: Transferencia
A47: 46037 | B47: Factura B | C47: 0001-00001043 | D47: Consumidor final | F47: Cortes premium | G47: 1 | H47: 42462 | I47: 0.21 | J47: =ROUND(H47*I47,2) -> 8917.02 | K47: =ROUND(H47+J47,2) -> 51379.02 | L47: Tarjeta de débito
A48: 46038 | B48: Factura B | C48: 0001-00001044 | D48: Consumidor final | F48: Bebidas y cubiertos | G48: 2 | H48: 55408 | I48: 0.21 | J48: =ROUND(H48*I48,2) -> 11635.68 | K48: =ROUND(H48+J48,2) -> 67043.68 | L48: Mercado Pago
A49: 46039 | B49: Factura B | C49: 0001-00001045 | D49: Consumidor final | F49: Parrilla y cortes | G49: 3 | H49: 68354 | I49: 0.21 | J49: =ROUND(H49*I49,2) -> 14354.34 | K49: =ROUND(H49+J49,2) -> 82708.34 | L49: Tarjeta de crédito
A50: 46040 | B50: Factura B | C50: 0001-00001046 | D50: Empresa de Eventos Sur (FICTICIA) | F50: Menú ejecutivo | G50: 4 | H50: 81300 | I50: 0.21 | J50: =ROUND(H50*I50,2) -> 17073 | K50: =ROUND(H50+J50,2) -> 98373 | L50: Efectivo
A51: 46041 | B51: Factura B | C51: 0001-00001047 | D51: Consumidor final | F51: Cortes premium | G51: 5 | H51: 94246 | I51: 0.21 | J51: =ROUND(H51*I51,2) -> 19791.66 | K51: =ROUND(H51+J51,2) -> 114037.66 | L51: Transferencia
A52: 46042 | B52: Factura B | C52: 0001-00001048 | D52: Agencia Costera (FICTICIA) | F52: Bebidas y cubiertos | G52: 6 | H52: 107192 | I52: 0.21 | J52: =ROUND(H52*I52,2) -> 22510.32 | K52: =ROUND(H52+J52,2) -> 129702.32 | L52: Tarjeta de débito
A53: 46043 | B53: Factura B | C53: 0001-00001049 | D53: Consumidor final | F53: Parrilla y cortes | G53: 1 | H53: 120138 | I53: 0.21 | J53: =ROUND(H53*I53,2) -> 25228.98 | K53: =ROUND(H53+J53,2) -> 145366.98 | L53: Mercado Pago
A54: 46044 | B54: Factura B | C54: 0001-00001050 | D54: Hotel Dársena (FICTICIO) | F54: Menú ejecutivo | G54: 2 | H54: 43083 | I54: 0.21 | J54: =ROUND(H54*I54,2) -> 9047.43 | K54: =ROUND(H54+J54,2) -> 52130.43 | L54: Tarjeta de crédito
A55: 46045 | B55: Factura A | C55: 0001-00001051 | D55: Consumidor final | E55: 30-70062050-3 | F55: Cortes premium | G55: 3 | H55: 56029 | I55: 0.21 | J55: =ROUND(H55*I55,2) -> 11766.09 | K55: =ROUND(H55+J55,2) -> 67795.09 | L55: Efectivo
A56: 46046 | B56: Factura B | C56: 0001-00001052 | D56: Consultora Río (FICTICIA) | F56: Bebidas y cubiertos | G56: 4 | H56: 68975 | I56: 0.21 | J56: =ROUND(H56*I56,2) -> 14484.75 | K56: =ROUND(H56+J56,2) -> 83459.75 | L56: Transferencia
A57: 46047 | B57: Factura B | C57: 0001-00001053 | D57: Estudio Madero (FICTICIO) | F57: Parrilla y cortes | G57: 5 | H57: 81921 | I57: 0.21 | J57: =ROUND(H57*I57,2) -> 17203.41 | K57: =ROUND(H57+J57,2) -> 99124.41 | L57: Tarjeta de débito
A58: 46048 | B58: Factura B | C58: 0001-00001054 | D58: Consumidor final | F58: Menú ejecutivo | G58: 6 | H58: 94867 | I58: 0.21 | J58: =ROUND(H58*I58,2) -> 19922.07 | K58: =ROUND(H58+J58,2) -> 114789.07 | L58: Mercado Pago

Sheet Enero Gastos
A1: COSTANERA GRILL · ENERO 2026 · REGISTRO DE COMPRAS Y GASTOS (SIMULACIÓN)
A2: Proveedores y comprobantes ficticios. Alícuotas ilustrativas; verificar normativa aplicable en un caso real.
A4: Fecha | B4: Proveedor | C4: CUIT proveedor (ficticio) | D4: Tipo comprobante | E4: Categoría | F4: Detalle | G4: Neto gravado | H4: Alícuota IVA | I4: IVA crédito | J4: Total | K4: Medio de pago
A5: 46024 | B5: Frigorífico La Pampa (FICTICIO) | C5: 30-70123456-1 | D5: Factura A | E5: Carne | F5: Compra de carne para operación | G5: 215353 | H5: 0.105 | I5: =ROUND(G5*H5,2) -> 22612.07 | J5: =ROUND(G5+I5,2) -> 237965.07 | K5: Efectivo
A6: 46027 | B6: Carnes del Sur (FICTICIO) | C6: 30-70987654-2 | D6: Factura B | E6: Carne | F6: Compra de carne para operación | G6: 180030 | H6: 0.105 | I6: =ROUND(G6*H6,2) -> 18903.15 | J6: =ROUND(G6+I6,2) -> 198933.15 | K6: Tarjeta de débito
A7: 46030 | B7: Bebidas Río (FICTICIO) | C7: 30-71234567-3 | D7: Factura B | E7: Bebidas | F7: Compra de bebidas para operación | G7: 94278 | H7: 0.21 | I7: =ROUND(G7*H7,2) -> 19798.38 | J7: =ROUND(G7+I7,2) -> 114076.38 | K7: Tarjeta de crédito
A8: 46033 | B8: Distribuidora Malbec (FICTICIO) | C8: 30-72345678-4 | D8: Factura A | E8: Bebidas | F8: Compra de bebidas para operación | G8: 56754 | H8: 0.21 | I8: =ROUND(G8*H8,2) -> 11918.34 | J8: =ROUND(G8+I8,2) -> 68672.34 | K8: Transferencia
A9: 46036 | B9: Edenor - ejemplo didáctico | C9: 30-54567891-2 | D9: Factura B | E9: Electricidad | F9: Compra de electricidad para operación | G9: 103573 | H9: 0.21 | I9: =ROUND(G9*H9,2) -> 21750.33 | J9: =ROUND(G9+I9,2) -> 125323.33 | K9: Mercado Pago
A10: 46039 | B10: Metrogas - ejemplo didáctico | C10: 30-65789123-4 | D10: Factura B | E10: Gas | F10: Compra de gas para operación | G10: 79939 | H10: 0.21 | I10: =ROUND(G10*H10,2) -> 16787.19 | J10: =ROUND(G10+I10,2) -> 96726.19 | K10: Efectivo
A11: 46042 | B11: Fibra Puerto (FICTICIO) | C11: 30-67891234-5 | D11: Factura A | E11: Internet | F11: Compra de internet para operación | G11: 29718 | H11: 0.21 | I11: =ROUND(G11*H11,2) -> 6240.78 | J11: =ROUND(G11+I11,2) -> 35958.78 | K11: Tarjeta de débito
A12: 46045 | B12: Limpieza del Puerto (FICTICIO) | C12: 30-68912345-6 | D12: Factura B | E12: Limpieza | F12: Compra de limpieza para operación | G12: 50045 | H12: 0.21 | I12: =ROUND(G12*H12,2) -> 10509.45 | J12: =ROUND(G12+I12,2) -> 60554.45 | K12: Tarjeta de crédito
A13: 46048 | B13: Envases del Plata (FICTICIO) | C13: 30-69123456-7 | D13: Factura B | E13: Insumos | F13: Compra de insumos para operación | G13: 52468 | H13: 0.21 | I13: =ROUND(G13*H13,2) -> 11018.28 | J13: =ROUND(G13+I13,2) -> 63486.28 | K13: Transferencia
A14: 46024 | B14: Alquiler local Puerto Madero (FICTICIO) | C14: 30-61234567-8 | D14: Factura A | E14: Alquiler | F14: Compra de alquiler para operación | G14: 131393 | H14: 0.21 | I14: =ROUND(G14*H14,2) -> 27592.53 | J14: =ROUND(G14+I14,2) -> 158985.53 | K14: Mercado Pago
A15: 46027 | B15: Mantenimiento Parrillero (FICTICIO) | C15: 30-63456789-1 | D15: Factura B | E15: Mantenimiento | F15: Compra de mantenimiento para operación | G15: 48409 | H15: 0.21 | I15: =ROUND(G15*H15,2) -> 10165.89 | J15: =ROUND(G15+I15,2) -> 58574.89 | K15: Efectivo
A16: 46030 | B16: Panificados del Puerto (FICTICIO) | C16: 30-64567891-3 | D16: Factura B | E16: Alimentos | F16: Compra de alimentos para operación | G16: 43167 | H16: 0.21 | I16: =ROUND(G16*H16,2) -> 9065.07 | J16: =ROUND(G16+I16,2) -> 52232.07 | K16: Tarjeta de débito
... A22: 46048 | B22: Papelería Administrativa (FICTICIO) | C22: 30-61234578-9 | D22: Factura B | E22: Administración | F22: Compra de administración para operación | G22: 12369 | H22: 0.21 | I22: =ROUND(G22*H22,2) -> 2597.49 | J22: =ROUND(G22+I22,2) -> 14966.49 | K22: Tarjeta de crédito

Sheet Febrero Ventas
A1: COSTANERA GRILL · FEBRERO 2026 · REGISTRO DE VENTAS (SIMULACIÓN)
A2: Datos inventados para ejercicio de capacitación. Sin validez fiscal ni contable. IVA calculado con fórmula sobre base imponible.
A4: Fecha | B4: Tipo comprobante | C4: Número | D4: Cliente | E4: CUIT cliente (ficticio) | F4: Concepto | G4: Cantidad | H4: Neto gravado | I4: Alícuota IVA | J4: IVA débito | K4: Total | L4: Medio de cobro
A5: 46054 | B5: Factura A | C5: 0001-00002001 | D5: Consumidor final | E5: 30-70052547-4 | F5: Menú ejecutivo | G5: 1 | H5: 95724.92 | I5: 0.21 | J5: =ROUND(H5*I5,2) -> 20102.23 | K5: =ROUND(H5+J5,2) -> 115827.15 | L5: Tarjeta de débito
A6: 46055 | B6: Factura B | C6: 0001-00002002 | D6: Consumidor final | F6: Cortes premium | G6: 2 | H6: 38704.22 | I6: 0.21 | J6: =ROUND(H6*I6,2) -> 8127.89 | K6: =ROUND(H6+J6,2) -> 46832.11 | L6: Mercado Pago
A7: 46056 | B7: Factura B | C7: 0001-00002003 | D7: Empresa de Eventos Sur (FICTICIA) | F7: Bebidas y cubiertos | G7: 3 | H7: 48284.26 | I7: 0.21 | J7: =ROUND(H7*I7,2) -> 10139.69 | K7: =ROUND(H7+J7,2) -> 58423.95 | L7: Tarjeta de crédito
A8: 46057 | B8: Factura B | C8: 0001-00002004 | D8: Consumidor final | F8: Parrilla y cortes | G8: 4 | H8: 57864.3 | I8: 0.21 | J8: =ROUND(H8*I8,2) -> 12151.5 | K8: =ROUND(H8+J8,2) -> 70015.8 | L8: Efectivo
A9: 46058 | B9: Factura B | C9: 0001-00002005 | D9: Agencia Costera (FICTICIA) | F9: Menú ejecutivo | G9: 5 | H9: 67444.34 | I9: 0.21 | J9: =ROUND(H9*I9,2) -> 14163.31 | K9: =ROUND(H9+J9,2) -> 81607.65 | L9: Transferencia
A10: 46059 | B10: Factura B | C10: 0001-00002006 | D10: Consumidor final | F10: Cortes premium | G10: 6 | H10: 77024.38 | I10: 0.21 | J10: =ROUND(H10*I10,2) -> 16175.12 | K10: =ROUND(H10+J10,2) -> 93199.5 | L10: Tarjeta de débito
A11: 46060 | B11: Factura B | C11: 0001-00002007 | D11: Hotel Dársena (FICTICIO) | F11: Bebidas y cubiertos | G11: 1 | H11: 86604.42 | I11: 0.21 | J11: =ROUND(H11*I11,2) -> 18186.93 | K11: =ROUND(H11+J11,2) -> 104791.35 | L11: Mercado Pago
A12: 46061 | B12: Factura B | C12: 0001-00002008 | D12: Consumidor final | F12: Parrilla y cortes | G12: 2 | H12: 96184.46 | I12: 0.21 | J12: =ROUND(H12*I12,2) -> 20198.74 | K12: =ROUND(H12+J12,2) -> 116383.2 | L12: Tarjeta de crédito
A13: 46062 | B13: Factura B | C13: 0001-00002009 | D13: Consultora Río (FICTICIA) | F13: Menú ejecutivo | G13: 3 | H13: 39163.76 | I13: 0.21 | J13: =ROUND(H13*I13,2) -> 8224.39 | K13: =ROUND(H13+J13,2) -> 47388.15 | L13: Efectivo
A14: 46063 | B14: Factura B | C14: 0001-00002010 | D14: Estudio Madero (FICTICIO) | F14: Cortes premium | G14: 4 | H14: 48743.8 | I14: 0.21 | J14: =ROUND(H14*I14,2) -> 10236.2 | K14: =ROUND(H14+J14,2) -> 58980 | L14: Transferencia
A15: 46064 | B15: Factura A | C15: 0001-00002011 | D15: Consumidor final | E15: 30-70054757-6 | F15: Bebidas y cubiertos | G15: 5 | H15: 58323.84 | I15: 0.21 | J15: =ROUND(H15*I15,2) -> 12248.01 | K15: =ROUND(H15+J15,2) -> 70571.85 | L15: Tarjeta de débito
A16: 46065 | B16: Factura B | C16: 0001-00002012 | D16: Consumidor final | F16: Parrilla y cortes | G16: 6 | H16: 67903.88 | I16: 0.21 | J16: =ROUND(H16*I16,2) -> 14259.81 | K16: =ROUND(H16+J16,2) -> 82163.69 | L16: Mercado Pago
A17: 46066 | B17: Factura B | C17: 0001-00002013 | D17: Consumidor final | F17: Menú ejecutivo | G17: 1 | H17: 77483.92 | I17: 0.21 | J17: =ROUND(H17*I17,2) -> 16271.62 | K17: =ROUND(H17+J17,2) -> 93755.54 | L17: Tarjeta de crédito
A18: 46067 | B18: Factura B | C18: 0001-00002014 | D18: Consumidor final | F18: Cortes premium | G18: 2 | H18: 87063.96 | I18: 0.21 | J18: =ROUND(H18*I18,2) -> 18283.43 | K18: =ROUND(H18+J18,2) -> 105347.39 | L18: Efectivo
A19: 46068 | B19: Factura B | C19: 0001-00002015 | D19: Empresa de Eventos Sur (FICTICIA) | F19: Bebidas y cubiertos | G19: 3 | H19: 96644 | I19: 0.21 | J19: =ROUND(H19*I19,2) -> 20295.24 | K19: =ROUND(H19+J19,2) -> 116939.24 | L19: Transferencia
A20: 46069 | B20: Factura B | C20: 0001-00002016 | D20: Consumidor final | F20: Parrilla y cortes | G20: 4 | H20: 39623.3 | I20: 0.21 | J20: =ROUND(H20*I20,2) -> 8320.89 | K20: =ROUND(H20+J20,2) -> 47944.19 | L20: Tarjeta de débito
A21: 46070 | B21: Factura B | C21: 0001-00002017 | D21: Agencia Costera (FICTICIA) | F21: Menú ejecutivo | G21: 5 | H21: 49203.34 | I21: 0.21 | J21: =ROUND(H21*I21,2) -> 10332.7 | K21: =ROUND(H21+J21,2) -> 59536.04 | L21: Mercado Pago
A22: 46071 | B22: Factura B | C22: 0001-00002018 | D22: Consumidor final | F22: Cortes premium | G22: 6 | H22: 58783.38 | I22: 0.21 | J22: =ROUND(H22*I22,2) -> 12344.51 | K22: =ROUND(H22+J22,2) -> 71127.89 | L22: Tarjeta de crédito
A23: 46072 | B23: Factura B | C23: 0001-00002019 | D23: Hotel Dársena (FICTICIO) | F23: Bebidas y cubiertos | G23: 1 | H23: 68363.42 | I23: 0.21 | J23: =ROUND(H23*I23,2) -> 14356.32 | K23: =ROUND(H23+J23,2) -> 82719.74 | L23: Efectivo
A24: 46073 | B24: Factura B | C24: 0001-00002020 | D24: Consumidor final | F24: Parrilla y cortes | G24: 2 | H24: 77943.46 | I24: 0.21 | J24: =ROUND(H24*I24,2) -> 16368.13 | K24: =ROUND(H24+J24,2) -> 94311.59 | L24: Transferencia
A25: 46074 | B25: Factura A | C25: 0001-00002021 | D25: Consultora Río (FICTICIA) | E25: 30-70056967-8 | F25: Menú ejecutivo | G25: 3 | H25: 118275 | I25: 0.21 | J25: =ROUND(H25*I25,2) -> 24837.75 | K25: =ROUND(H25+J25,2) -> 143112.75 | L25: Tarjeta de débito
A26: 46075 | B26: Factura B | C26: 0001-00002022 | D26: Estudio Madero (FICTICIO) | F26: Cortes premium | G26: 4 | H26: 131221 | I26: 0.21 | J26: =ROUND(H26*I26,2) -> 27556.41 | K26: =ROUND(H26+J26,2) -> 158777.41 | L26: Mercado Pago
A27: 46076 | B27: Factura B | C27: 0001-00002023 | D27: Consumidor final | F27: Bebidas y cubiertos | G27: 5 | H27: 54166 | I27: 0.21 | J27: =ROUND(H27*I27,2) -> 11374.86 | K27: =ROUND(H27+J27,2) -> 65540.86 | L27: Tarjeta de crédito
A28: 46077 | B28: Factura B | C28: 0001-00002024 | D28: Consumidor final | F28: Parrilla y cortes | G28: 6 | H28: 67112 | I28: 0.21 | J28: =ROUND(H28*I28,2) -> 14093.52 | K28: =ROUND(H28+J28,2) -> 81205.52 | L28: Efectivo
A29: 46078 | B29: Factura B | C29: 0001-00002025 | D29: Consumidor final | F29: Menú ejecutivo | G29: 1 | H29: 80058 | I29: 0.21 | J29: =ROUND(H29*I29,2) -> 16812.18 | K29: =ROUND(H29+J29,2) -> 96870.18 | L29: Transferencia
A30: 46079 | B30: Factura B | C30: 0001-00002026 | D30: Consumidor final | F30: Cortes premium | G30: 2 | H30: 93004 | I30: 0.21 | J30: =ROUND(H30*I30,2) -> 19530.84 | K30: =ROUND(H30+J30,2) -> 112534.84 | L30: Tarjeta de débito
A31: 46080 | B31: Factura B | C31: 0001-00002027 | D31: Empresa de Eventos Sur (FICTICIA) | F31: Bebidas y cubiertos | G31: 3 | H31: 105950 | I31: 0.21 | J31: =ROUND(H31*I31,2) -> 22249.5 | K31: =ROUND(H31+J31,2) -> 128199.5 | L31: Mercado Pago
A32: 46081 | B32: Factura B | C32: 0001-00002028 | D32: Consumidor final | F32: Parrilla y cortes | G32: 4 | H32: 118896 | I32: 0.21 | J32: =ROUND(H32*I32,2) -> 24968.16 | K32: =ROUND(H32+J32,2) -> 143864.16 | L32: Tarjeta de crédito
A33: 46054 | B33: Factura B | C33: 0001-00002029 | D33: Agencia Costera (FICTICIA) | F33: Menú ejecutivo | G33: 5 | H33: 131842 | I33: 0.21 | J33: =ROUND(H33*I33,2) -> 27686.82 | K33: =ROUND(H33+J33,2) -> 159528.82 | L33: Efectivo
A34: 46055 | B34: Factura B | C34: 0001-00002030 | D34: Consumidor final | F34: Cortes premium | G34: 6 | H34: 54787 | I34: 0.21 | J34: =ROUND(H34*I34,2) -> 11505.27 | K34: =ROUND(H34+J34,2) -> 66292.27 | L34: Transferencia
A35: 46056 | B35: Factura A | C35: 0001-00002031 | D35: Hotel Dársena (FICTICIO) | E35: 30-70059177-2 | F35: Bebidas y cubiertos | G35: 1 | H35: 67733 | I35: 0.21 | J35: =ROUND(H35*I35,2) -> 14223.93 | K35: =ROUND(H35+J35,2) -> 81956.93 | L35: Tarjeta de débito
A36: 46057 | B36: Factura B | C36: 0001-00002032 | D36: Consumidor final | F36: Parrilla y cortes | G36: 2 | H36: 80679 | I36: 0.21 | J36: =ROUND(H36*I36,2) -> 16942.59 | K36: =ROUND(H36+J36,2) -> 97621.59 | L36: Mercado Pago
A37: 46058 | B37: Factura B | C37: 0001-00002033 | D37: Consultora Río (FICTICIA) | F37: Menú ejecutivo | G37: 3 | H37: 93625 | I37: 0.21 | J37: =ROUND(H37*I37,2) -> 19661.25 | K37: =ROUND(H37+J37,2) -> 113286.25 | L37: Tarjeta de crédito
A38: 46059 | B38: Factura B | C38: 0001-00002034 | D38: Estudio Madero (FICTICIO) | F38: Cortes premium | G38: 4 | H38: 106571 | I38: 0.21 | J38: =ROUND(H38*I38,2) -> 22379.91 | K38: =ROUND(H38+J38,2) -> 128950.91 | L38: Efectivo
A39: 46060 | B39: Factura B | C39: 0001-00002035 | D39: Consumidor final | F39: Bebidas y cubiertos | G39: 5 | H39: 119517 | I39: 0.21 | J39: =ROUND(H39*I39,2) -> 25098.57 | K39: =ROUND(H39+J39,2) -> 144615.57 | L39: Transferencia
A40: 46061 | B40: Factura B | C40: 0001-00002036 | D40: Consumidor final | F40: Parrilla y cortes | G40: 6 | H40: 42462 | I40: 0.21 | J40: =ROUND(H40*I40,2) -> 8917.02 | K40: =ROUND(H40+J40,2) -> 51379.02 | L40: Tarjeta de débito
A41: 46062 | B41: Factura B | C41: 0001-00002037 | D41: Consumidor final | F41: Menú ejecutivo | G41: 1 | H41: 55408 | I41: 0.21 | J41: =ROUND(H41*I41,2) -> 11635.68 | K41: =ROUND(H41+J41,2) -> 67043.68 | L41: Mercado Pago
A42: 46063 | B42: Factura B | C42: 0001-00002038 | D42: Consumidor final | F42: Cortes premium | G42: 2 | H42: 68354 | I42: 0.21 | J42: =ROUND(H42*I42,2) -> 14354.34 | K42: =ROUND(H42+J42,2) -> 82708.34 | L42: Tarjeta de crédito
A43: 46064 | B43: Factura B | C43: 0001-00002039 | D43: Empresa de Eventos Sur (FICTICIA) | F43: Bebidas y cubiertos | G43: 3 | H43: 81300 | I43: 0.21 | J43: =ROUND(H43*I43,2) -> 17073 | K43: =ROUND(H43+J43,2) -> 98373 | L43: Efectivo
A44: 46065 | B44: Factura B | C44: 0001-00002040 | D44: Consumidor final | F44: Parrilla y cortes | G44: 4 | H44: 94246 | I44: 0.21 | J44: =ROUND(H44*I44,2) -> 19791.66 | K44: =ROUND(H44+J44,2) -> 114037.66 | L44: Transferencia
A45: 46066 | B45: Factura A | C45: 0001-00002041 | D45: Agencia Costera (FICTICIA) | E45: 30-70061387-4 | F45: Menú ejecutivo | G45: 5 | H45: 107192 | I45: 0.21 | J45: =ROUND(H45*I45,2) -> 22510.32 | K45: =ROUND(H45+J45,2) -> 129702.32 | L45: Tarjeta de débito
A46: 46067 | B46: Factura B | C46: 0001-00002042 | D46: Consumidor final | F46: Cortes premium | G46: 6 | H46: 120138 | I46: 0.21 | J46: =ROUND(H46*I46,2) -> 25228.98 | K46: =ROUND(H46+J46,2) -> 145366.98 | L46: Mercado Pago
A47: 46068 | B47: Factura B | C47: 0001-00002043 | D47: Hotel Dársena (FICTICIO) | F47: Bebidas y cubiertos | G47: 1 | H47: 43083 | I47: 0.21 | J47: =ROUND(H47*I47,2) -> 9047.43 | K47: =ROUND(H47+J47,2) -> 52130.43 | L47: Tarjeta de crédito
A48: 46069 | B48: Factura B | C48: 0001-00002044 | D48: Consumidor final | F48: Parrilla y cortes | G48: 2 | H48: 56029 | I48: 0.21 | J48: =ROUND(H48*I48,2) -> 11766.09 | K48: =ROUND(H48+J48,2) -> 67795.09 | L48: Efectivo
A49: 46070 | B49: Factura B | C49: 0001-00002045 | D49: Consultora Río (FICTICIA) | F49: Menú ejecutivo | G49: 3 | H49: 68975 | I49: 0.21 | J49: =ROUND(H49*I49,2) -> 14484.75 | K49: =ROUND(H49+J49,2) -> 83459.75 | L49: Transferencia
A50: 46071 | B50: Factura B | C50: 0001-00002046 | D50: Estudio Madero (FICTICIO) | F50: Cortes premium | G50: 4 | H50: 81921 | I50: 0.21 | J50: =ROUND(H50*I50,2) -> 17203.41 | K50: =ROUND(H50+J50,2) -> 99124.41 | L50: Tarjeta de débito
A51: 46072 | B51: Factura B | C51: 0001-00002047 | D51: Consumidor final | F51: Bebidas y cubiertos | G51: 5 | H51: 94867 | I51: 0.21 | J51: =ROUND(H51*I51,2) -> 19922.07 | K51: =ROUND(H51+J51,2) -> 114789.07 | L51: Mercado Pago
A52: 46073 | B52: Factura B | C52: 0001-00002048 | D52: Consumidor final | F52: Parrilla y cortes | G52: 6 | H52: 107813 | I52: 0.21 | J52: =ROUND(H52*I52,2) -> 22640.73 | K52: =ROUND(H52+J52,2) -> 130453.73 | L52: Tarjeta de crédito
A53: 46074 | B53: Factura B | C53: 0001-00002049 | D53: Consumidor final | F53: Menú ejecutivo | G53: 1 | H53: 120759 | I53: 0.21 | J53: =ROUND(H53*I53,2) -> 25359.39 | K53: =ROUND(H53+J53,2) -> 146118.39 | L53: Efectivo
A54: 46075 | B54: Factura B | C54: 0001-00002050 | D54: Consumidor final | F54: Cortes premium | G54: 2 | H54: 43704 | I54: 0.21 | J54: =ROUND(H54*I54,2) -> 9177.84 | K54: =ROUND(H54+J54,2) -> 52881.84 | L54: Transferencia
A55: 46076 | B55: Factura A | C55: 0001-00002051 | D55: Empresa de Eventos Sur (FICTICIA) | E55: 30-70063597-6 | F55: Bebidas y cubiertos | G55: 3 | H55: 56650 | I55: 0.21 | J55: =ROUND(H55*I55,2) -> 11896.5 | K55: =ROUND(H55+J55,2) -> 68546.5 | L55: Tarjeta de débito
A56: 46077 | B56: Factura B | C56: 0001-00002052 | D56: Consumidor final | F56: Parrilla y cortes | G56: 4 | H56: 69596 | I56: 0.21 | J56: =ROUND(H56*I56,2) -> 14615.16 | K56: =ROUND(H56+J56,2) -> 84211.16 | L56: Mercado Pago
A57: 46078 | B57: Factura B | C57: 0001-00002053 | D57: Agencia Costera (FICTICIA) | F57: Menú ejecutivo | G57: 5 | H57: 82542 | I57: 0.21 | J57: =ROUND(H57*I57,2) -> 17333.82 | K57: =ROUND(H57+J57,2) -> 99875.82 | L57: Tarjeta de crédito
A58: 46079 | B58: Factura B | C58: 0001-00002054 | D58: Consumidor final | F58: Cortes premium | G58: 6 | H58: 95488 | I58: 0.21 | J58: =ROUND(H58*I58,2) -> 20052.48 | K58: =ROUND(H58+J58,2) -> 115540.48 | L58: Efectivo

Sheet Febrero Gastos
A1: COSTANERA GRILL · FEBRERO 2026 · REGISTRO DE COMPRAS Y GASTOS (SIMULACIÓN)
A2: Proveedores y comprobantes ficticios. Alícuotas ilustrativas; verificar normativa aplicable en un caso real.
A4: Fecha | B4: Proveedor | C4: CUIT proveedor (ficticio) | D4: Tipo comprobante | E4: Categoría | F4: Detalle | G4: Neto gravado | H4: Alícuota IVA | I4: IVA crédito | J4: Total | K4: Medio de pago
A5: 46055 | B5: Frigorífico La Pampa (FICTICIO) | C5: 30-70123456-1 | D5: Factura A | E5: Carne | F5: Compra de carne para operación | G5: 1350447 | H5: 0.105 | I5: =ROUND(G5*H5,2) -> 141796.94 | J5: =ROUND(G5+I5,2) -> 1492243.9 | K5: Tarjeta de débito
A6: 46058 | B6: Carnes del Sur (FICTICIO) | C6: 30-70987654-2 | D6: Factura B | E6: Carne | F6: Compra de carne para operación | G6: 759444 | H6: 0.105 | I6: =ROUND(G6*H6,2) -> 79741.62 | J6: =ROUND(G6+I6,2) -> 839185.62 | K6: Tarjeta de crédito
A7: 46061 | B7: Bebidas Río (FICTICIO) | C7: 30-71234567-3 | D7: Factura B | E7: Bebidas | F7: Compra de bebidas para operación | G7: 537738 | H7: 0.21 | I7: =ROUND(G7*H7,2) -> 112924.98 | J7: =ROUND(G7+I7,2) -> 650662.98 | K7: Transferencia
A8: 46064 | B8: Distribuidora Malbec (FICTICIO) | C8: 30-72345678-4 | D8: Factura A | E8: Bebidas | F8: Compra de bebidas para operación | G8: 367071 | H8: 0.21 | I8: =ROUND(G8*H8,2) -> 77084.91 | J8: =ROUND(G8+I8,2) -> 444155.91 | K8: Mercado Pago
A9: 46067 | B9: Edenor - ejemplo didáctico | C9: 30-54567891-2 | D9: Factura B | E9: Electricidad | F9: Compra de electricidad para operación | G9: 595367 | H9: 0.21 | I9: =ROUND(G9*H9,2) -> 125027.07 | J9: =ROUND(G9+I9,2) -> 720394.07 | K9: Efectivo
A10: 46070 | B10: Metrogas - ejemplo didáctico | C10: 30-65789123-4 | D10: Factura B | E10: Gas | F10: Compra de gas para operación | G10: 510806 | H10: 0.21 | I10: =ROUND(G10*H10,2) -> 107269.26 | J10: =ROUND(G10+I10,2) -> 618075.26 | K10: Tarjeta de débito
A11: 46073 | B11: Fibra Puerto (FICTICIO) | C11: 30-67891234-5 | D11: Factura A | E11: Internet | F11: Compra de internet para operación | G11: 136995 | H11: 0.21 | I11: =ROUND(G11*H11,2) -> 28768.95 | J11: =ROUND(G11+I11,2) -> 165763.95 | K11: Tarjeta de crédito
A12: 46076 | B12: Limpieza del Puerto (FICTICIO) | C12: 30-68912345-6 | D12: Factura B | E12: Limpieza | F12: Compra de limpieza para operación | G12: 238526 | H12: 0.21 | I12: =ROUND(G12*H12,2) -> 50090.46 | J12: =ROUND(G12+I12,2) -> 288616.46 | K12: Transferencia
A13: 46079 | B13: Envases del Plata (FICTICIO) | C13: 30-69123456-7 | D13: Factura B | E13: Insumos | F13: Compra de insumos para operación | G13: 191636 | H13: 0.21 | I13: =ROUND(G13*H13,2) -> 40243.56 | J13: =ROUND(G13+I13,2) -> 231879.56 | K13: Mercado Pago
A14: 46055 | B14: Alquiler local Puerto Madero (FICTICIO) | C14: 30-61234567-8 | D14: Factura A | E14: Alquiler | F14: Compra de alquiler para operación | G14: 643802 | H14: 0.21 | I14: =ROUND(G14*H14,2) -> 135198.42 | J14: =ROUND(G14+I14,2) -> 779000.42 | K14: Efectivo
A15: 46058 | B15: Mantenimiento Parrillero (FICTICIO) | C15: 30-63456789-1 | D15: Factura B | E15: Mantenimiento | F15: Compra de mantenimiento para operación | G15: 253233 | H15: 0.21 | I15: =ROUND(G15*H15,2) -> 53178.93 | J15: =ROUND(G15+I15,2) -> 306411.93 | K15: Tarjeta de débito
A16: 46061 | B16: Panificados del Puerto (FICTICIO) | C16: 30-64567891-3 | D16: Factura B | E16: Alimentos | F16: Compra de alimentos para operación | G16: 208345 | H16: 0.21 | I16: =ROUND(G16*H16,2) -> 43752.45 | J16: =ROUND(G16+I16,2) -> 252097.45 | K16: Tarjeta de crédito
... A22: 46079 | B22: Papelería Administrativa (FICTICIO) | C22: 30-61234578-9 | D22: Factura B | E22: Administración | F22: Compra de administración para operación | G22: 141112 | H22: 0.21 | I22: =ROUND(G22*H22,2) -> 29633.52 | J22: =ROUND(G22+I22,2) -> 170745.52 | K22: Transferencia

Sheet Marzo Ventas
A1: COSTANERA GRILL · MARZO 2026 · REGISTRO DE VENTAS (SIMULACIÓN)
A2: Datos inventados para ejercicio de capacitación. Sin validez fiscal ni contable. IVA calculado con fórmula sobre base imponible.
A4: Fecha | B4: Tipo comprobante | C4: Número | D4: Cliente | E4: CUIT cliente (ficticio) | F4: Concepto | G4: Cantidad | H4: Neto gravado | I4: Alícuota IVA | J4: IVA débito | K4: Total | L4: Medio de cobro
A5: 46082 | B5: Factura A | C5: 0001-00003001 | D5: Consumidor final | E5: 30-70054094-7 | F5: Cortes premium | G5: 1 | H5: 129979 | I5: 0.21 | J5: =ROUND(H5*I5,2) -> 27295.59 | K5: =ROUND(H5+J5,2) -> 157274.59 | L5: Tarjeta de crédito
A6: 46083 | B6: Factura B | C6: 0001-00003002 | D6: Consultora Río (FICTICIA) | F6: Bebidas y cubiertos | G6: 2 | H6: 52924 | I6: 0.21 | J6: =ROUND(H6*I6,2) -> 11114.04 | K6: =ROUND(H6+J6,2) -> 64038.04 | L6: Efectivo
A7: 46084 | B7: Factura B | C7: 0001-00003003 | D7: Estudio Madero (FICTICIO) | F7: Parrilla y cortes | G7: 3 | H7: 65870 | I7: 0.21 | J7: =ROUND(H7*I7,2) -> 13832.7 | K7: =ROUND(H7+J7,2) -> 79702.7 | L7: Transferencia
A8: 46085 | B8: Factura B | C8: 0001-00003004 | D8: Consumidor final | F8: Menú ejecutivo | G8: 4 | H8: 78816 | I8: 0.21 | J8: =ROUND(H8*I8,2) -> 16551.36 | K8: =ROUND(H8+J8,2) -> 95367.36 | L8: Tarjeta de débito
A9: 46086 | B9: Factura B | C9: 0001-00003005 | D9: Consumidor final | F9: Cortes premium | G9: 5 | H9: 91762 | I9: 0.21 | J9: =ROUND(H9*I9,2) -> 19270.02 | K9: =ROUND(H9+J9,2) -> 111032.02 | L9: Mercado Pago
A10: 46087 | B10: Factura B | C10: 0001-00003006 | D10: Consumidor final | F10: Bebidas y cubiertos | G10: 6 | H10: 104708 | I10: 0.21 | J10: =ROUND(H10*I10,2) -> 21988.68 | K10: =ROUND(H10+J10,2) -> 126696.68 | L10: Tarjeta de crédito
A11: 46088 | B11: Factura B | C11: 0001-00003007 | D11: Consumidor final | F11: Parrilla y cortes | G11: 1 | H11: 117654 | I11: 0.21 | J11: =ROUND(H11*I11,2) -> 24707.34 | K11: =ROUND(H11+J11,2) -> 142361.34 | L11: Efectivo
A12: 46089 | B12: Factura B | C12: 0001-00003008 | D12: Empresa de Eventos Sur (FICTICIA) | F12: Menú ejecutivo | G12: 2 | H12: 130600 | I12: 0.21 | J12: =ROUND(H12*I12,2) -> 27426 | K12: =ROUND(H12+J12,2) -> 158026 | L12: Transferencia
A13: 46090 | B13: Factura B | C13: 0001-00003009 | D13: Consumidor final | F13: Cortes premium | G13: 3 | H13: 53545 | I13: 0.21 | J13: =ROUND(H13*I13,2) -> 11244.45 | K13: =ROUND(H13+J13,2) -> 64789.45 | L13: Tarjeta de débito
A14: 46091 | B14: Factura B | C14: 0001-00003010 | D14: Agencia Costera (FICTICIA) | F14: Bebidas y cubiertos | G14: 4 | H14: 66491 | I14: 0.21 | J14: =ROUND(H14*I14,2) -> 13963.11 | K14: =ROUND(H14+J14,2) -> 80454.11 | L14: Mercado Pago
A15: 46092 | B15: Factura A | C15: 0001-00003011 | D15: Consumidor final | E15: 30-70056304-1 | F15: Parrilla y cortes | G15: 5 | H15: 79437 | I15: 0.21 | J15: =ROUND(H15*I15,2) -> 16681.77 | K15: =ROUND(H15+J15,2) -> 96118.77 | L15: Tarjeta de crédito
A16: 46093 | B16: Factura B | C16: 0001-00003012 | D16: Hotel Dársena (FICTICIO) | F16: Menú ejecutivo | G16: 6 | H16: 92383 | I16: 0.21 | J16: =ROUND(H16*I16,2) -> 19400.43 | K16: =ROUND(H16+J16,2) -> 111783.43 | L16: Efectivo
A17: 46094 | B17: Factura B | C17: 0001-00003013 | D17: Consumidor final | F17: Cortes premium | G17: 1 | H17: 105329 | I17: 0.21 | J17: =ROUND(H17*I17,2) -> 22119.09 | K17: =ROUND(H17+J17,2) -> 127448.09 | L17: Transferencia
A18: 46095 | B18: Factura B | C18: 0001-00003014 | D18: Consultora Río (FICTICIA) | F18: Bebidas y cubiertos | G18: 2 | H18: 118275 | I18: 0.21 | J18: =ROUND(H18*I18,2) -> 24837.75 | K18: =ROUND(H18+J18,2) -> 143112.75 | L18: Tarjeta de débito
A19: 46096 | B19: Factura B | C19: 0001-00003015 | D19: Estudio Madero (FICTICIO) | F19: Parrilla y cortes | G19: 3 | H19: 131221 | I19: 0.21 | J19: =ROUND(H19*I19,2) -> 27556.41 | K19: =ROUND(H19+J19,2) -> 158777.41 | L19: Mercado Pago
A20: 46097 | B20: Factura B | C20: 0001-00003016 | D20: Consumidor final | F20: Menú ejecutivo | G20: 4 | H20: 54166 | I20: 0.21 | J20: =ROUND(H20*I20,2) -> 11374.86 | K20: =ROUND(H20+J20,2) -> 65540.86 | L20: Tarjeta de crédito
A21: 46098 | B21: Factura B | C21: 0001-00003017 | D21: Consumidor final | F21: Cortes premium | G21: 5 | H21: 67112 | I21: 0.21 | J21: =ROUND(H21*I21,2) -> 14093.52 | K21: =ROUND(H21+J21,2) -> 81205.52 | L21: Efectivo
A22: 46099 | B22: Factura B | C22: 0001-00003018 | D22: Consumidor final | F22: Bebidas y cubiertos | G22: 6 | H22: 80058 | I22: 0.21 | J22: =ROUND(H22*I22,2) -> 16812.18 | K22: =ROUND(H22+J22,2) -> 96870.18 | L22: Transferencia
A23: 46100 | B23: Factura B | C23: 0001-00003019 | D23: Consumidor final | F23: Parrilla y cortes | G23: 1 | H23: 93004 | I23: 0.21 | J23: =ROUND(H23*I23,2) -> 19530.84 | K23: =ROUND(H23+J23,2) -> 112534.84 | L23: Tarjeta de débito
A24: 46101 | B24: Factura B | C24: 0001-00003020 | D24: Empresa de Eventos Sur (FICTICIA) | F24: Menú ejecutivo | G24: 2 | H24: 105950 | I24: 0.21 | J24: =ROUND(H24*I24,2) -> 22249.5 | K24: =ROUND(H24+J24,2) -> 128199.5 | L24: Mercado Pago
A25: 46102 | B25: Factura A | C25: 0001-00003021 | D25: Consumidor final | E25: 30-70058514-3 | F25: Cortes premium | G25: 3 | H25: 118896 | I25: 0.21 | J25: =ROUND(H25*I25,2) -> 24968.16 | K25: =ROUND(H25+J25,2) -> 143864.16 | L25: Tarjeta de crédito
A26: 46103 | B26: Factura B | C26: 0001-00003022 | D26: Agencia Costera (FICTICIA) | F26: Bebidas y cubiertos | G26: 4 | H26: 131842 | I26: 0.21 | J26: =ROUND(H26*I26,2) -> 27686.82 | K26: =ROUND(H26+J26,2) -> 159528.82 | L26: Efectivo
A27: 46104 | B27: Factura B | C27: 0001-00003023 | D27: Consumidor final | F27: Parrilla y cortes | G27: 5 | H27: 54787 | I27: 0.21 | J27: =ROUND(H27*I27,2) -> 11505.27 | K27: =ROUND(H27+J27,2) -> 66292.27 | L27: Transferencia
A28: 46105 | B28: Factura B | C28: 0001-00003024 | D28: Hotel Dársena (FICTICIO) | F28: Menú ejecutivo | G28: 6 | H28: 67733 | I28: 0.21 | J28: =ROUND(H28*I28,2) -> 14223.93 | K28: =ROUND(H28+J28,2) -> 81956.93 | L28: Tarjeta de débito
A29: 46106 | B29: Factura B | C29: 0001-00003025 | D29: Consumidor final | F29: Cortes premium | G29: 1 | H29: 80679 | I29: 0.21 | J29: =ROUND(H29*I29,2) -> 16942.59 | K29: =ROUND(H29+J29,2) -> 97621.59 | L29: Mercado Pago
A30: 46107 | B30: Factura B | C30: 0001-00003026 | D30: Consultora Río (FICTICIA) | F30: Bebidas y cubiertos | G30: 2 | H30: 93625 | I30: 0.21 | J30: =ROUND(H30*I30,2) -> 19661.25 | K30: =ROUND(H30+J30,2) -> 113286.25 | L30: Tarjeta de crédito
A31: 46108 | B31: Factura B | C31: 0001-00003027 | D31: Estudio Madero (FICTICIO) | F31: Parrilla y cortes | G31: 3 | H31: 106571 | I31: 0.21 | J31: =ROUND(H31*I31,2) -> 22379.91 | K31: =ROUND(H31+J31,2) -> 128950.91 | L31: Efectivo
A32: 46109 | B32: Factura B | C32: 0001-00003028 | D32: Consumidor final | F32: Menú ejecutivo | G32: 4 | H32: 119517 | I32: 0.21 | J32: =ROUND(H32*I32,2) -> 25098.57 | K32: =ROUND(H32+J32,2) -> 144615.57 | L32: Transferencia
A33: 46082 | B33: Factura B | C33: 0001-00003029 | D33: Consumidor final | F33: Cortes premium | G33: 5 | H33: 42462 | I33: 0.21 | J33: =ROUND(H33*I33,2) -> 8917.02 | K33: =ROUND(H33+J33,2) -> 51379.02 | L33: Tarjeta de débito
A34: 46083 | B34: Factura B | C34: 0001-00003030 | D34: Consumidor final | F34: Bebidas y cubiertos | G34: 6 | H34: 55408 | I34: 0.21 | J34: =ROUND(H34*I34,2) -> 11635.68 | K34: =ROUND(H34+J34,2) -> 67043.68 | L34: Mercado Pago
A35: 46084 | B35: Factura A | C35: 0001-00003031 | D35: Consumidor final | E35: 30-70060724-5 | F35: Parrilla y cortes | G35: 1 | H35: 68354 | I35: 0.21 | J35: =ROUND(H35*I35,2) -> 14354.34 | K35: =ROUND(H35+J35,2) -> 82708.34 | L35: Tarjeta de crédito
A36: 46085 | B36: Factura B | C36: 0001-00003032 | D36: Empresa de Eventos Sur (FICTICIA) | F36: Menú ejecutivo | G36: 2 | H36: 81300 | I36: 0.21 | J36: =ROUND(H36*I36,2) -> 17073 | K36: =ROUND(H36+J36,2) -> 98373 | L36: Efectivo
A37: 46086 | B37: Factura B | C37: 0001-00003033 | D37: Consumidor final | F37: Cortes premium | G37: 3 | H37: 94246 | I37: 0.21 | J37: =ROUND(H37*I37,2) -> 19791.66 | K37: =ROUND(H37+J37,2) -> 114037.66 | L37: Transferencia
A38: 46087 | B38: Factura B | C38: 0001-00003034 | D38: Agencia Costera (FICTICIA) | F38: Bebidas y cubiertos | G38: 4 | H38: 107192 | I38: 0.21 | J38: =ROUND(H38*I38,2) -> 22510.32 | K38: =ROUND(H38+J38,2) -> 129702.32 | L38: Tarjeta de débito
A39: 46088 | B39: Factura B | C39: 0001-00003035 | D39: Consumidor final | F39: Parrilla y cortes | G39: 5 | H39: 120138 | I39: 0.21 | J39: =ROUND(H39*I39,2) -> 25228.98 | K39: =ROUND(H39+J39,2) -> 145366.98 | L39: Mercado Pago
A40: 46089 | B40: Factura B | C40: 0001-00003036 | D40: Hotel Dársena (FICTICIO) | F40: Menú ejecutivo | G40: 6 | H40: 43083 | I40: 0.21 | J40: =ROUND(H40*I40,2) -> 9047.43 | K40: =ROUND(H40+J40,2) -> 52130.43 | L40: Tarjeta de crédito
A41: 46090 | B41: Factura B | C41: 0001-00003037 | D41: Consumidor final | F41: Cortes premium | G41: 1 | H41: 56029 | I41: 0.21 | J41: =ROUND(H41*I41,2) -> 11766.09 | K41: =ROUND(H41+J41,2) -> 67795.09 | L41: Efectivo
A42: 46091 | B42: Factura B | C42: 0001-00003038 | D42: Consultora Río (FICTICIA) | F42: Bebidas y cubiertos | G42: 2 | H42: 68975 | I42: 0.21 | J42: =ROUND(H42*I42,2) -> 14484.75 | K42: =ROUND(H42+J42,2) -> 83459.75 | L42: Transferencia
A43: 46092 | B43: Factura B | C43: 0001-00003039 | D43: Estudio Madero (FICTICIO) | F43: Parrilla y cortes | G43: 3 | H43: 81921 | I43: 0.21 | J43: =ROUND(H43*I43,2) -> 17203.41 | K43: =ROUND(H43+J43,2) -> 99124.41 | L43: Tarjeta de débito
A44: 46093 | B44: Factura B | C44: 0001-00003040 | D44: Consumidor final | F44: Menú ejecutivo | G44: 4 | H44: 94867 | I44: 0.21 | J44: =ROUND(H44*I44,2) -> 19922.07 | K44: =ROUND(H44+J44,2) -> 114789.07 | L44: Mercado Pago
A45: 46094 | B45: Factura A | C45: 0001-00003041 | D45: Consumidor final | E45: 30-70062934-7 | F45: Cortes premium | G45: 5 | H45: 107813 | I45: 0.21 | J45: =ROUND(H45*I45,2) -> 22640.73 | K45: =ROUND(H45+J45,2) -> 130453.73 | L45: Tarjeta de crédito
A46: 46095 | B46: Factura B | C46: 0001-00003042 | D46: Consumidor final | F46: Bebidas y cubiertos | G46: 6 | H46: 120759 | I46: 0.21 | J46: =ROUND(H46*I46,2) -> 25359.39 | K46: =ROUND(H46+J46,2) -> 146118.39 | L46: Efectivo
A47: 46096 | B47: Factura B | C47: 0001-00003043 | D47: Consumidor final | F47: Parrilla y cortes | G47: 1 | H47: 43704 | I47: 0.21 | J47: =ROUND(H47*I47,2) -> 9177.84 | K47: =ROUND(H47+J47,2) -> 52881.84 | L47: Transferencia
A48: 46097 | B48: Factura B | C48: 0001-00003044 | D48: Empresa de Eventos Sur (FICTICIA) | F48: Menú ejecutivo | G48: 2 | H48: 56650 | I48: 0.21 | J48: =ROUND(H48*I48,2) -> 11896.5 | K48: =ROUND(H48+J48,2) -> 68546.5 | L48: Tarjeta de débito
A49: 46098 | B49: Factura B | C49: 0001-00003045 | D49: Consumidor final | F49: Cortes premium | G49: 3 | H49: 69596 | I49: 0.21 | J49: =ROUND(H49*I49,2) -> 14615.16 | K49: =ROUND(H49+J49,2) -> 84211.16 | L49: Mercado Pago
A50: 46099 | B50: Factura B | C50: 0001-00003046 | D50: Agencia Costera (FICTICIA) | F50: Bebidas y cubiertos | G50: 4 | H50: 82542 | I50: 0.21 | J50: =ROUND(H50*I50,2) -> 17333.82 | K50: =ROUND(H50+J50,2) -> 99875.82 | L50: Tarjeta de crédito
A51: 46100 | B51: Factura B | C51: 0001-00003047 | D51: Consumidor final | F51: Parrilla y cortes | G51: 5 | H51: 95488 | I51: 0.21 | J51: =ROUND(H51*I51,2) -> 20052.48 | K51: =ROUND(H51+J51,2) -> 115540.48 | L51: Efectivo
A52: 46101 | B52: Factura B | C52: 0001-00003048 | D52: Hotel Dársena (FICTICIO) | F52: Menú ejecutivo | G52: 6 | H52: 108434 | I52: 0.21 | J52: =ROUND(H52*I52,2) -> 22771.14 | K52: =ROUND(H52+J52,2) -> 131205.14 | L52: Transferencia
A53: 46102 | B53: Factura B | C53: 0001-00003049 | D53: Consumidor final | F53: Cortes premium | G53: 1 | H53: 121380 | I53: 0.21 | J53: =ROUND(H53*I53,2) -> 25489.8 | K53: =ROUND(H53+J53,2) -> 146869.8 | L53: Tarjeta de débito
A54: 46103 | B54: Factura B | C54: 0001-00003050 | D54: Consultora Río (FICTICIA) | F54: Bebidas y cubiertos | G54: 2 | H54: 44325 | I54: 0.21 | J54: =ROUND(H54*I54,2) -> 9308.25 | K54: =ROUND(H54+J54,2) -> 53633.25 | L54: Mercado Pago
A55: 46104 | B55: Factura A | C55: 0001-00003051 | D55: Estudio Madero (FICTICIO) | E55: 30-70065144-1 | F55: Parrilla y cortes | G55: 3 | H55: 57271 | I55: 0.21 | J55: =ROUND(H55*I55,2) -> 12026.91 | K55: =ROUND(H55+J55,2) -> 69297.91 | L55: Tarjeta de crédito
A56: 46105 | B56: Factura B | C56: 0001-00003052 | D56: Consumidor final | F56: Menú ejecutivo | G56: 4 | H56: 70217 | I56: 0.21 | J56: =ROUND(H56*I56,2) -> 14745.57 | K56: =ROUND(H56+J56,2) -> 84962.57 | L56: Efectivo
A57: 46106 | B57: Factura B | C57: 0001-00003053 | D57: Consumidor final | F57: Cortes premium | G57: 5 | H57: 83163 | I57: 0.21 | J57: =ROUND(H57*I57,2) -> 17464.23 | K57: =ROUND(H57+J57,2) -> 100627.23 | L57: Transferencia
A58: 46107 | B58: Factura B | C58: 0001-00003054 | D58: Consumidor final | F58: Bebidas y cubiertos | G58: 6 | H58: 96109 | I58: 0.21 | J58: =ROUND(H58*I58,2) -> 20182.89 | K58: =ROUND(H58+J58,2) -> 116291.89 | L58: Tarjeta de débito

Sheet Marzo Gastos
A1: COSTANERA GRILL · MARZO 2026 · REGISTRO DE COMPRAS Y GASTOS (SIMULACIÓN)
A2: Proveedores y comprobantes ficticios. Alícuotas ilustrativas; verificar normativa aplicable en un caso real.
A4: Fecha | B4: Proveedor | C4: CUIT proveedor (ficticio) | D4: Tipo comprobante | E4: Categoría | F4: Detalle | G4: Neto gravado | H4: Alícuota IVA | I4: IVA crédito | J4: Total | K4: Medio de pago
A5: 46083 | B5: Frigorífico La Pampa (FICTICIO) | C5: 30-70123456-1 | D5: Factura A | E5: Carne | F5: Compra de carne para operación | G5: 220275 | H5: 0.105 | I5: =ROUND(G5*H5,2) -> 23128.88 | J5: =ROUND(G5+I5,2) -> 243403.88 | K5: Tarjeta de crédito
A6: 46086 | B6: Carnes del Sur (FICTICIO) | C6: 30-70987654-2 | D6: Factura B | E6: Carne | F6: Compra de carne para operación | G6: 179953 | H6: 0.105 | I6: =ROUND(G6*H6,2) -> 18895.07 | J6: =ROUND(G6+I6,2) -> 198848.07 | K6: Transferencia
A7: 46089 | B7: Bebidas Río (FICTICIO) | C7: 30-71234567-3 | D7: Factura B | E7: Bebidas | F7: Compra de bebidas para operación | G7: 79186 | H7: 0.21 | I7: =ROUND(G7*H7,2) -> 16629.06 | J7: =ROUND(G7+I7,2) -> 95815.06 | K7: Mercado Pago
A8: 46092 | B8: Distribuidora Malbec (FICTICIO) | C8: 30-72345678-4 | D8: Factura A | E8: Bebidas | F8: Compra de bebidas para operación | G8: 61656 | H8: 0.21 | I8: =ROUND(G8*H8,2) -> 12947.76 | J8: =ROUND(G8+I8,2) -> 74603.76 | K8: Efectivo
A9: 46095 | B9: Edenor - ejemplo didáctico | C9: 30-54567891-2 | D9: Factura B | E9: Electricidad | F9: Compra de electricidad para operación | G9: 88481 | H9: 0.21 | I9: =ROUND(G9*H9,2) -> 18581.01 | J9: =ROUND(G9+I9,2) -> 107062.01 | K9: Tarjeta de débito
A10: 46098 | B10: Metrogas - ejemplo didáctico | C10: 30-65789123-4 | D10: Factura B | E10: Gas | F10: Compra de gas para operación | G10: 84837 | H10: 0.21 | I10: =ROUND(G10*H10,2) -> 17815.77 | J10: =ROUND(G10+I10,2) -> 102652.77 | K10: Tarjeta de crédito
A11: 46101 | B11: Fibra Puerto (FICTICIO) | C11: 30-67891234-5 | D11: Factura A | E11: Internet | F11: Compra de internet para operación | G11: 28475 | H11: 0.21 | I11: =ROUND(G11*H11,2) -> 5979.75 | J11: =ROUND(G11+I11,2) -> 34454.75 | K11: Transferencia
A12: 46104 | B12: Limpieza del Puerto (FICTICIO) | C12: 30-68912345-6 | D12: Factura B | E12: Limpieza | F12: Compra de limpieza para operación | G12: 26899 | H12: 0.21 | I12: =ROUND(G12*H12,2) -> 5648.79 | J12: =ROUND(G12+I12,2) -> 32547.79 | K12: Mercado Pago
A13: 46107 | B13: Envases del Plata (FICTICIO) | C13: 30-69123456-7 | D13: Factura B | E13: Insumos | F13: Compra de insumos para operación | G13: 51351 | H13: 0.21 | I13: =ROUND(G13*H13,2) -> 10783.71 | J13: =ROUND(G13+I13,2) -> 62134.71 | K13: Efectivo
A14: 46083 | B14: Alquiler local Puerto Madero (FICTICIO) | C14: 30-61234567-8 | D14: Factura A | E14: Alquiler | F14: Compra de alquiler para operación | G14: 126286 | H14: 0.21 | I14: =ROUND(G14*H14,2) -> 26520.06 | J14: =ROUND(G14+I14,2) -> 152806.06 | K14: Tarjeta de débito
A15: 46086 | B15: Mantenimiento Parrillero (FICTICIO) | C15: 30-63456789-1 | D15: Factura B | E15: Mantenimiento | F15: Compra de mantenimiento para operación | G15: 33279 | H15: 0.21 | I15: =ROUND(G15*H15,2) -> 6988.59 | J15: =ROUND(G15+I15,2) -> 40267.59 | K15: Tarjeta de crédito
A16: 46089 | B16: Panificados del Puerto (FICTICIO) | C16: 30-64567891-3 | D16: Factura B | E16: Alimentos | F16: Compra de alimentos para operación | G16: 61042 | H16: 0.21 | I16: =ROUND(G16*H16,2) -> 12818.82 | J16: =ROUND(G16+I16,2) -> 73860.82 | K16: Transferencia
... A22: 46107 | B22: Papelería Administrativa (FICTICIO) | C22: 30-61234578-9 | D22: Factura B | E22: Administración | F22: Compra de administración para operación | G22: 17150 | H22: 0.21 | I22: =ROUND(G22*H22,2) -> 3601.5 | J22: =ROUND(G22+I22,2) -> 20751.5 | K22: Mercado Pago

Sheet Abril Ventas
A1: COSTANERA GRILL · ABRIL 2026 · REGISTRO DE VENTAS (SIMULACIÓN)
A2: Datos inventados para ejercicio de capacitación. Sin validez fiscal ni contable. IVA calculado con fórmula sobre base imponible.
A4: Fecha | B4: Tipo comprobante | C4: Número | D4: Cliente | E4: CUIT cliente (ficticio) | F4: Concepto | G4: Cantidad | H4: Neto gravado | I4: Alícuota IVA | J4: IVA débito | K4: Total | L4: Medio de cobro
A5: 46113 | B5: Factura A | C5: 0001-00004001 | D5: Empresa de Eventos Sur (FICTICIA) | E5: 30-70055641-2 | F5: Bebidas y cubiertos | G5: 1 | H5: 130600 | I5: 0.21 | J5: =ROUND(H5*I5,2) -> 27426 | K5: =ROUND(H5+J5,2) -> 158026 | L5: Transferencia
A6: 46114 | B6: Factura B | C6: 0001-00004002 | D6: Consumidor final | F6: Parrilla y cortes | G6: 2 | H6: 53545 | I6: 0.21 | J6: =ROUND(H6*I6,2) -> 11244.45 | K6: =ROUND(H6+J6,2) -> 64789.45 | L6: Tarjeta de débito
A7: 46115 | B7: Factura B | C7: 0001-00004003 | D7: Agencia Costera (FICTICIA) | F7: Menú ejecutivo | G7: 3 | H7: 66491 | I7: 0.21 | J7: =ROUND(H7*I7,2) -> 13963.11 | K7: =ROUND(H7+J7,2) -> 80454.11 | L7: Mercado Pago
A8: 46116 | B8: Factura B | C8: 0001-00004004 | D8: Consumidor final | F8: Cortes premium | G8: 4 | H8: 79437 | I8: 0.21 | J8: =ROUND(H8*I8,2) -> 16681.77 | K8: =ROUND(H8+J8,2) -> 96118.77 | L8: Tarjeta de crédito
A9: 46117 | B9: Factura B | C9: 0001-00004005 | D9: Hotel Dársena (FICTICIO) | F9: Bebidas y cubiertos | G9: 5 | H9: 92383 | I9: 0.21 | J9: =ROUND(H9*I9,2) -> 19400.43 | K9: =ROUND(H9+J9,2) -> 111783.43 | L9: Efectivo
A10: 46118 | B10: Factura B | C10: 0001-00004006 | D10: Consumidor final | F10: Parrilla y cortes | G10: 6 | H10: 105329 | I10: 0.21 | J10: =ROUND(H10*I10,2) -> 22119.09 | K10: =ROUND(H10+J10,2) -> 127448.09 | L10: Transferencia
A11: 46119 | B11: Factura B | C11: 0001-00004007 | D11: Consultora Río (FICTICIA) | F11: Menú ejecutivo | G11: 1 | H11: 118275 | I11: 0.21 | J11: =ROUND(H11*I11,2) -> 24837.75 | K11: =ROUND(H11+J11,2) -> 143112.75 | L11: Tarjeta de débito
A12: 46120 | B12: Factura B | C12: 0001-00004008 | D12: Estudio Madero (FICTICIO) | F12: Cortes premium | G12: 2 | H12: 131221 | I12: 0.21 | J12: =ROUND(H12*I12,2) -> 27556.41 | K12: =ROUND(H12+J12,2) -> 158777.41 | L12: Mercado Pago
A13: 46121 | B13: Factura B | C13: 0001-00004009 | D13: Consumidor final | F13: Bebidas y cubiertos | G13: 3 | H13: 54166 | I13: 0.21 | J13: =ROUND(H13*I13,2) -> 11374.86 | K13: =ROUND(H13+J13,2) -> 65540.86 | L13: Tarjeta de crédito
A14: 46122 | B14: Factura B | C14: 0001-00004010 | D14: Consumidor final | F14: Parrilla y cortes | G14: 4 | H14: 67112 | I14: 0.21 | J14: =ROUND(H14*I14,2) -> 14093.52 | K14: =ROUND(H14+J14,2) -> 81205.52 | L14: Efectivo
A15: 46123 | B15: Factura A | C15: 0001-00004011 | D15: Consumidor final | E15: 30-70057851-4 | F15: Menú ejecutivo | G15: 5 | H15: 80058 | I15: 0.21 | J15: =ROUND(H15*I15,2) -> 16812.18 | K15: =ROUND(H15+J15,2) -> 96870.18 | L15: Transferencia
A16: 46124 | B16: Factura B | C16: 0001-00004012 | D16: Consumidor final | F16: Cortes premium | G16: 6 | H16: 93004 | I16: 0.21 | J16: =ROUND(H16*I16,2) -> 19530.84 | K16: =ROUND(H16+J16,2) -> 112534.84 | L16: Tarjeta de débito
A17: 46125 | B17: Factura B | C17: 0001-00004013 | D17: Empresa de Eventos Sur (FICTICIA) | F17: Bebidas y cubiertos | G17: 1 | H17: 105950 | I17: 0.21 | J17: =ROUND(H17*I17,2) -> 22249.5 | K17: =ROUND(H17+J17,2) -> 128199.5 | L17: Mercado Pago
A18: 46126 | B18: Factura B | C18: 0001-00004014 | D18: Consumidor final | F18: Parrilla y cortes | G18: 2 | H18: 118896 | I18: 0.21 | J18: =ROUND(H18*I18,2) -> 24968.16 | K18: =ROUND(H18+J18,2) -> 143864.16 | L18: Tarjeta de crédito
A19: 46127 | B19: Factura B | C19: 0001-00004015 | D19: Agencia Costera (FICTICIA) | F19: Menú ejecutivo | G19: 3 | H19: 131842 | I19: 0.21 | J19: =ROUND(H19*I19,2) -> 27686.82 | K19: =ROUND(H19+J19,2) -> 159528.82 | L19: Efectivo
A20: 46128 | B20: Factura B | C20: 0001-00004016 | D20: Consumidor final | F20: Cortes premium | G20: 4 | H20: 54787 | I20: 0.21 | J20: =ROUND(H20*I20,2) -> 11505.27 | K20: =ROUND(H20+J20,2) -> 66292.27 | L20: Transferencia
A21: 46129 | B21: Factura B | C21: 0001-00004017 | D21: Hotel Dársena (FICTICIO) | F21: Bebidas y cubiertos | G21: 5 | H21: 67733 | I21: 0.21 | J21: =ROUND(H21*I21,2) -> 14223.93 | K21: =ROUND(H21+J21,2) -> 81956.93 | L21: Tarjeta de débito
A22: 46130 | B22: Factura B | C22: 0001-00004018 | D22: Consumidor final | F22: Parrilla y cortes | G22: 6 | H22: 80679 | I22: 0.21 | J22: =ROUND(H22*I22,2) -> 16942.59 | K22: =ROUND(H22+J22,2) -> 97621.59 | L22: Mercado Pago
A23: 46131 | B23: Factura B | C23: 0001-00004019 | D23: Consultora Río (FICTICIA) | F23: Menú ejecutivo | G23: 1 | H23: 93625 | I23: 0.21 | J23: =ROUND(H23*I23,2) -> 19661.25 | K23: =ROUND(H23+J23,2) -> 113286.25 | L23: Tarjeta de crédito
A24: 46132 | B24: Factura B | C24: 0001-00004020 | D24: Estudio Madero (FICTICIO) | F24: Cortes premium | G24: 2 | H24: 106571 | I24: 0.21 | J24: =ROUND(H24*I24,2) -> 22379.91 | K24: =ROUND(H24+J24,2) -> 128950.91 | L24: Efectivo
A25: 46133 | B25: Factura A | C25: 0001-00004021 | D25: Consumidor final | E25: 30-70060061-6 | F25: Bebidas y cubiertos | G25: 3 | H25: 119517 | I25: 0.21 | J25: =ROUND(H25*I25,2) -> 25098.57 | K25: =ROUND(H25+J25,2) -> 144615.57 | L25: Transferencia
A26: 46134 | B26: Factura B | C26: 0001-00004022 | D26: Consumidor final | F26: Parrilla y cortes | G26: 4 | H26: 42462 | I26: 0.21 | J26: =ROUND(H26*I26,2) -> 8917.02 | K26: =ROUND(H26+J26,2) -> 51379.02 | L26: Tarjeta de débito
A27: 46135 | B27: Factura B | C27: 0001-00004023 | D27: Consumidor final | F27: Menú ejecutivo | G27: 5 | H27: 55408 | I27: 0.21 | J27: =ROUND(H27*I27,2) -> 11635.68 | K27: =ROUND(H27+J27,2) -> 67043.68 | L27: Mercado Pago
A28: 46136 | B28: Factura B | C28: 0001-00004024 | D28: Consumidor final | F28: Cortes premium | G28: 6 | H28: 68354 | I28: 0.21 | J28: =ROUND(H28*I28,2) -> 14354.34 | K28: =ROUND(H28+J28,2) -> 82708.34 | L28: Tarjeta de crédito
A29: 46137 | B29: Factura B | C29: 0001-00004025 | D29: Empresa de Eventos Sur (FICTICIA) | F29: Bebidas y cubiertos | G29: 1 | H29: 81300 | I29: 0.21 | J29: =ROUND(H29*I29,2) -> 17073 | K29: =ROUND(H29+J29,2) -> 98373 | L29: Efectivo
A30: 46138 | B30: Factura B | C30: 0001-00004026 | D30: Consumidor final | F30: Parrilla y cortes | G30: 2 | H30: 94246 | I30: 0.21 | J30: =ROUND(H30*I30,2) -> 19791.66 | K30: =ROUND(H30+J30,2) -> 114037.66 | L30: Transferencia
A31: 46139 | B31: Factura B | C31: 0001-00004027 | D31: Agencia Costera (FICTICIA) | F31: Menú ejecutivo | G31: 3 | H31: 107192 | I31: 0.21 | J31: =ROUND(H31*I31,2) -> 22510.32 | K31: =ROUND(H31+J31,2) -> 129702.32 | L31: Tarjeta de débito
A32: 46140 | B32: Factura B | C32: 0001-00004028 | D32: Consumidor final | F32: Cortes premium | G32: 4 | H32: 120138 | I32: 0.21 | J32: =ROUND(H32*I32,2) -> 25228.98 | K32: =ROUND(H32+J32,2) -> 145366.98 | L32: Mercado Pago
A33: 46113 | B33: Factura B | C33: 0001-00004029 | D33: Hotel Dársena (FICTICIO) | F33: Bebidas y cubiertos | G33: 5 | H33: 43083 | I33: 0.21 | J33: =ROUND(H33*I33,2) -> 9047.43 | K33: =ROUND(H33+J33,2) -> 52130.43 | L33: Tarjeta de crédito
A34: 46114 | B34: Factura B | C34: 0001-00004030 | D34: Consumidor final | F34: Parrilla y cortes | G34: 6 | H34: 56029 | I34: 0.21 | J34: =ROUND(H34*I34,2) -> 11766.09 | K34: =ROUND(H34+J34,2) -> 67795.09 | L34: Efectivo
A35: 46115 | B35: Factura A | C35: 0001-00004031 | D35: Consultora Río (FICTICIA) | E35: 30-70062271-8 | F35: Menú ejecutivo | G35: 1 | H35: 68975 | I35: 0.21 | J35: =ROUND(H35*I35,2) -> 14484.75 | K35: =ROUND(H35+J35,2) -> 83459.75 | L35: Transferencia
A36: 46116 | B36: Factura B | C36: 0001-00004032 | D36: Estudio Madero (FICTICIO) | F36: Cortes premium | G36: 2 | H36: 81921 | I36: 0.21 | J36: =ROUND(H36*I36,2) -> 17203.41 | K36: =ROUND(H36+J36,2) -> 99124.41 | L36: Tarjeta de débito
A37: 46117 | B37: Factura B | C37: 0001-00004033 | D37: Consumidor final | F37: Bebidas y cubiertos | G37: 3 | H37: 94867 | I37: 0.21 | J37: =ROUND(H37*I37,2) -> 19922.07 | K37: =ROUND(H37+J37,2) -> 114789.07 | L37: Mercado Pago
A38: 46118 | B38: Factura B | C38: 0001-00004034 | D38: Consumidor final | F38: Parrilla y cortes | G38: 4 | H38: 107813 | I38: 0.21 | J38: =ROUND(H38*I38,2) -> 22640.73 | K38: =ROUND(H38+J38,2) -> 130453.73 | L38: Tarjeta de crédito
A39: 46119 | B39: Factura B | C39: 0001-00004035 | D39: Consumidor final | F39: Menú ejecutivo | G39: 5 | H39: 120759 | I39: 0.21 | J39: =ROUND(H39*I39,2) -> 25359.39 | K39: =ROUND(H39+J39,2) -> 146118.39 | L39: Efectivo
A40: 46120 | B40: Factura B | C40: 0001-00004036 | D40: Consumidor final | F40: Cortes premium | G40: 6 | H40: 43704 | I40: 0.21 | J40: =ROUND(H40*I40,2) -> 9177.84 | K40: =ROUND(H40+J40,2) -> 52881.84 | L40: Transferencia
A41: 46121 | B41: Factura B | C41: 0001-00004037 | D41: Empresa de Eventos Sur (FICTICIA) | F41: Bebidas y cubiertos | G41: 1 | H41: 56650 | I41: 0.21 | J41: =ROUND(H41*I41,2) -> 11896.5 | K41: =ROUND(H41+J41,2) -> 68546.5 | L41: Tarjeta de débito
A42: 46122 | B42: Factura B | C42: 0001-00004038 | D42: Consumidor final | F42: Parrilla y cortes | G42: 2 | H42: 69596 | I42: 0.21 | J42: =ROUND(H42*I42,2) -> 14615.16 | K42: =ROUND(H42+J42,2) -> 84211.16 | L42: Mercado Pago
A43: 46123 | B43: Factura B | C43: 0001-00004039 | D43: Agencia Costera (FICTICIA) | F43: Menú ejecutivo | G43: 3 | H43: 82542 | I43: 0.21 | J43: =ROUND(H43*I43,2) -> 17333.82 | K43: =ROUND(H43+J43,2) -> 99875.82 | L43: Tarjeta de crédito
A44: 46124 | B44: Factura B | C44: 0001-00004040 | D44: Consumidor final | F44: Cortes premium | G44: 4 | H44: 95488 | I44: 0.21 | J44: =ROUND(H44*I44,2) -> 20052.48 | K44: =ROUND(H44+J44,2) -> 115540.48 | L44: Efectivo
A45: 46125 | B45: Factura A | C45: 0001-00004041 | D45: Hotel Dársena (FICTICIO) | E45: 30-70064481-2 | F45: Bebidas y cubiertos | G45: 5 | H45: 108434 | I45: 0.21 | J45: =ROUND(H45*I45,2) -> 22771.14 | K45: =ROUND(H45+J45,2) -> 131205.14 | L45: Transferencia
A46: 46126 | B46: Factura B | C46: 0001-00004042 | D46: Consumidor final | F46: Parrilla y cortes | G46: 6 | H46: 121380 | I46: 0.21 | J46: =ROUND(H46*I46,2) -> 25489.8 | K46: =ROUND(H46+J46,2) -> 146869.8 | L46: Tarjeta de débito
A47: 46127 | B47: Factura B | C47: 0001-00004043 | D47: Consultora Río (FICTICIA) | F47: Menú ejecutivo | G47: 1 | H47: 44325 | I47: 0.21 | J47: =ROUND(H47*I47,2) -> 9308.25 | K47: =ROUND(H47+J47,2) -> 53633.25 | L47: Mercado Pago
A48: 46128 | B48: Factura B | C48: 0001-00004044 | D48: Estudio Madero (FICTICIO) | F48: Cortes premium | G48: 2 | H48: 57271 | I48: 0.21 | J48: =ROUND(H48*I48,2) -> 12026.91 | K48: =ROUND(H48+J48,2) -> 69297.91 | L48: Tarjeta de crédito
A49: 46129 | B49: Factura B | C49: 0001-00004045 | D49: Consumidor final | F49: Bebidas y cubiertos | G49: 3 | H49: 70217 | I49: 0.21 | J49: =ROUND(H49*I49,2) -> 14745.57 | K49: =ROUND(H49+J49,2) -> 84962.57 | L49: Efectivo
A50: 46130 | B50: Factura B | C50: 0001-00004046 | D50: Consumidor final | F50: Parrilla y cortes | G50: 4 | H50: 83163 | I50: 0.21 | J50: =ROUND(H50*I50,2) -> 17464.23 | K50: =ROUND(H50+J50,2) -> 100627.23 | L50: Transferencia
A51: 46131 | B51: Factura B | C51: 0001-00004047 | D51: Consumidor final | F51: Menú ejecutivo | G51: 5 | H51: 96109 | I51: 0.21 | J51: =ROUND(H51*I51,2) -> 20182.89 | K51: =ROUND(H51+J51,2) -> 116291.89 | L51: Tarjeta de débito
A52: 46132 | B52: Factura B | C52: 0001-00004048 | D52: Consumidor final | F52: Cortes premium | G52: 6 | H52: 109055 | I52: 0.21 | J52: =ROUND(H52*I52,2) -> 22901.55 | K52: =ROUND(H52+J52,2) -> 131956.55 | L52: Mercado Pago
A53: 46133 | B53: Factura B | C53: 0001-00004049 | D53: Empresa de Eventos Sur (FICTICIA) | F53: Bebidas y cubiertos | G53: 1 | H53: 122001 | I53: 0.21 | J53: =ROUND(H53*I53,2) -> 25620.21 | K53: =ROUND(H53+J53,2) -> 147621.21 | L53: Tarjeta de crédito
A54: 46134 | B54: Factura B | C54: 0001-00004050 | D54: Consumidor final | F54: Parrilla y cortes | G54: 2 | H54: 44946 | I54: 0.21 | J54: =ROUND(H54*I54,2) -> 9438.66 | K54: =ROUND(H54+J54,2) -> 54384.66 | L54: Efectivo
A55: 46135 | B55: Factura A | C55: 0001-00004051 | D55: Agencia Costera (FICTICIA) | E55: 30-70066691-4 | F55: Menú ejecutivo | G55: 3 | H55: 57892 | I55: 0.21 | J55: =ROUND(H55*I55,2) -> 12157.32 | K55: =ROUND(H55+J55,2) -> 70049.32 | L55: Transferencia
A56: 46136 | B56: Factura B | C56: 0001-00004052 | D56: Consumidor final | F56: Cortes premium | G56: 4 | H56: 70838 | I56: 0.21 | J56: =ROUND(H56*I56,2) -> 14875.98 | K56: =ROUND(H56+J56,2) -> 85713.98 | L56: Tarjeta de débito
A57: 46137 | B57: Factura B | C57: 0001-00004053 | D57: Hotel Dársena (FICTICIO) | F57: Bebidas y cubiertos | G57: 5 | H57: 83784 | I57: 0.21 | J57: =ROUND(H57*I57,2) -> 17594.64 | K57: =ROUND(H57+J57,2) -> 101378.64 | L57: Mercado Pago
A58: 46138 | B58: Factura B | C58: 0001-00004054 | D58: Consumidor final | F58: Parrilla y cortes | G58: 6 | H58: 96730 | I58: 0.21 | J58: =ROUND(H58*I58,2) -> 20313.3 | K58: =ROUND(H58+J58,2) -> 117043.3 | L58: Tarjeta de crédito

Sheet Abril Gastos
A1: COSTANERA GRILL · ABRIL 2026 · REGISTRO DE COMPRAS Y GASTOS (SIMULACIÓN)
A2: Proveedores y comprobantes ficticios. Alícuotas ilustrativas; verificar normativa aplicable en un caso real.
A4: Fecha | B4: Proveedor | C4: CUIT proveedor (ficticio) | D4: Tipo comprobante | E4: Categoría | F4: Detalle | G4: Neto gravado | H4: Alícuota IVA | I4: IVA crédito | J4: Total | K4: Medio de pago
A5: 46114 | B5: Frigorífico La Pampa (FICTICIO) | C5: 30-70123456-1 | D5: Factura A | E5: Carne | F5: Compra de carne para operación | G5: 222736 | H5: 0.105 | I5: =ROUND(G5*H5,2) -> 23387.28 | J5: =ROUND(G5+I5,2) -> 246123.28 | K5: Transferencia
A6: 46117 | B6: Carnes del Sur (FICTICIO) | C6: 30-70987654-2 | D6: Factura B | E6: Carne | F6: Compra de carne para operación | G6: 122414 | H6: 0.105 | I6: =ROUND(G6*H6,2) -> 12853.47 | J6: =ROUND(G6+I6,2) -> 135267.47 | K6: Mercado Pago
A7: 46120 | B7: Bebidas Río (FICTICIO) | C7: 30-71234567-3 | D7: Factura B | E7: Bebidas | F7: Compra de bebidas para operación | G7: 71640 | H7: 0.21 | I7: =ROUND(G7*H7,2) -> 15044.4 | J7: =ROUND(G7+I7,2) -> 86684.4 | K7: Efectivo
A8: 46123 | B8: Distribuidora Malbec (FICTICIO) | C8: 30-72345678-4 | D8: Factura A | E8: Bebidas | F8: Compra de bebidas para operación | G8: 64107 | H8: 0.21 | I8: =ROUND(G8*H8,2) -> 13462.47 | J8: =ROUND(G8+I8,2) -> 77569.47 | K8: Tarjeta de débito
A9: 46126 | B9: Edenor - ejemplo didáctico | C9: 30-54567891-2 | D9: Factura B | E9: Electricidad | F9: Compra de electricidad para operación | G9: 150936 | H9: 0.21 | I9: =ROUND(G9*H9,2) -> 31696.56 | J9: =ROUND(G9+I9,2) -> 182632.56 | K9: Tarjeta de crédito
A10: 46129 | B10: Metrogas - ejemplo didáctico | C10: 30-65789123-4 | D10: Factura B | E10: Gas | F10: Compra de gas para operación | G10: 87286 | H10: 0.21 | I10: =ROUND(G10*H10,2) -> 18330.06 | J10: =ROUND(G10+I10,2) -> 105616.06 | K10: Transferencia
A11: 46132 | B11: Fibra Puerto (FICTICIO) | C11: 30-67891234-5 | D11: Factura A | E11: Internet | F11: Compra de internet para operación | G11: 20853 | H11: 0.21 | I11: =ROUND(G11*H11,2) -> 4379.13 | J11: =ROUND(G11+I11,2) -> 25232.13 | K11: Mercado Pago
A12: 46135 | B12: Limpieza del Puerto (FICTICIO) | C12: 30-68912345-6 | D12: Factura B | E12: Limpieza | F12: Compra de limpieza para operación | G12: 44327 | H12: 0.21 | I12: =ROUND(G12*H12,2) -> 9308.67 | J12: =ROUND(G12+I12,2) -> 53635.67 | K12: Efectivo
A13: 46138 | B13: Envases del Plata (FICTICIO) | C13: 30-69123456-7 | D13: Factura B | E13: Insumos | F13: Compra de insumos para operación | G13: 29792 | H13: 0.21 | I13: =ROUND(G13*H13,2) -> 6256.32 | J13: =ROUND(G13+I13,2) -> 36048.32 | K13: Tarjeta de débito
A14: 46114 | B14: Alquiler local Puerto Madero (FICTICIO) | C14: 30-61234567-8 | D14: Factura A | E14: Alquiler | F14: Compra de alquiler para operación | G14: 98732 | H14: 0.21 | I14: =ROUND(G14*H14,2) -> 20733.72 | J14: =ROUND(G14+I14,2) -> 119465.72 | K14: Tarjeta de crédito
A15: 46117 | B15: Mantenimiento Parrillero (FICTICIO) | C15: 30-63456789-1 | D15: Factura B | E15: Mantenimiento | F15: Compra de mantenimiento para operación | G15: 25714 | H15: 0.21 | I15: =ROUND(G15*H15,2) -> 5399.94 | J15: =ROUND(G15+I15,2) -> 31113.94 | K15: Transferencia
A16: 46120 | B16: Panificados del Puerto (FICTICIO) | C16: 30-64567891-3 | D16: Factura B | E16: Alimentos | F16: Compra de alimentos para operación | G16: 51479 | H16: 0.21 | I16: =ROUND(G16*H16,2) -> 10810.59 | J16: =ROUND(G16+I16,2) -> 62289.59 | K16: Mercado Pago
... A22: 46138 | B22: Papelería Administrativa (FICTICIO) | C22: 30-61234578-9 | D22: Factura B | E22: Administración | F22: Compra de administración para operación | G22: 11540 | H22: 0.21 | I22: =ROUND(G22*H22,2) -> 2423.4 | J22: =ROUND(G22+I22,2) -> 13963.4 | K22: Efectivo

Sheet Mayo Ventas
A1: COSTANERA GRILL · MAYO 2026 · REGISTRO DE VENTAS (SIMULACIÓN)
A2: Datos inventados para ejercicio de capacitación. Sin validez fiscal ni contable. IVA calculado con fórmula sobre base imponible.
A4: Fecha | B4: Tipo comprobante | C4: Número | D4: Cliente | E4: CUIT cliente (ficticio) | F4: Concepto | G4: Cantidad | H4: Neto gravado | I4: Alícuota IVA | J4: IVA débito | K4: Total | L4: Medio de cobro
A5: 46143 | B5: Factura A | C5: 0001-00005001 | D5: Estudio Madero (FICTICIO) | E5: 30-70057188-5 | F5: Parrilla y cortes | G5: 1 | H5: 131221 | I5: 0.21 | J5: =ROUND(H5*I5,2) -> 27556.41 | K5: =ROUND(H5+J5,2) -> 158777.41 | L5: Mercado Pago
A6: 46144 | B6: Factura B | C6: 0001-00005002 | D6: Consumidor final | F6: Menú ejecutivo | G6: 2 | H6: 54166 | I6: 0.21 | J6: =ROUND(H6*I6,2) -> 11374.86 | K6: =ROUND(H6+J6,2) -> 65540.86 | L6: Tarjeta de crédito
A7: 46145 | B7: Factura B | C7: 0001-00005003 | D7: Consumidor final | F7: Cortes premium | G7: 3 | H7: 67112 | I7: 0.21 | J7: =ROUND(H7*I7,2) -> 14093.52 | K7: =ROUND(H7+J7,2) -> 81205.52 | L7: Efectivo
A8: 46146 | B8: Factura B | C8: 0001-00005004 | D8: Consumidor final | F8: Bebidas y cubiertos | G8: 4 | H8: 80058 | I8: 0.21 | J8: =ROUND(H8*I8,2) -> 16812.18 | K8: =ROUND(H8+J8,2) -> 96870.18 | L8: Transferencia
A9: 46147 | B9: Factura B | C9: 0001-00005005 | D9: Consumidor final | F9: Parrilla y cortes | G9: 5 | H9: 93004 | I9: 0.21 | J9: =ROUND(H9*I9,2) -> 19530.84 | K9: =ROUND(H9+J9,2) -> 112534.84 | L9: Tarjeta de débito
A10: 46148 | B10: Factura B | C10: 0001-00005006 | D10: Empresa de Eventos Sur (FICTICIA) | F10: Menú ejecutivo | G10: 6 | H10: 105950 | I10: 0.21 | J10: =ROUND(H10*I10,2) -> 22249.5 | K10: =ROUND(H10+J10,2) -> 128199.5 | L10: Mercado Pago
A11: 46149 | B11: Factura B | C11: 0001-00005007 | D11: Consumidor final | F11: Cortes premium | G11: 1 | H11: 118896 | I11: 0.21 | J11: =ROUND(H11*I11,2) -> 24968.16 | K11: =ROUND(H11+J11,2) -> 143864.16 | L11: Tarjeta de crédito
A12: 46150 | B12: Factura B | C12: 0001-00005008 | D12: Agencia Costera (FICTICIA) | F12: Bebidas y cubiertos | G12: 2 | H12: 131842 | I12: 0.21 | J12: =ROUND(H12*I12,2) -> 27686.82 | K12: =ROUND(H12+J12,2) -> 159528.82 | L12: Efectivo
A13: 46151 | B13: Factura B | C13: 0001-00005009 | D13: Consumidor final | F13: Parrilla y cortes | G13: 3 | H13: 54787 | I13: 0.21 | J13: =ROUND(H13*I13,2) -> 11505.27 | K13: =ROUND(H13+J13,2) -> 66292.27 | L13: Transferencia
A14: 46152 | B14: Factura B | C14: 0001-00005010 | D14: Hotel Dársena (FICTICIO) | F14: Menú ejecutivo | G14: 4 | H14: 67733 | I14: 0.21 | J14: =ROUND(H14*I14,2) -> 14223.93 | K14: =ROUND(H14+J14,2) -> 81956.93 | L14: Tarjeta de débito
A15: 46153 | B15: Factura A | C15: 0001-00005011 | D15: Consumidor final | E15: 30-70059398-7 | F15: Cortes premium | G15: 5 | H15: 80679 | I15: 0.21 | J15: =ROUND(H15*I15,2) -> 16942.59 | K15: =ROUND(H15+J15,2) -> 97621.59 | L15: Mercado Pago
A16: 46154 | B16: Factura B | C16: 0001-00005012 | D16: Consultora Río (FICTICIA) | F16: Bebidas y cubiertos | G16: 6 | H16: 93625 | I16: 0.21 | J16: =ROUND(H16*I16,2) -> 19661.25 | K16: =ROUND(H16+J16,2) -> 113286.25 | L16: Tarjeta de crédito
A17: 46155 | B17: Factura B | C17: 0001-00005013 | D17: Estudio Madero (FICTICIO) | F17: Parrilla y cortes | G17: 1 | H17: 106571 | I17: 0.21 | J17: =ROUND(H17*I17,2) -> 22379.91 | K17: =ROUND(H17+J17,2) -> 128950.91 | L17: Efectivo
A18: 46156 | B18: Factura B | C18: 0001-00005014 | D18: Consumidor final | F18: Menú ejecutivo | G18: 2 | H18: 119517 | I18: 0.21 | J18: =ROUND(H18*I18,2) -> 25098.57 | K18: =ROUND(H18+J18,2) -> 144615.57 | L18: Transferencia
A19: 46157 | B19: Factura B | C19: 0001-00005015 | D19: Consumidor final | F19: Cortes premium | G19: 3 | H19: 42462 | I19: 0.21 | J19: =ROUND(H19*I19,2) -> 8917.02 | K19: =ROUND(H19+J19,2) -> 51379.02 | L19: Tarjeta de débito
A20: 46158 | B20: Factura B | C20: 0001-00005016 | D20: Consumidor final | F20: Bebidas y cubiertos | G20: 4 | H20: 55408 | I20: 0.21 | J20: =ROUND(H20*I20,2) -> 11635.68 | K20: =ROUND(H20+J20,2) -> 67043.68 | L20: Mercado Pago
A21: 46159 | B21: Factura B | C21: 0001-00005017 | D21: Consumidor final | F21: Parrilla y cortes | G21: 5 | H21: 68354 | I21: 0.21 | J21: =ROUND(H21*I21,2) -> 14354.34 | K21: =ROUND(H21+J21,2) -> 82708.34 | L21: Tarjeta de crédito
A22: 46160 | B22: Factura B | C22: 0001-00005018 | D22: Empresa de Eventos Sur (FICTICIA) | F22: Menú ejecutivo | G22: 6 | H22: 81300 | I22: 0.21 | J22: =ROUND(H22*I22,2) -> 17073 | K22: =ROUND(H22+J22,2) -> 98373 | L22: Efectivo
A23: 46161 | B23: Factura B | C23: 0001-00005019 | D23: Consumidor final | F23: Cortes premium | G23: 1 | H23: 94246 | I23: 0.21 | J23: =ROUND(H23*I23,2) -> 19791.66 | K23: =ROUND(H23+J23,2) -> 114037.66 | L23: Transferencia
A24: 46162 | B24: Factura B | C24: 0001-00005020 | D24: Agencia Costera (FICTICIA) | F24: Bebidas y cubiertos | G24: 2 | H24: 107192 | I24: 0.21 | J24: =ROUND(H24*I24,2) -> 22510.32 | K24: =ROUND(H24+J24,2) -> 129702.32 | L24: Tarjeta de débito
A25: 46163 | B25: Factura A | C25: 0001-00005021 | D25: Consumidor final | E25: 30-70061608-1 | F25: Parrilla y cortes | G25: 3 | H25: 120138 | I25: 0.21 | J25: =ROUND(H25*I25,2) -> 25228.98 | K25: =ROUND(H25+J25,2) -> 145366.98 | L25: Mercado Pago
A26: 46164 | B26: Factura B | C26: 0001-00005022 | D26: Hotel Dársena (FICTICIO) | F26: Menú ejecutivo | G26: 4 | H26: 43083 | I26: 0.21 | J26: =ROUND(H26*I26,2) -> 9047.43 | K26: =ROUND(H26+J26,2) -> 52130.43 | L26: Tarjeta de crédito
A27: 46165 | B27: Factura B | C27: 0001-00005023 | D27: Consumidor final | F27: Cortes premium | G27: 5 | H27: 56029 | I27: 0.21 | J27: =ROUND(H27*I27,2) -> 11766.09 | K27: =ROUND(H27+J27,2) -> 67795.09 | L27: Efectivo
A28: 46166 | B28: Factura B | C28: 0001-00005024 | D28: Consultora Río (FICTICIA) | F28: Bebidas y cubiertos | G28: 6 | H28: 68975 | I28: 0.21 | J28: =ROUND(H28*I28,2) -> 14484.75 | K28: =ROUND(H28+J28,2) -> 83459.75 | L28: Transferencia
A29: 46167 | B29: Factura B | C29: 0001-00005025 | D29: Estudio Madero (FICTICIO) | F29: Parrilla y cortes | G29: 1 | H29: 81921 | I29: 0.21 | J29: =ROUND(H29*I29,2) -> 17203.41 | K29: =ROUND(H29+J29,2) -> 99124.41 | L29: Tarjeta de débito
A30: 46168 | B30: Factura B | C30: 0001-00005026 | D30: Consumidor final | F30: Menú ejecutivo | G30: 2 | H30: 94867 | I30: 0.21 | J30: =ROUND(H30*I30,2) -> 19922.07 | K30: =ROUND(H30+J30,2) -> 114789.07 | L30: Mercado Pago
A31: 46169 | B31: Factura B | C31: 0001-00005027 | D31: Consumidor final | F31: Cortes premium | G31: 3 | H31: 107813 | I31: 0.21 | J31: =ROUND(H31*I31,2) -> 22640.73 | K31: =ROUND(H31+J31,2) -> 130453.73 | L31: Tarjeta de crédito
A32: 46170 | B32: Factura B | C32: 0001-00005028 | D32: Consumidor final | F32: Bebidas y cubiertos | G32: 4 | H32: 120759 | I32: 0.21 | J32: =ROUND(H32*I32,2) -> 25359.39 | K32: =ROUND(H32+J32,2) -> 146118.39 | L32: Efectivo
A33: 46143 | B33: Factura B | C33: 0001-00005029 | D33: Consumidor final | F33: Parrilla y cortes | G33: 5 | H33: 43704 | I33: 0.21 | J33: =ROUND(H33*I33,2) -> 9177.84 | K33: =ROUND(H33+J33,2) -> 52881.84 | L33: Transferencia
A34: 46144 | B34: Factura B | C34: 0001-00005030 | D34: Empresa de Eventos Sur (FICTICIA) | F34: Menú ejecutivo | G34: 6 | H34: 56650 | I34: 0.21 | J34: =ROUND(H34*I34,2) -> 11896.5 | K34: =ROUND(H34+J34,2) -> 68546.5 | L34: Tarjeta de débito
A35: 46145 | B35: Factura A | C35: 0001-00005031 | D35: Consumidor final | E35: 30-70063818-3 | F35: Cortes premium | G35: 1 | H35: 69596 | I35: 0.21 | J35: =ROUND(H35*I35,2) -> 14615.16 | K35: =ROUND(H35+J35,2) -> 84211.16 | L35: Mercado Pago
A36: 46146 | B36: Factura B | C36: 0001-00005032 | D36: Agencia Costera (FICTICIA) | F36: Bebidas y cubiertos | G36: 2 | H36: 82542 | I36: 0.21 | J36: =ROUND(H36*I36,2) -> 17333.82 | K36: =ROUND(H36+J36,2) -> 99875.82 | L36: Tarjeta de crédito
A37: 46147 | B37: Factura B | C37: 0001-00005033 | D37: Consumidor final | F37: Parrilla y cortes | G37: 3 | H37: 95488 | I37: 0.21 | J37: =ROUND(H37*I37,2) -> 20052.48 | K37: =ROUND(H37+J37,2) -> 115540.48 | L37: Efectivo
A38: 46148 | B38: Factura B | C38: 0001-00005034 | D38: Hotel Dársena (FICTICIO) | F38: Menú ejecutivo | G38: 4 | H38: 108434 | I38: 0.21 | J38: =ROUND(H38*I38,2) -> 22771.14 | K38: =ROUND(H38+J38,2) -> 131205.14 | L38: Transferencia
A39: 46149 | B39: Factura B | C39: 0001-00005035 | D39: Consumidor final | F39: Cortes premium | G39: 5 | H39: 121380 | I39: 0.21 | J39: =ROUND(H39*I39,2) -> 25489.8 | K39: =ROUND(H39+J39,2) -> 146869.8 | L39: Tarjeta de débito
A40: 46150 | B40: Factura B | C40: 0001-00005036 | D40: Consultora Río (FICTICIA) | F40: Bebidas y cubiertos | G40: 6 | H40: 44325 | I40: 0.21 | J40: =ROUND(H40*I40,2) -> 9308.25 | K40: =ROUND(H40+J40,2) -> 53633.25 | L40: Mercado Pago
A41: 46151 | B41: Factura B | C41: 0001-00005037 | D41: Estudio Madero (FICTICIO) | F41: Parrilla y cortes | G41: 1 | H41: 57271 | I41: 0.21 | J41: =ROUND(H41*I41,2) -> 12026.91 | K41: =ROUND(H41+J41,2) -> 69297.91 | L41: Tarjeta de crédito
A42: 46152 | B42: Factura B | C42: 0001-00005038 | D42: Consumidor final | F42: Menú ejecutivo | G42: 2 | H42: 70217 | I42: 0.21 | J42: =ROUND(H42*I42,2) -> 14745.57 | K42: =ROUND(H42+J42,2) -> 84962.57 | L42: Efectivo
A43: 46153 | B43: Factura B | C43: 0001-00005039 | D43: Consumidor final | F43: Cortes premium | G43: 3 | H43: 83163 | I43: 0.21 | J43: =ROUND(H43*I43,2) -> 17464.23 | K43: =ROUND(H43+J43,2) -> 100627.23 | L43: Transferencia
A44: 46154 | B44: Factura B | C44: 0001-00005040 | D44: Consumidor final | F44: Bebidas y cubiertos | G44: 4 | H44: 96109 | I44: 0.21 | J44: =ROUND(H44*I44,2) -> 20182.89 | K44: =ROUND(H44+J44,2) -> 116291.89 | L44: Tarjeta de débito
A45: 46155 | B45: Factura A | C45: 0001-00005041 | D45: Consumidor final | E45: 30-70066028-5 | F45: Parrilla y cortes | G45: 5 | H45: 109055 | I45: 0.21 | J45: =ROUND(H45*I45,2) -> 22901.55 | K45: =ROUND(H45+J45,2) -> 131956.55 | L45: Mercado Pago
A46: 46156 | B46: Factura B | C46: 0001-00005042 | D46: Empresa de Eventos Sur (FICTICIA) | F46: Menú ejecutivo | G46: 6 | H46: 122001 | I46: 0.21 | J46: =ROUND(H46*I46,2) -> 25620.21 | K46: =ROUND(H46+J46,2) -> 147621.21 | L46: Tarjeta de crédito
A47: 46157 | B47: Factura B | C47: 0001-00005043 | D47: Consumidor final | F47: Cortes premium | G47: 1 | H47: 44946 | I47: 0.21 | J47: =ROUND(H47*I47,2) -> 9438.66 | K47: =ROUND(H47+J47,2) -> 54384.66 | L47: Efectivo
A48: 46158 | B48: Factura B | C48: 0001-00005044 | D48: Agencia Costera (FICTICIA) | F48: Bebidas y cubiertos | G48: 2 | H48: 57892 | I48: 0.21 | J48: =ROUND(H48*I48,2) -> 12157.32 | K48: =ROUND(H48+J48,2) -> 70049.32 | L48: Transferencia
A49: 46159 | B49: Factura B | C49: 0001-00005045 | D49: Consumidor final | F49: Parrilla y cortes | G49: 3 | H49: 70838 | I49: 0.21 | J49: =ROUND(H49*I49,2) -> 14875.98 | K49: =ROUND(H49+J49,2) -> 85713.98 | L49: Tarjeta de débito
A50: 46160 | B50: Factura B | C50: 0001-00005046 | D50: Hotel Dársena (FICTICIO) | F50: Menú ejecutivo | G50: 4 | H50: 83784 | I50: 0.21 | J50: =ROUND(H50*I50,2) -> 17594.64 | K50: =ROUND(H50+J50,2) -> 101378.64 | L50: Mercado Pago
A51: 46161 | B51: Factura B | C51: 0001-00005047 | D51: Consumidor final | F51: Cortes premium | G51: 5 | H51: 96730 | I51: 0.21 | J51: =ROUND(H51*I51,2) -> 20313.3 | K51: =ROUND(H51+J51,2) -> 117043.3 | L51: Tarjeta de crédito
A52: 46162 | B52: Factura B | C52: 0001-00005048 | D52: Consultora Río (FICTICIA) | F52: Bebidas y cubiertos | G52: 6 | H52: 109676 | I52: 0.21 | J52: =ROUND(H52*I52,2) -> 23031.96 | K52: =ROUND(H52+J52,2) -> 132707.96 | L52: Efectivo
A53: 46163 | B53: Factura B | C53: 0001-00005049 | D53: Estudio Madero (FICTICIO) | F53: Parrilla y cortes | G53: 1 | H53: 122622 | I53: 0.21 | J53: =ROUND(H53*I53,2) -> 25750.62 | K53: =ROUND(H53+J53,2) -> 148372.62 | L53: Transferencia
A54: 46164 | B54: Factura B | C54: 0001-00005050 | D54: Consumidor final | F54: Menú ejecutivo | G54: 2 | H54: 45567 | I54: 0.21 | J54: =ROUND(H54*I54,2) -> 9569.07 | K54: =ROUND(H54+J54,2) -> 55136.07 | L54: Tarjeta de débito
A55: 46165 | B55: Factura A | C55: 0001-00005051 | D55: Consumidor final | E55: 30-70068238-7 | F55: Cortes premium | G55: 3 | H55: 58513 | I55: 0.21 | J55: =ROUND(H55*I55,2) -> 12287.73 | K55: =ROUND(H55+J55,2) -> 70800.73 | L55: Mercado Pago
A56: 46166 | B56: Factura B | C56: 0001-00005052 | D56: Consumidor final | F56: Bebidas y cubiertos | G56: 4 | H56: 71459 | I56: 0.21 | J56: =ROUND(H56*I56,2) -> 15006.39 | K56: =ROUND(H56+J56,2) -> 86465.39 | L56: Tarjeta de crédito
A57: 46167 | B57: Factura B | C57: 0001-00005053 | D57: Consumidor final | F57: Parrilla y cortes | G57: 5 | H57: 84405 | I57: 0.21 | J57: =ROUND(H57*I57,2) -> 17725.05 | K57: =ROUND(H57+J57,2) -> 102130.05 | L57: Efectivo
A58: 46168 | B58: Factura B | C58: 0001-00005054 | D58: Empresa de Eventos Sur (FICTICIA) | F58: Menú ejecutivo | G58: 6 | H58: 97351 | I58: 0.21 | J58: =ROUND(H58*I58,2) -> 20443.71 | K58: =ROUND(H58+J58,2) -> 117794.71 | L58: Transferencia

Sheet Mayo Gastos
A1: COSTANERA GRILL · MAYO 2026 · REGISTRO DE COMPRAS Y GASTOS (SIMULACIÓN)
A2: Proveedores y comprobantes ficticios. Alícuotas ilustrativas; verificar normativa aplicable en un caso real.
A4: Fecha | B4: Proveedor | C4: CUIT proveedor (ficticio) | D4: Tipo comprobante | E4: Categoría | F4: Detalle | G4: Neto gravado | H4: Alícuota IVA | I4: IVA crédito | J4: Total | K4: Medio de pago
A5: 46144 | B5: Frigorífico La Pampa (FICTICIO) | C5: 30-70123456-1 | D5: Factura A | E5: Carne | F5: Compra de carne para operación | G5: 115196 | H5: 0.105 | I5: =ROUND(G5*H5,2) -> 12095.58 | J5: =ROUND(G5+I5,2) -> 127291.58 | K5: Mercado Pago
A6: 46147 | B6: Carnes del Sur (FICTICIO) | C6: 30-70987654-2 | D6: Factura B | E6: Carne | F6: Compra de carne para operación | G6: 179876 | H6: 0.105 | I6: =ROUND(G6*H6,2) -> 18886.98 | J6: =ROUND(G6+I6,2) -> 198762.98 | K6: Efectivo
A7: 46150 | B7: Bebidas Río (FICTICIO) | C7: 30-71234567-3 | D7: Factura B | E7: Bebidas | F7: Compra de bebidas para operación | G7: 64094 | H7: 0.21 | I7: =ROUND(G7*H7,2) -> 13459.74 | J7: =ROUND(G7+I7,2) -> 77553.74 | K7: Tarjeta de débito
A8: 46153 | B8: Distribuidora Malbec (FICTICIO) | C8: 30-72345678-4 | D8: Factura A | E8: Bebidas | F8: Compra de bebidas para operación | G8: 66558 | H8: 0.21 | I8: =ROUND(G8*H8,2) -> 13977.18 | J8: =ROUND(G8+I8,2) -> 80535.18 | K8: Tarjeta de crédito
A9: 46156 | B9: Edenor - ejemplo didáctico | C9: 30-54567891-2 | D9: Factura B | E9: Electricidad | F9: Compra de electricidad para operación | G9: 143390 | H9: 0.21 | I9: =ROUND(G9*H9,2) -> 30111.9 | J9: =ROUND(G9+I9,2) -> 173501.9 | K9: Transferencia
A10: 46159 | B10: Metrogas - ejemplo didáctico | C10: 30-65789123-4 | D10: Factura B | E10: Gas | F10: Compra de gas para operación | G10: 89735 | H10: 0.21 | I10: =ROUND(G10*H10,2) -> 18844.35 | J10: =ROUND(G10+I10,2) -> 108579.35 | K10: Mercado Pago
A11: 46162 | B11: Fibra Puerto (FICTICIO) | C11: 30-67891234-5 | D11: Factura A | E11: Internet | F11: Compra de internet para operación | G11: 27232 | H11: 0.21 | I11: =ROUND(G11*H11,2) -> 5718.72 | J11: =ROUND(G11+I11,2) -> 32950.72 | K11: Efectivo
A12: 46165 | B12: Limpieza del Puerto (FICTICIO) | C12: 30-68912345-6 | D12: Factura B | E12: Limpieza | F12: Compra de limpieza para operación | G12: 32754 | H12: 0.21 | I12: =ROUND(G12*H12,2) -> 6878.34 | J12: =ROUND(G12+I12,2) -> 39632.34 | K12: Tarjeta de débito
A13: 46168 | B13: Envases del Plata (FICTICIO) | C13: 30-69123456-7 | D13: Factura B | E13: Insumos | F13: Compra de insumos para operación | G13: 50234 | H13: 0.21 | I13: =ROUND(G13*H13,2) -> 10549.14 | J13: =ROUND(G13+I13,2) -> 60783.14 | K13: Tarjeta de crédito
A14: 46144 | B14: Alquiler local Puerto Madero (FICTICIO) | C14: 30-61234567-8 | D14: Factura A | E14: Alquiler | F14: Compra de alquiler para operación | G14: 121179 | H14: 0.21 | I14: =ROUND(G14*H14,2) -> 25447.59 | J14: =ROUND(G14+I14,2) -> 146626.59 | K14: Transferencia
A15: 46147 | B15: Mantenimiento Parrillero (FICTICIO) | C15: 30-63456789-1 | D15: Factura B | E15: Mantenimiento | F15: Compra de mantenimiento para operación | G15: 18149 | H15: 0.21 | I15: =ROUND(G15*H15,2) -> 3811.29 | J15: =ROUND(G15+I15,2) -> 21960.29 | K15: Mercado Pago
A16: 46150 | B16: Panificados del Puerto (FICTICIO) | C16: 30-64567891-3 | D16: Factura B | E16: Alimentos | F16: Compra de alimentos para operación | G16: 41916 | H16: 0.21 | I16: =ROUND(G16*H16,2) -> 8802.36 | J16: =ROUND(G16+I16,2) -> 50718.36 | K16: Efectivo
... A22: 46168 | B22: Papelería Administrativa (FICTICIO) | C22: 30-61234578-9 | D22: Factura B | E22: Administración | F22: Compra de administración para operación | G22: 21931 | H22: 0.21 | I22: =ROUND(G22*H22,2) -> 4605.51 | J22: =ROUND(G22+I22,2) -> 26536.51 | K22: Tarjeta de débito

Sheet Junio Ventas
A1: COSTANERA GRILL · JUNIO 2026 · REGISTRO DE VENTAS (SIMULACIÓN)
A2: Datos inventados para ejercicio de capacitación. Sin validez fiscal ni contable. IVA calculado con fórmula sobre base imponible.
A4: Fecha | B4: Tipo comprobante | C4: Número | D4: Cliente | E4: CUIT cliente (ficticio) | F4: Concepto | G4: Cantidad | H4: Neto gravado | I4: Alícuota IVA | J4: IVA débito | K4: Total | L4: Medio de cobro
A5: 46174 | B5: Factura A | C5: 0001-00006001 | D5: Agencia Costera (FICTICIA) | E5: 30-70058735-8 | F5: Menú ejecutivo | G5: 1 | H5: 131842 | I5: 0.21 | J5: =ROUND(H5*I5,2) -> 27686.82 | K5: =ROUND(H5+J5,2) -> 159528.82 | L5: Efectivo
A6: 46175 | B6: Factura B | C6: 0001-00006002 | D6: Consumidor final | F6: Cortes premium | G6: 2 | H6: 54787 | I6: 0.21 | J6: =ROUND(H6*I6,2) -> 11505.27 | K6: =ROUND(H6+J6,2) -> 66292.27 | L6: Transferencia
A7: 46176 | B7: Factura B | C7: 0001-00006003 | D7: Hotel Dársena (FICTICIO) | F7: Bebidas y cubiertos | G7: 3 | H7: 67733 | I7: 0.21 | J7: =ROUND(H7*I7,2) -> 14223.93 | K7: =ROUND(H7+J7,2) -> 81956.93 | L7: Tarjeta de débito
A8: 46177 | B8: Factura B | C8: 0001-00006004 | D8: Consumidor final | F8: Parrilla y cortes | G8: 4 | H8: 80679 | I8: 0.21 | J8: =ROUND(H8*I8,2) -> 16942.59 | K8: =ROUND(H8+J8,2) -> 97621.59 | L8: Mercado Pago
A9: 46178 | B9: Factura B | C9: 0001-00006005 | D9: Consultora Río (FICTICIA) | F9: Menú ejecutivo | G9: 5 | H9: 93625 | I9: 0.21 | J9: =ROUND(H9*I9,2) -> 19661.25 | K9: =ROUND(H9+J9,2) -> 113286.25 | L9: Tarjeta de crédito
A10: 46179 | B10: Factura B | C10: 0001-00006006 | D10: Estudio Madero (FICTICIO) | F10: Cortes premium | G10: 6 | H10: 106571 | I10: 0.21 | J10: =ROUND(H10*I10,2) -> 22379.91 | K10: =ROUND(H10+J10,2) -> 128950.91 | L10: Efectivo
A11: 46180 | B11: Factura B | C11: 0001-00006007 | D11: Consumidor final | F11: Bebidas y cubiertos | G11: 1 | H11: 119517 | I11: 0.21 | J11: =ROUND(H11*I11,2) -> 25098.57 | K11: =ROUND(H11+J11,2) -> 144615.57 | L11: Transferencia
A12: 46181 | B12: Factura B | C12: 0001-00006008 | D12: Consumidor final | F12: Parrilla y cortes | G12: 2 | H12: 42462 | I12: 0.21 | J12: =ROUND(H12*I12,2) -> 8917.02 | K12: =ROUND(H12+J12,2) -> 51379.02 | L12: Tarjeta de débito
A13: 46182 | B13: Factura B | C13: 0001-00006009 | D13: Consumidor final | F13: Menú ejecutivo | G13: 3 | H13: 55408 | I13: 0.21 | J13: =ROUND(H13*I13,2) -> 11635.68 | K13: =ROUND(H13+J13,2) -> 67043.68 | L13: Mercado Pago
A14: 46183 | B14: Factura B | C14: 0001-00006010 | D14: Consumidor final | F14: Cortes premium | G14: 4 | H14: 68354 | I14: 0.21 | J14: =ROUND(H14*I14,2) -> 14354.34 | K14: =ROUND(H14+J14,2) -> 82708.34 | L14: Tarjeta de crédito
A15: 46184 | B15: Factura A | C15: 0001-00006011 | D15: Empresa de Eventos Sur (FICTICIA) | E15: 30-70060945-2 | F15: Bebidas y cubiertos | G15: 5 | H15: 81300 | I15: 0.21 | J15: =ROUND(H15*I15,2) -> 17073 | K15: =ROUND(H15+J15,2) -> 98373 | L15: Efectivo
A16: 46185 | B16: Factura B | C16: 0001-00006012 | D16: Consumidor final | F16: Parrilla y cortes | G16: 6 | H16: 94246 | I16: 0.21 | J16: =ROUND(H16*I16,2) -> 19791.66 | K16: =ROUND(H16+J16,2) -> 114037.66 | L16: Transferencia
A17: 46186 | B17: Factura B | C17: 0001-00006013 | D17: Agencia Costera (FICTICIA) | F17: Menú ejecutivo | G17: 1 | H17: 107192 | I17: 0.21 | J17: =ROUND(H17*I17,2) -> 22510.32 | K17: =ROUND(H17+J17,2) -> 129702.32 | L17: Tarjeta de débito
A18: 46187 | B18: Factura B | C18: 0001-00006014 | D18: Consumidor final | F18: Cortes premium | G18: 2 | H18: 120138 | I18: 0.21 | J18: =ROUND(H18*I18,2) -> 25228.98 | K18: =ROUND(H18+J18,2) -> 145366.98 | L18: Mercado Pago
A19: 46188 | B19: Factura B | C19: 0001-00006015 | D19: Hotel Dársena (FICTICIO) | F19: Bebidas y cubiertos | G19: 3 | H19: 43083 | I19: 0.21 | J19: =ROUND(H19*I19,2) -> 9047.43 | K19: =ROUND(H19+J19,2) -> 52130.43 | L19: Tarjeta de crédito
A20: 46189 | B20: Factura B | C20: 0001-00006016 | D20: Consumidor final | F20: Parrilla y cortes | G20: 4 | H20: 56029 | I20: 0.21 | J20: =ROUND(H20*I20,2) -> 11766.09 | K20: =ROUND(H20+J20,2) -> 67795.09 | L20: Efectivo
A21: 46190 | B21: Factura B | C21: 0001-00006017 | D21: Consultora Río (FICTICIA) | F21: Menú ejecutivo | G21: 5 | H21: 68975 | I21: 0.21 | J21: =ROUND(H21*I21,2) -> 14484.75 | K21: =ROUND(H21+J21,2) -> 83459.75 | L21: Transferencia
A22: 46191 | B22: Factura B | C22: 0001-00006018 | D22: Estudio Madero (FICTICIO) | F22: Cortes premium | G22: 6 | H22: 81921 | I22: 0.21 | J22: =ROUND(H22*I22,2) -> 17203.41 | K22: =ROUND(H22+J22,2) -> 99124.41 | L22: Tarjeta de débito
A23: 46192 | B23: Factura B | C23: 0001-00006019 | D23: Consumidor final | F23: Bebidas y cubiertos | G23: 1 | H23: 94867 | I23: 0.21 | J23: =ROUND(H23*I23,2) -> 19922.07 | K23: =ROUND(H23+J23,2) -> 114789.07 | L23: Mercado Pago
A24: 46193 | B24: Factura B | C24: 0001-00006020 | D24: Consumidor final | F24: Parrilla y cortes | G24: 2 | H24: 107813 | I24: 0.21 | J24: =ROUND(H24*I24,2) -> 22640.73 | K24: =ROUND(H24+J24,2) -> 130453.73 | L24: Tarjeta de crédito
A25: 46194 | B25: Factura A | C25: 0001-00006021 | D25: Consumidor final | E25: 30-70063155-4 | F25: Menú ejecutivo | G25: 3 | H25: 120759 | I25: 0.21 | J25: =ROUND(H25*I25,2) -> 25359.39 | K25: =ROUND(H25+J25,2) -> 146118.39 | L25: Efectivo
A26: 46195 | B26: Factura B | C26: 0001-00006022 | D26: Consumidor final | F26: Cortes premium | G26: 4 | H26: 43704 | I26: 0.21 | J26: =ROUND(H26*I26,2) -> 9177.84 | K26: =ROUND(H26+J26,2) -> 52881.84 | L26: Transferencia
A27: 46196 | B27: Factura B | C27: 0001-00006023 | D27: Empresa de Eventos Sur (FICTICIA) | F27: Bebidas y cubiertos | G27: 5 | H27: 56650 | I27: 0.21 | J27: =ROUND(H27*I27,2) -> 11896.5 | K27: =ROUND(H27+J27,2) -> 68546.5 | L27: Tarjeta de débito
A28: 46197 | B28: Factura B | C28: 0001-00006024 | D28: Consumidor final | F28: Parrilla y cortes | G28: 6 | H28: 69596 | I28: 0.21 | J28: =ROUND(H28*I28,2) -> 14615.16 | K28: =ROUND(H28+J28,2) -> 84211.16 | L28: Mercado Pago
A29: 46198 | B29: Factura B | C29: 0001-00006025 | D29: Agencia Costera (FICTICIA) | F29: Menú ejecutivo | G29: 1 | H29: 82542 | I29: 0.21 | J29: =ROUND(H29*I29,2) -> 17333.82 | K29: =ROUND(H29+J29,2) -> 99875.82 | L29: Tarjeta de crédito
A30: 46199 | B30: Factura B | C30: 0001-00006026 | D30: Consumidor final | F30: Cortes premium | G30: 2 | H30: 95488 | I30: 0.21 | J30: =ROUND(H30*I30,2) -> 20052.48 | K30: =ROUND(H30+J30,2) -> 115540.48 | L30: Efectivo
A31: 46200 | B31: Factura B | C31: 0001-00006027 | D31: Hotel Dársena (FICTICIO) | F31: Bebidas y cubiertos | G31: 3 | H31: 108434 | I31: 0.21 | J31: =ROUND(H31*I31,2) -> 22771.14 | K31: =ROUND(H31+J31,2) -> 131205.14 | L31: Transferencia
A32: 46201 | B32: Factura B | C32: 0001-00006028 | D32: Consumidor final | F32: Parrilla y cortes | G32: 4 | H32: 121380 | I32: 0.21 | J32: =ROUND(H32*I32,2) -> 25489.8 | K32: =ROUND(H32+J32,2) -> 146869.8 | L32: Tarjeta de débito
A33: 46174 | B33: Factura B | C33: 0001-00006029 | D33: Consultora Río (FICTICIA) | F33: Menú ejecutivo | G33: 5 | H33: 44325 | I33: 0.21 | J33: =ROUND(H33*I33,2) -> 9308.25 | K33: =ROUND(H33+J33,2) -> 53633.25 | L33: Mercado Pago
A34: 46175 | B34: Factura B | C34: 0001-00006030 | D34: Estudio Madero (FICTICIO) | F34: Cortes premium | G34: 6 | H34: 57271 | I34: 0.21 | J34: =ROUND(H34*I34,2) -> 12026.91 | K34: =ROUND(H34+J34,2) -> 69297.91 | L34: Tarjeta de crédito
A35: 46176 | B35: Factura A | C35: 0001-00006031 | D35: Consumidor final | E35: 30-70065365-6 | F35: Bebidas y cubiertos | G35: 1 | H35: 70217 | I35: 0.21 | J35: =ROUND(H35*I35,2) -> 14745.57 | K35: =ROUND(H35+J35,2) -> 84962.57 | L35: Efectivo
A36: 46177 | B36: Factura B | C36: 0001-00006032 | D36: Consumidor final | F36: Parrilla y cortes | G36: 2 | H36: 83163 | I36: 0.21 | J36: =ROUND(H36*I36,2) -> 17464.23 | K36: =ROUND(H36+J36,2) -> 100627.23 | L36: Transferencia
A37: 46178 | B37: Factura B | C37: 0001-00006033 | D37: Consumidor final | F37: Menú ejecutivo | G37: 3 | H37: 96109 | I37: 0.21 | J37: =ROUND(H37*I37,2) -> 20182.89 | K37: =ROUND(H37+J37,2) -> 116291.89 | L37: Tarjeta de débito
A38: 46179 | B38: Factura B | C38: 0001-00006034 | D38: Consumidor final | F38: Cortes premium | G38: 4 | H38: 109055 | I38: 0.21 | J38: =ROUND(H38*I38,2) -> 22901.55 | K38: =ROUND(H38+J38,2) -> 131956.55 | L38: Mercado Pago
A39: 46180 | B39: Factura B | C39: 0001-00006035 | D39: Empresa de Eventos Sur (FICTICIA) | F39: Bebidas y cubiertos | G39: 5 | H39: 122001 | I39: 0.21 | J39: =ROUND(H39*I39,2) -> 25620.21 | K39: =ROUND(H39+J39,2) -> 147621.21 | L39: Tarjeta de crédito
A40: 46181 | B40: Factura B | C40: 0001-00006036 | D40: Consumidor final | F40: Parrilla y cortes | G40: 6 | H40: 44946 | I40: 0.21 | J40: =ROUND(H40*I40,2) -> 9438.66 | K40: =ROUND(H40+J40,2) -> 54384.66 | L40: Efectivo
A41: 46182 | B41: Factura B | C41: 0001-00006037 | D41: Agencia Costera (FICTICIA) | F41: Menú ejecutivo | G41: 1 | H41: 57892 | I41: 0.21 | J41: =ROUND(H41*I41,2) -> 12157.32 | K41: =ROUND(H41+J41,2) -> 70049.32 | L41: Transferencia
A42: 46183 | B42: Factura B | C42: 0001-00006038 | D42: Consumidor final | F42: Cortes premium | G42: 2 | H42: 70838 | I42: 0.21 | J42: =ROUND(H42*I42,2) -> 14875.98 | K42: =ROUND(H42+J42,2) -> 85713.98 | L42: Tarjeta de débito
A43: 46184 | B43: Factura B | C43: 0001-00006039 | D43: Hotel Dársena (FICTICIO) | F43: Bebidas y cubiertos | G43: 3 | H43: 83784 | I43: 0.21 | J43: =ROUND(H43*I43,2) -> 17594.64 | K43: =ROUND(H43+J43,2) -> 101378.64 | L43: Mercado Pago
A44: 46185 | B44: Factura B | C44: 0001-00006040 | D44: Consumidor final | F44: Parrilla y cortes | G44: 4 | H44: 96730 | I44: 0.21 | J44: =ROUND(H44*I44,2) -> 20313.3 | K44: =ROUND(H44+J44,2) -> 117043.3 | L44: Tarjeta de crédito
A45: 46186 | B45: Factura A | C45: 0001-00006041 | D45: Consultora Río (FICTICIA) | E45: 30-70067575-8 | F45: Menú ejecutivo | G45: 5 | H45: 109676 | I45: 0.21 | J45: =ROUND(H45*I45,2) -> 23031.96 | K45: =ROUND(H45+J45,2) -> 132707.96 | L45: Efectivo
A46: 46187 | B46: Factura B | C46: 0001-00006042 | D46: Estudio Madero (FICTICIO) | F46: Cortes premium | G46: 6 | H46: 122622 | I46: 0.21 | J46: =ROUND(H46*I46,2) -> 25750.62 | K46: =ROUND(H46+J46,2) -> 148372.62 | L46: Transferencia
A47: 46188 | B47: Factura B | C47: 0001-00006043 | D47: Consumidor final | F47: Bebidas y cubiertos | G47: 1 | H47: 45567 | I47: 0.21 | J47: =ROUND(H47*I47,2) -> 9569.07 | K47: =ROUND(H47+J47,2) -> 55136.07 | L47: Tarjeta de débito
A48: 46189 | B48: Factura B | C48: 0001-00006044 | D48: Consumidor final | F48: Parrilla y cortes | G48: 2 | H48: 58513 | I48: 0.21 | J48: =ROUND(H48*I48,2) -> 12287.73 | K48: =ROUND(H48+J48,2) -> 70800.73 | L48: Mercado Pago
A49: 46190 | B49: Factura B | C49: 0001-00006045 | D49: Consumidor final | F49: Menú ejecutivo | G49: 3 | H49: 71459 | I49: 0.21 | J49: =ROUND(H49*I49,2) -> 15006.39 | K49: =ROUND(H49+J49,2) -> 86465.39 | L49: Tarjeta de crédito
A50: 46191 | B50: Factura B | C50: 0001-00006046 | D50: Consumidor final | F50: Cortes premium | G50: 4 | H50: 84405 | I50: 0.21 | J50: =ROUND(H50*I50,2) -> 17725.05 | K50: =ROUND(H50+J50,2) -> 102130.05 | L50: Efectivo
A51: 46192 | B51: Factura B | C51: 0001-00006047 | D51: Empresa de Eventos Sur (FICTICIA) | F51: Bebidas y cubiertos | G51: 5 | H51: 97351 | I51: 0.21 | J51: =ROUND(H51*I51,2) -> 20443.71 | K51: =ROUND(H51+J51,2) -> 117794.71 | L51: Transferencia
A52: 46193 | B52: Factura B | C52: 0001-00006048 | D52: Consumidor final | F52: Parrilla y cortes | G52: 6 | H52: 110297 | I52: 0.21 | J52: =ROUND(H52*I52,2) -> 23162.37 | K52: =ROUND(H52+J52,2) -> 133459.37 | L52: Tarjeta de débito
A53: 46194 | B53: Factura B | C53: 0001-00006049 | D53: Agencia Costera (FICTICIA) | F53: Menú ejecutivo | G53: 1 | H53: 123243 | I53: 0.21 | J53: =ROUND(H53*I53,2) -> 25881.03 | K53: =ROUND(H53+J53,2) -> 149124.03 | L53: Mercado Pago
A54: 46195 | B54: Factura B | C54: 0001-00006050 | D54: Consumidor final | F54: Cortes premium | G54: 2 | H54: 46188 | I54: 0.21 | J54: =ROUND(H54*I54,2) -> 9699.48 | K54: =ROUND(H54+J54,2) -> 55887.48 | L54: Tarjeta de crédito
A55: 46196 | B55: Factura A | C55: 0001-00006051 | D55: Hotel Dársena (FICTICIO) | E55: 30-70069785-2 | F55: Bebidas y cubiertos | G55: 3 | H55: 59134 | I55: 0.21 | J55: =ROUND(H55*I55,2) -> 12418.14 | K55: =ROUND(H55+J55,2) -> 71552.14 | L55: Efectivo
A56: 46197 | B56: Factura B | C56: 0001-00006052 | D56: Consumidor final | F56: Parrilla y cortes | G56: 4 | H56: 72080 | I56: 0.21 | J56: =ROUND(H56*I56,2) -> 15136.8 | K56: =ROUND(H56+J56,2) -> 87216.8 | L56: Transferencia
A57: 46198 | B57: Factura B | C57: 0001-00006053 | D57: Consultora Río (FICTICIA) | F57: Menú ejecutivo | G57: 5 | H57: 85026 | I57: 0.21 | J57: =ROUND(H57*I57,2) -> 17855.46 | K57: =ROUND(H57+J57,2) -> 102881.46 | L57: Tarjeta de débito
A58: 46199 | B58: Factura B | C58: 0001-00006054 | D58: Estudio Madero (FICTICIO) | F58: Cortes premium | G58: 6 | H58: 97972 | I58: 0.21 | J58: =ROUND(H58*I58,2) -> 20574.12 | K58: =ROUND(H58+J58,2) -> 118546.12 | L58: Mercado Pago

Sheet Junio Gastos
A1: COSTANERA GRILL · JUNIO 2026 · REGISTRO DE COMPRAS Y GASTOS (SIMULACIÓN)
A2: Proveedores y comprobantes ficticios. Alícuotas ilustrativas; verificar normativa aplicable en un caso real.
A4: Fecha | B4: Proveedor | C4: CUIT proveedor (ficticio) | D4: Tipo comprobante | E4: Categoría | F4: Detalle | G4: Neto gravado | H4: Alícuota IVA | I4: IVA crédito | J4: Total | K4: Medio de pago
A5: 46175 | B5: Frigorífico La Pampa (FICTICIO) | C5: 30-70123456-1 | D5: Factura A | E5: Carne | F5: Compra de carne para operación | G5: 117657 | H5: 0.105 | I5: =ROUND(G5*H5,2) -> 12353.99 | J5: =ROUND(G5+I5,2) -> 130010.99 | K5: Efectivo
A6: 46178 | B6: Carnes del Sur (FICTICIO) | C6: 30-70987654-2 | D6: Factura B | E6: Carne | F6: Compra de carne para operación | G6: 122337 | H6: 0.105 | I6: =ROUND(G6*H6,2) -> 12845.39 | J6: =ROUND(G6+I6,2) -> 135182.39 | K6: Tarjeta de débito
A7: 46181 | B7: Bebidas Río (FICTICIO) | C7: 30-71234567-3 | D7: Factura B | E7: Bebidas | F7: Compra de bebidas para operación | G7: 56548 | H7: 0.21 | I7: =ROUND(G7*H7,2) -> 11875.08 | J7: =ROUND(G7+I7,2) -> 68423.08 | K7: Tarjeta de crédito
A8: 46184 | B8: Distribuidora Malbec (FICTICIO) | C8: 30-72345678-4 | D8: Factura A | E8: Bebidas | F8: Compra de bebidas para operación | G8: 69009 | H8: 0.21 | I8: =ROUND(G8*H8,2) -> 14491.89 | J8: =ROUND(G8+I8,2) -> 83500.89 | K8: Transferencia
A9: 46187 | B9: Edenor - ejemplo didáctico | C9: 30-54567891-2 | D9: Factura B | E9: Electricidad | F9: Compra de electricidad para operación | G9: 135844 | H9: 0.21 | I9: =ROUND(G9*H9,2) -> 28527.24 | J9: =ROUND(G9+I9,2) -> 164371.24 | K9: Mercado Pago
A10: 46190 | B10: Metrogas - ejemplo didáctico | C10: 30-65789123-4 | D10: Factura B | E10: Gas | F10: Compra de gas para operación | G10: 92184 | H10: 0.21 | I10: =ROUND(G10*H10,2) -> 19358.64 | J10: =ROUND(G10+I10,2) -> 111542.64 | K10: Efectivo
A11: 46193 | B11: Fibra Puerto (FICTICIO) | C11: 30-67891234-5 | D11: Factura A | E11: Internet | F11: Compra de internet para operación | G11: 19610 | H11: 0.21 | I11: =ROUND(G11*H11,2) -> 4118.1 | J11: =ROUND(G11+I11,2) -> 23728.1 | K11: Tarjeta de débito
A12: 46196 | B12: Limpieza del Puerto (FICTICIO) | C12: 30-68912345-6 | D12: Factura B | E12: Limpieza | F12: Compra de limpieza para operación | G12: 50182 | H12: 0.21 | I12: =ROUND(G12*H12,2) -> 10538.22 | J12: =ROUND(G12+I12,2) -> 60720.22 | K12: Tarjeta de crédito
A13: 46199 | B13: Envases del Plata (FICTICIO) | C13: 30-69123456-7 | D13: Factura B | E13: Insumos | F13: Compra de insumos para operación | G13: 28675 | H13: 0.21 | I13: =ROUND(G13*H13,2) -> 6021.75 | J13: =ROUND(G13+I13,2) -> 34696.75 | K13: Transferencia
A14: 46175 | B14: Alquiler local Puerto Madero (FICTICIO) | C14: 30-61234567-8 | D14: Factura A | E14: Alquiler | F14: Compra de alquiler para operación | G14: 143626 | H14: 0.21 | I14: =ROUND(G14*H14,2) -> 30161.46 | J14: =ROUND(G14+I14,2) -> 173787.46 | K14: Mercado Pago
A15: 46178 | B15: Mantenimiento Parrillero (FICTICIO) | C15: 30-63456789-1 | D15: Factura B | E15: Mantenimiento | F15: Compra de mantenimiento para operación | G15: 45585 | H15: 0.21 | I15: =ROUND(G15*H15,2) -> 9572.85 | J15: =ROUND(G15+I15,2) -> 55157.85 | K15: Efectivo
A16: 46181 | B16: Panificados del Puerto (FICTICIO) | C16: 30-64567891-3 | D16: Factura B | E16: Alimentos | F16: Compra de alimentos para operación | G16: 32353 | H16: 0.21 | I16: =ROUND(G16*H16,2) -> 6794.13 | J16: =ROUND(G16+I16,2) -> 39147.13 | K16: Tarjeta de débito
... A22: 46199 | B22: Papelería Administrativa (FICTICIO) | C22: 30-61234578-9 | D22: Factura B | E22: Administración | F22: Compra de administración para operación | G22: 16321 | H22: 0.21 | I22: =ROUND(G22*H22,2) -> 3427.41 | J22: =ROUND(G22+I22,2) -> 19748.41 | K22: Tarjeta de crédito

Sheet Julio Ventas
A1: COSTANERA GRILL · JULIO 2026 · REGISTRO DE VENTAS (SIMULACIÓN)
A2: Datos inventados para ejercicio de capacitación. Sin validez fiscal ni contable. IVA calculado con fórmula sobre base imponible.
A4: Fecha | B4: Tipo comprobante | C4: Número | D4: Cliente | E4: CUIT cliente (ficticio) | F4: Concepto | G4: Cantidad | H4: Neto gravado | I4: Alícuota IVA | J4: IVA débito | K4: Total | L4: Medio de cobro
A5: 46204 | B5: Factura A | C5: 0001-00007001 | D5: Consumidor final | E5: 30-70060282-3 | F5: Cortes premium | G5: 1 | H5: 42462 | I5: 0.21 | J5: =ROUND(H5*I5,2) -> 8917.02 | K5: =ROUND(H5+J5,2) -> 51379.02 | L5: Tarjeta de débito
A6: 46205 | B6: Factura B | C6: 0001-00007002 | D6: Consumidor final | F6: Bebidas y cubiertos | G6: 2 | H6: 55408 | I6: 0.21 | J6: =ROUND(H6*I6,2) -> 11635.68 | K6: =ROUND(H6+J6,2) -> 67043.68 | L6: Mercado Pago
A7: 46206 | B7: Factura B | C7: 0001-00007003 | D7: Consumidor final | F7: Parrilla y cortes | G7: 3 | H7: 68354 | I7: 0.21 | J7: =ROUND(H7*I7,2) -> 14354.34 | K7: =ROUND(H7+J7,2) -> 82708.34 | L7: Tarjeta de crédito
A8: 46207 | B8: Factura B | C8: 0001-00007004 | D8: Empresa de Eventos Sur (FICTICIA) | F8: Menú ejecutivo | G8: 4 | H8: 81300 | I8: 0.21 | J8: =ROUND(H8*I8,2) -> 17073 | K8: =ROUND(H8+J8,2) -> 98373 | L8: Efectivo
A9: 46208 | B9: Factura B | C9: 0001-00007005 | D9: Consumidor final | F9: Cortes premium | G9: 5 | H9: 94246 | I9: 0.21 | J9: =ROUND(H9*I9,2) -> 19791.66 | K9: =ROUND(H9+J9,2) -> 114037.66 | L9: Transferencia
A10: 46209 | B10: Factura B | C10: 0001-00007006 | D10: Agencia Costera (FICTICIA) | F10: Bebidas y cubiertos | G10: 6 | H10: 107192 | I10: 0.21 | J10: =ROUND(H10*I10,2) -> 22510.32 | K10: =ROUND(H10+J10,2) -> 129702.32 | L10: Tarjeta de débito
A11: 46210 | B11: Factura B | C11: 0001-00007007 | D11: Consumidor final | F11: Parrilla y cortes | G11: 1 | H11: 120138 | I11: 0.21 | J11: =ROUND(H11*I11,2) -> 25228.98 | K11: =ROUND(H11+J11,2) -> 145366.98 | L11: Mercado Pago
A12: 46211 | B12: Factura B | C12: 0001-00007008 | D12: Hotel Dársena (FICTICIO) | F12: Menú ejecutivo | G12: 2 | H12: 43083 | I12: 0.21 | J12: =ROUND(H12*I12,2) -> 9047.43 | K12: =ROUND(H12+J12,2) -> 52130.43 | L12: Tarjeta de crédito
A13: 46212 | B13: Factura B | C13: 0001-00007009 | D13: Consumidor final | F13: Cortes premium | G13: 3 | H13: 56029 | I13: 0.21 | J13: =ROUND(H13*I13,2) -> 11766.09 | K13: =ROUND(H13+J13,2) -> 67795.09 | L13: Efectivo
A14: 46213 | B14: Factura B | C14: 0001-00007010 | D14: Consultora Río (FICTICIA) | F14: Bebidas y cubiertos | G14: 4 | H14: 68975 | I14: 0.21 | J14: =ROUND(H14*I14,2) -> 14484.75 | K14: =ROUND(H14+J14,2) -> 83459.75 | L14: Transferencia
A15: 46214 | B15: Factura A | C15: 0001-00007011 | D15: Estudio Madero (FICTICIO) | E15: 30-70062492-5 | F15: Parrilla y cortes | G15: 5 | H15: 81921 | I15: 0.21 | J15: =ROUND(H15*I15,2) -> 17203.41 | K15: =ROUND(H15+J15,2) -> 99124.41 | L15: Tarjeta de débito
A16: 46215 | B16: Factura B | C16: 0001-00007012 | D16: Consumidor final | F16: Menú ejecutivo | G16: 6 | H16: 94867 | I16: 0.21 | J16: =ROUND(H16*I16,2) -> 19922.07 | K16: =ROUND(H16+J16,2) -> 114789.07 | L16: Mercado Pago
A17: 46216 | B17: Factura B | C17: 0001-00007013 | D17: Consumidor final | F17: Cortes premium | G17: 1 | H17: 107813 | I17: 0.21 | J17: =ROUND(H17*I17,2) -> 22640.73 | K17: =ROUND(H17+J17,2) -> 130453.73 | L17: Tarjeta de crédito
A18: 46217 | B18: Factura B | C18: 0001-00007014 | D18: Consumidor final | F18: Bebidas y cubiertos | G18: 2 | H18: 120759 | I18: 0.21 | J18: =ROUND(H18*I18,2) -> 25359.39 | K18: =ROUND(H18+J18,2) -> 146118.39 | L18: Efectivo
A19: 46218 | B19: Factura B | C19: 0001-00007015 | D19: Consumidor final | F19: Parrilla y cortes | G19: 3 | H19: 43704 | I19: 0.21 | J19: =ROUND(H19*I19,2) -> 9177.84 | K19: =ROUND(H19+J19,2) -> 52881.84 | L19: Transferencia
A20: 46219 | B20: Factura B | C20: 0001-00007016 | D20: Empresa de Eventos Sur (FICTICIA) | F20: Menú ejecutivo | G20: 4 | H20: 56650 | I20: 0.21 | J20: =ROUND(H20*I20,2) -> 11896.5 | K20: =ROUND(H20+J20,2) -> 68546.5 | L20: Tarjeta de débito
A21: 46220 | B21: Factura B | C21: 0001-00007017 | D21: Consumidor final | F21: Cortes premium | G21: 5 | H21: 69596 | I21: 0.21 | J21: =ROUND(H21*I21,2) -> 14615.16 | K21: =ROUND(H21+J21,2) -> 84211.16 | L21: Mercado Pago
A22: 46221 | B22: Factura B | C22: 0001-00007018 | D22: Agencia Costera (FICTICIA) | F22: Bebidas y cubiertos | G22: 6 | H22: 82542 | I22: 0.21 | J22: =ROUND(H22*I22,2) -> 17333.82 | K22: =ROUND(H22+J22,2) -> 99875.82 | L22: Tarjeta de crédito
A23: 46222 | B23: Factura B | C23: 0001-00007019 | D23: Consumidor final | F23: Parrilla y cortes | G23: 1 | H23: 95488 | I23: 0.21 | J23: =ROUND(H23*I23,2) -> 20052.48 | K23: =ROUND(H23+J23,2) -> 115540.48 | L23: Efectivo
A24: 46223 | B24: Factura B | C24: 0001-00007020 | D24: Hotel Dársena (FICTICIO) | F24: Menú ejecutivo | G24: 2 | H24: 108434 | I24: 0.21 | J24: =ROUND(H24*I24,2) -> 22771.14 | K24: =ROUND(H24+J24,2) -> 131205.14 | L24: Transferencia
A25: 46224 | B25: Factura A | C25: 0001-00007021 | D25: Consumidor final | E25: 30-70064702-7 | F25: Cortes premium | G25: 3 | H25: 121380 | I25: 0.21 | J25: =ROUND(H25*I25,2) -> 25489.8 | K25: =ROUND(H25+J25,2) -> 146869.8 | L25: Tarjeta de débito
A26: 46225 | B26: Factura B | C26: 0001-00007022 | D26: Consultora Río (FICTICIA) | F26: Bebidas y cubiertos | G26: 4 | H26: 44325 | I26: 0.21 | J26: =ROUND(H26*I26,2) -> 9308.25 | K26: =ROUND(H26+J26,2) -> 53633.25 | L26: Mercado Pago
A27: 46226 | B27: Factura B | C27: 0001-00007023 | D27: Estudio Madero (FICTICIO) | F27: Parrilla y cortes | G27: 5 | H27: 57271 | I27: 0.21 | J27: =ROUND(H27*I27,2) -> 12026.91 | K27: =ROUND(H27+J27,2) -> 69297.91 | L27: Tarjeta de crédito
A28: 46227 | B28: Factura B | C28: 0001-00007024 | D28: Consumidor final | F28: Menú ejecutivo | G28: 6 | H28: 70217 | I28: 0.21 | J28: =ROUND(H28*I28,2) -> 14745.57 | K28: =ROUND(H28+J28,2) -> 84962.57 | L28: Efectivo
A29: 46228 | B29: Factura B | C29: 0001-00007025 | D29: Consumidor final | F29: Cortes premium | G29: 1 | H29: 83163 | I29: 0.21 | J29: =ROUND(H29*I29,2) -> 17464.23 | K29: =ROUND(H29+J29,2) -> 100627.23 | L29: Transferencia
A30: 46229 | B30: Factura B | C30: 0001-00007026 | D30: Consumidor final | F30: Bebidas y cubiertos | G30: 2 | H30: 96109 | I30: 0.21 | J30: =ROUND(H30*I30,2) -> 20182.89 | K30: =ROUND(H30+J30,2) -> 116291.89 | L30: Tarjeta de débito
A31: 46230 | B31: Factura B | C31: 0001-00007027 | D31: Consumidor final | F31: Parrilla y cortes | G31: 3 | H31: 109055 | I31: 0.21 | J31: =ROUND(H31*I31,2) -> 22901.55 | K31: =ROUND(H31+J31,2) -> 131956.55 | L31: Mercado Pago
A32: 46231 | B32: Factura B | C32: 0001-00007028 | D32: Empresa de Eventos Sur (FICTICIA) | F32: Menú ejecutivo | G32: 4 | H32: 122001 | I32: 0.21 | J32: =ROUND(H32*I32,2) -> 25620.21 | K32: =ROUND(H32+J32,2) -> 147621.21 | L32: Tarjeta de crédito
A33: 46204 | B33: Factura B | C33: 0001-00007029 | D33: Consumidor final | F33: Cortes premium | G33: 5 | H33: 44946 | I33: 0.21 | J33: =ROUND(H33*I33,2) -> 9438.66 | K33: =ROUND(H33+J33,2) -> 54384.66 | L33: Efectivo
A34: 46205 | B34: Factura B | C34: 0001-00007030 | D34: Agencia Costera (FICTICIA) | F34: Bebidas y cubiertos | G34: 6 | H34: 57892 | I34: 0.21 | J34: =ROUND(H34*I34,2) -> 12157.32 | K34: =ROUND(H34+J34,2) -> 70049.32 | L34: Transferencia
A35: 46206 | B35: Factura A | C35: 0001-00007031 | D35: Consumidor final | E35: 30-70066912-1 | F35: Parrilla y cortes | G35: 1 | H35: 70838 | I35: 0.21 | J35: =ROUND(H35*I35,2) -> 14875.98 | K35: =ROUND(H35+J35,2) -> 85713.98 | L35: Tarjeta de débito
A36: 46207 | B36: Factura B | C36: 0001-00007032 | D36: Hotel Dársena (FICTICIO) | F36: Menú ejecutivo | G36: 2 | H36: 83784 | I36: 0.21 | J36: =ROUND(H36*I36,2) -> 17594.64 | K36: =ROUND(H36+J36,2) -> 101378.64 | L36: Mercado Pago
A37: 46208 | B37: Factura B | C37: 0001-00007033 | D37: Consumidor final | F37: Cortes premium | G37: 3 | H37: 96730 | I37: 0.21 | J37: =ROUND(H37*I37,2) -> 20313.3 | K37: =ROUND(H37+J37,2) -> 117043.3 | L37: Tarjeta de crédito
A38: 46209 | B38: Factura B | C38: 0001-00007034 | D38: Consultora Río (FICTICIA) | F38: Bebidas y cubiertos | G38: 4 | H38: 109676 | I38: 0.21 | J38: =ROUND(H38*I38,2) -> 23031.96 | K38: =ROUND(H38+J38,2) -> 132707.96 | L38: Efectivo
A39: 46210 | B39: Factura B | C39: 0001-00007035 | D39: Estudio Madero (FICTICIO) | F39: Parrilla y cortes | G39: 5 | H39: 122622 | I39: 0.21 | J39: =ROUND(H39*I39,2) -> 25750.62 | K39: =ROUND(H39+J39,2) -> 148372.62 | L39: Transferencia
A40: 46211 | B40: Factura B | C40: 0001-00007036 | D40: Consumidor final | F40: Menú ejecutivo | G40: 6 | H40: 45567 | I40: 0.21 | J40: =ROUND(H40*I40,2) -> 9569.07 | K40: =ROUND(H40+J40,2) -> 55136.07 | L40: Tarjeta de débito
A41: 46212 | B41: Factura B | C41: 0001-00007037 | D41: Consumidor final | F41: Cortes premium | G41: 1 | H41: 58513 | I41: 0.21 | J41: =ROUND(H41*I41,2) -> 12287.73 | K41: =ROUND(H41+J41,2) -> 70800.73 | L41: Mercado Pago
A42: 46213 | B42: Factura B | C42: 0001-00007038 | D42: Consumidor final | F42: Bebidas y cubiertos | G42: 2 | H42: 71459 | I42: 0.21 | J42: =ROUND(H42*I42,2) -> 15006.39 | K42: =ROUND(H42+J42,2) -> 86465.39 | L42: Tarjeta de crédito
A43: 46214 | B43: Factura B | C43: 0001-00007039 | D43: Consumidor final | F43: Parrilla y cortes | G43: 3 | H43: 84405 | I43: 0.21 | J43: =ROUND(H43*I43,2) -> 17725.05 | K43: =ROUND(H43+J43,2) -> 102130.05 | L43: Efectivo
A44: 46215 | B44: Factura B | C44: 0001-00007040 | D44: Empresa de Eventos Sur (FICTICIA) | F44: Menú ejecutivo | G44: 4 | H44: 97351 | I44: 0.21 | J44: =ROUND(H44*I44,2) -> 20443.71 | K44: =ROUND(H44+J44,2) -> 117794.71 | L44: Transferencia
A45: 46216 | B45: Factura A | C45: 0001-00007041 | D45: Consumidor final | E45: 30-70069122-3 | F45: Cortes premium | G45: 5 | H45: 110297 | I45: 0.21 | J45: =ROUND(H45*I45,2) -> 23162.37 | K45: =ROUND(H45+J45,2) -> 133459.37 | L45: Tarjeta de débito
A46: 46217 | B46: Factura B | C46: 0001-00007042 | D46: Agencia Costera (FICTICIA) | F46: Bebidas y cubiertos | G46: 6 | H46: 123243 | I46: 0.21 | J46: =ROUND(H46*I46,2) -> 25881.03 | K46: =ROUND(H46+J46,2) -> 149124.03 | L46: Mercado Pago
A47: 46218 | B47: Factura B | C47: 0001-00007043 | D47: Consumidor final | F47: Parrilla y cortes | G47: 1 | H47: 46188 | I47: 0.21 | J47: =ROUND(H47*I47,2) -> 9699.48 | K47: =ROUND(H47+J47,2) -> 55887.48 | L47: Tarjeta de crédito
A48: 46219 | B48: Factura B | C48: 0001-00007044 | D48: Hotel Dársena (FICTICIO) | F48: Menú ejecutivo | G48: 2 | H48: 59134 | I48: 0.21 | J48: =ROUND(H48*I48,2) -> 12418.14 | K48: =ROUND(H48+J48,2) -> 71552.14 | L48: Efectivo
A49: 46220 | B49: Factura B | C49: 0001-00007045 | D49: Consumidor final | F49: Cortes premium | G49: 3 | H49: 72080 | I49: 0.21 | J49: =ROUND(H49*I49,2) -> 15136.8 | K49: =ROUND(H49+J49,2) -> 87216.8 | L49: Transferencia
A50: 46221 | B50: Factura B | C50: 0001-00007046 | D50: Consultora Río (FICTICIA) | F50: Bebidas y cubiertos | G50: 4 | H50: 85026 | I50: 0.21 | J50: =ROUND(H50*I50,2) -> 17855.46 | K50: =ROUND(H50+J50,2) -> 102881.46 | L50: Tarjeta de débito
A51: 46222 | B51: Factura B | C51: 0001-00007047 | D51: Estudio Madero (FICTICIO) | F51: Parrilla y cortes | G51: 5 | H51: 97972 | I51: 0.21 | J51: =ROUND(H51*I51,2) -> 20574.12 | K51: =ROUND(H51+J51,2) -> 118546.12 | L51: Mercado Pago
A52: 46223 | B52: Factura B | C52: 0001-00007048 | D52: Consumidor final | F52: Menú ejecutivo | G52: 6 | H52: 110918 | I52: 0.21 | J52: =ROUND(H52*I52,2) -> 23292.78 | K52: =ROUND(H52+J52,2) -> 134210.78 | L52: Tarjeta de crédito
A53: 46224 | B53: Factura B | C53: 0001-00007049 | D53: Consumidor final | F53: Cortes premium | G53: 1 | H53: 123864 | I53: 0.21 | J53: =ROUND(H53*I53,2) -> 26011.44 | K53: =ROUND(H53+J53,2) -> 149875.44 | L53: Efectivo
A54: 46225 | B54: Factura B | C54: 0001-00007050 | D54: Consumidor final | F54: Bebidas y cubiertos | G54: 2 | H54: 46809 | I54: 0.21 | J54: =ROUND(H54*I54,2) -> 9829.89 | K54: =ROUND(H54+J54,2) -> 56638.89 | L54: Transferencia
A55: 46226 | B55: Factura A | C55: 0001-00007051 | D55: Consumidor final | E55: 30-70071332-5 | F55: Parrilla y cortes | G55: 3 | H55: 59755 | I55: 0.21 | J55: =ROUND(H55*I55,2) -> 12548.55 | K55: =ROUND(H55+J55,2) -> 72303.55 | L55: Tarjeta de débito
A56: 46227 | B56: Factura B | C56: 0001-00007052 | D56: Empresa de Eventos Sur (FICTICIA) | F56: Menú ejecutivo | G56: 4 | H56: 72701 | I56: 0.21 | J56: =ROUND(H56*I56,2) -> 15267.21 | K56: =ROUND(H56+J56,2) -> 87968.21 | L56: Mercado Pago
A57: 46228 | B57: Factura B | C57: 0001-00007053 | D57: Consumidor final | F57: Cortes premium | G57: 5 | H57: 85647 | I57: 0.21 | J57: =ROUND(H57*I57,2) -> 17985.87 | K57: =ROUND(H57+J57,2) -> 103632.87 | L57: Tarjeta de crédito
A58: 46229 | B58: Factura B | C58: 0001-00007054 | D58: Agencia Costera (FICTICIA) | F58: Bebidas y cubiertos | G58: 6 | H58: 98593 | I58: 0.21 | J58: =ROUND(H58*I58,2) -> 20704.53 | K58: =ROUND(H58+J58,2) -> 119297.53 | L58: Efectivo

Sheet Julio Gastos
A1: COSTANERA GRILL · JULIO 2026 · REGISTRO DE COMPRAS Y GASTOS (SIMULACIÓN)
A2: Proveedores y comprobantes ficticios. Alícuotas ilustrativas; verificar normativa aplicable en un caso real.
A4: Fecha | B4: Proveedor | C4: CUIT proveedor (ficticio) | D4: Tipo comprobante | E4: Categoría | F4: Detalle | G4: Neto gravado | H4: Alícuota IVA | I4: IVA crédito | J4: Total | K4: Medio de pago
A5: 46205 | B5: Frigorífico La Pampa (FICTICIO) | C5: 30-70123456-1 | D5: Factura A | E5: Carne | F5: Compra de carne para operación | G5: 120118 | H5: 0.105 | I5: =ROUND(G5*H5,2) -> 12612.39 | J5: =ROUND(G5+I5,2) -> 132730.39 | K5: Tarjeta de débito
A6: 46208 | B6: Carnes del Sur (FICTICIO) | C6: 30-70987654-2 | D6: Factura B | E6: Carne | F6: Compra de carne para operación | G6: 179799 | H6: 0.105 | I6: =ROUND(G6*H6,2) -> 18878.9 | J6: =ROUND(G6+I6,2) -> 198677.9 | K6: Tarjeta de crédito
A7: 46211 | B7: Bebidas Río (FICTICIO) | C7: 30-71234567-3 | D7: Factura B | E7: Bebidas | F7: Compra de bebidas para operación | G7: 49002 | H7: 0.21 | I7: =ROUND(G7*H7,2) -> 10290.42 | J7: =ROUND(G7+I7,2) -> 59292.42 | K7: Transferencia
A8: 46214 | B8: Distribuidora Malbec (FICTICIO) | C8: 30-72345678-4 | D8: Factura A | E8: Bebidas | F8: Compra de bebidas para operación | G8: 71460 | H8: 0.21 | I8: =ROUND(G8*H8,2) -> 15006.6 | J8: =ROUND(G8+I8,2) -> 86466.6 | K8: Mercado Pago
A9: 46217 | B9: Edenor - ejemplo didáctico | C9: 30-54567891-2 | D9: Factura B | E9: Electricidad | F9: Compra de electricidad para operación | G9: 128298 | H9: 0.21 | I9: =ROUND(G9*H9,2) -> 26942.58 | J9: =ROUND(G9+I9,2) -> 155240.58 | K9: Efectivo
A10: 46220 | B10: Metrogas - ejemplo didáctico | C10: 30-65789123-4 | D10: Factura B | E10: Gas | F10: Compra de gas para operación | G10: 94633 | H10: 0.21 | I10: =ROUND(G10*H10,2) -> 19872.93 | J10: =ROUND(G10+I10,2) -> 114505.93 | K10: Tarjeta de débito
A11: 46223 | B11: Fibra Puerto (FICTICIO) | C11: 30-67891234-5 | D11: Factura A | E11: Internet | F11: Compra de internet para operación | G11: 25989 | H11: 0.21 | I11: =ROUND(G11*H11,2) -> 5457.69 | J11: =ROUND(G11+I11,2) -> 31446.69 | K11: Tarjeta de crédito
A12: 46226 | B12: Limpieza del Puerto (FICTICIO) | C12: 30-68912345-6 | D12: Factura B | E12: Limpieza | F12: Compra de limpieza para operación | G12: 38609 | H12: 0.21 | I12: =ROUND(G12*H12,2) -> 8107.89 | J12: =ROUND(G12+I12,2) -> 46716.89 | K12: Transferencia
A13: 46229 | B13: Envases del Plata (FICTICIO) | C13: 30-69123456-7 | D13: Factura B | E13: Insumos | F13: Compra de insumos para operación | G13: 49117 | H13: 0.21 | I13: =ROUND(G13*H13,2) -> 10314.57 | J13: =ROUND(G13+I13,2) -> 59431.57 | K13: Mercado Pago
A14: 46205 | B14: Alquiler local Puerto Madero (FICTICIO) | C14: 30-61234567-8 | D14: Factura A | E14: Alquiler | F14: Compra de alquiler para operación | G14: 116072 | H14: 0.21 | I14: =ROUND(G14*H14,2) -> 24375.12 | J14: =ROUND(G14+I14,2) -> 140447.12 | K14: Efectivo
A15: 46208 | B15: Mantenimiento Parrillero (FICTICIO) | C15: 30-63456789-1 | D15: Factura B | E15: Mantenimiento | F15: Compra de mantenimiento para operación | G15: 38020 | H15: 0.21 | I15: =ROUND(G15*H15,2) -> 7984.2 | J15: =ROUND(G15+I15,2) -> 46004.2 | K15: Tarjeta de débito
A16: 46211 | B16: Panificados del Puerto (FICTICIO) | C16: 30-64567891-3 | D16: Factura B | E16: Alimentos | F16: Compra de alimentos para operación | G16: 59791 | H16: 0.21 | I16: =ROUND(G16*H16,2) -> 12556.11 | J16: =ROUND(G16+I16,2) -> 72347.11 | K16: Tarjeta de crédito
... A22: 46229 | B22: Papelería Administrativa (FICTICIO) | C22: 30-61234578-9 | D22: Factura B | E22: Administración | F22: Compra de administración para operación | G22: 10711 | H22: 0.21 | I22: =ROUND(G22*H22,2) -> 2249.31 | J22: =ROUND(G22+I22,2) -> 12960.31 | K22: Transferencia

Sheet Agosto Ventas
A1: COSTANERA GRILL · AGOSTO 2026 · REGISTRO DE VENTAS (SIMULACIÓN)
A2: Datos inventados para ejercicio de capacitación. Sin validez fiscal ni contable. IVA calculado con fórmula sobre base imponible.
A4: Fecha | B4: Tipo comprobante | C4: Número | D4: Cliente | E4: CUIT cliente (ficticio) | F4: Concepto | G4: Cantidad | H4: Neto gravado | I4: Alícuota IVA | J4: IVA débito | K4: Total | L4: Medio de cobro
A5: 46235 | B5: Factura A | C5: 0001-00008001 | D5: Hotel Dársena (FICTICIO) | E5: 30-70061829-6 | F5: Bebidas y cubiertos | G5: 1 | H5: 43083 | I5: 0.21 | J5: =ROUND(H5*I5,2) -> 9047.43 | K5: =ROUND(H5+J5,2) -> 52130.43 | L5: Tarjeta de crédito
A6: 46236 | B6: Factura B | C6: 0001-00008002 | D6: Consumidor final | F6: Parrilla y cortes | G6: 2 | H6: 56029 | I6: 0.21 | J6: =ROUND(H6*I6,2) -> 11766.09 | K6: =ROUND(H6+J6,2) -> 67795.09 | L6: Efectivo
A7: 46237 | B7: Factura B | C7: 0001-00008003 | D7: Consultora Río (FICTICIA) | F7: Menú ejecutivo | G7: 3 | H7: 68975 | I7: 0.21 | J7: =ROUND(H7*I7,2) -> 14484.75 | K7: =ROUND(H7+J7,2) -> 83459.75 | L7: Transferencia
A8: 46238 | B8: Factura B | C8: 0001-00008004 | D8: Estudio Madero (FICTICIO) | F8: Cortes premium | G8: 4 | H8: 81921 | I8: 0.21 | J8: =ROUND(H8*I8,2) -> 17203.41 | K8: =ROUND(H8+J8,2) -> 99124.41 | L8: Tarjeta de débito
A9: 46239 | B9: Factura B | C9: 0001-00008005 | D9: Consumidor final | F9: Bebidas y cubiertos | G9: 5 | H9: 94867 | I9: 0.21 | J9: =ROUND(H9*I9,2) -> 19922.07 | K9: =ROUND(H9+J9,2) -> 114789.07 | L9: Mercado Pago
A10: 46240 | B10: Factura B | C10: 0001-00008006 | D10: Consumidor final | F10: Parrilla y cortes | G10: 6 | H10: 107813 | I10: 0.21 | J10: =ROUND(H10*I10,2) -> 22640.73 | K10: =ROUND(H10+J10,2) -> 130453.73 | L10: Tarjeta de crédito
A11: 46241 | B11: Factura B | C11: 0001-00008007 | D11: Consumidor final | F11: Menú ejecutivo | G11: 1 | H11: 120759 | I11: 0.21 | J11: =ROUND(H11*I11,2) -> 25359.39 | K11: =ROUND(H11+J11,2) -> 146118.39 | L11: Efectivo
A12: 46242 | B12: Factura B | C12: 0001-00008008 | D12: Consumidor final | F12: Cortes premium | G12: 2 | H12: 43704 | I12: 0.21 | J12: =ROUND(H12*I12,2) -> 9177.84 | K12: =ROUND(H12+J12,2) -> 52881.84 | L12: Transferencia
A13: 46243 | B13: Factura B | C13: 0001-00008009 | D13: Empresa de Eventos Sur (FICTICIA) | F13: Bebidas y cubiertos | G13: 3 | H13: 56650 | I13: 0.21 | J13: =ROUND(H13*I13,2) -> 11896.5 | K13: =ROUND(H13+J13,2) -> 68546.5 | L13: Tarjeta de débito
A14: 46244 | B14: Factura B | C14: 0001-00008010 | D14: Consumidor final | F14: Parrilla y cortes | G14: 4 | H14: 69596 | I14: 0.21 | J14: =ROUND(H14*I14,2) -> 14615.16 | K14: =ROUND(H14+J14,2) -> 84211.16 | L14: Mercado Pago
A15: 46245 | B15: Factura A | C15: 0001-00008011 | D15: Agencia Costera (FICTICIA) | E15: 30-70064039-8 | F15: Menú ejecutivo | G15: 5 | H15: 82542 | I15: 0.21 | J15: =ROUND(H15*I15,2) -> 17333.82 | K15: =ROUND(H15+J15,2) -> 99875.82 | L15: Tarjeta de crédito
A16: 46246 | B16: Factura B | C16: 0001-00008012 | D16: Consumidor final | F16: Cortes premium | G16: 6 | H16: 95488 | I16: 0.21 | J16: =ROUND(H16*I16,2) -> 20052.48 | K16: =ROUND(H16+J16,2) -> 115540.48 | L16: Efectivo
A17: 46247 | B17: Factura B | C17: 0001-00008013 | D17: Hotel Dársena (FICTICIO) | F17: Bebidas y cubiertos | G17: 1 | H17: 108434 | I17: 0.21 | J17: =ROUND(H17*I17,2) -> 22771.14 | K17: =ROUND(H17+J17,2) -> 131205.14 | L17: Transferencia
A18: 46248 | B18: Factura B | C18: 0001-00008014 | D18: Consumidor final | F18: Parrilla y cortes | G18: 2 | H18: 121380 | I18: 0.21 | J18: =ROUND(H18*I18,2) -> 25489.8 | K18: =ROUND(H18+J18,2) -> 146869.8 | L18: Tarjeta de débito
A19: 46249 | B19: Factura B | C19: 0001-00008015 | D19: Consultora Río (FICTICIA) | F19: Menú ejecutivo | G19: 3 | H19: 44325 | I19: 0.21 | J19: =ROUND(H19*I19,2) -> 9308.25 | K19: =ROUND(H19+J19,2) -> 53633.25 | L19: Mercado Pago
A20: 46250 | B20: Factura B | C20: 0001-00008016 | D20: Estudio Madero (FICTICIO) | F20: Cortes premium | G20: 4 | H20: 57271 | I20: 0.21 | J20: =ROUND(H20*I20,2) -> 12026.91 | K20: =ROUND(H20+J20,2) -> 69297.91 | L20: Tarjeta de crédito
A21: 46251 | B21: Factura B | C21: 0001-00008017 | D21: Consumidor final | F21: Bebidas y cubiertos | G21: 5 | H21: 70217 | I21: 0.21 | J21: =ROUND(H21*I21,2) -> 14745.57 | K21: =ROUND(H21+J21,2) -> 84962.57 | L21: Efectivo
A22: 46252 | B22: Factura B | C22: 0001-00008018 | D22: Consumidor final | F22: Parrilla y cortes | G22: 6 | H22: 83163 | I22: 0.21 | J22: =ROUND(H22*I22,2) -> 17464.23 | K22: =ROUND(H22+J22,2) -> 100627.23 | L22: Transferencia
A23: 46253 | B23: Factura B | C23: 0001-00008019 | D23: Consumidor final | F23: Menú ejecutivo | G23: 1 | H23: 96109 | I23: 0.21 | J23: =ROUND(H23*I23,2) -> 20182.89 | K23: =ROUND(H23+J23,2) -> 116291.89 | L23: Tarjeta de débito
A24: 46254 | B24: Factura B | C24: 0001-00008020 | D24: Consumidor final | F24: Cortes premium | G24: 2 | H24: 109055 | I24: 0.21 | J24: =ROUND(H24*I24,2) -> 22901.55 | K24: =ROUND(H24+J24,2) -> 131956.55 | L24: Mercado Pago
A25: 46255 | B25: Factura A | C25: 0001-00008021 | D25: Empresa de Eventos Sur (FICTICIA) | E25: 30-70066249-2 | F25: Bebidas y cubiertos | G25: 3 | H25: 122001 | I25: 0.21 | J25: =ROUND(H25*I25,2) -> 25620.21 | K25: =ROUND(H25+J25,2) -> 147621.21 | L25: Tarjeta de crédito
A26: 46256 | B26: Factura B | C26: 0001-00008022 | D26: Consumidor final | F26: Parrilla y cortes | G26: 4 | H26: 44946 | I26: 0.21 | J26: =ROUND(H26*I26,2) -> 9438.66 | K26: =ROUND(H26+J26,2) -> 54384.66 | L26: Efectivo
A27: 46257 | B27: Factura B | C27: 0001-00008023 | D27: Agencia Costera (FICTICIA) | F27: Menú ejecutivo | G27: 5 | H27: 57892 | I27: 0.21 | J27: =ROUND(H27*I27,2) -> 12157.32 | K27: =ROUND(H27+J27,2) -> 70049.32 | L27: Transferencia
A28: 46258 | B28: Factura B | C28: 0001-00008024 | D28: Consumidor final | F28: Cortes premium | G28: 6 | H28: 70838 | I28: 0.21 | J28: =ROUND(H28*I28,2) -> 14875.98 | K28: =ROUND(H28+J28,2) -> 85713.98 | L28: Tarjeta de débito
A29: 46259 | B29: Factura B | C29: 0001-00008025 | D29: Hotel Dársena (FICTICIO) | F29: Bebidas y cubiertos | G29: 1 | H29: 83784 | I29: 0.21 | J29: =ROUND(H29*I29,2) -> 17594.64 | K29: =ROUND(H29+J29,2) -> 101378.64 | L29: Mercado Pago
A30: 46260 | B30: Factura B | C30: 0001-00008026 | D30: Consumidor final | F30: Parrilla y cortes | G30: 2 | H30: 96730 | I30: 0.21 | J30: =ROUND(H30*I30,2) -> 20313.3 | K30: =ROUND(H30+J30,2) -> 117043.3 | L30: Tarjeta de crédito
A31: 46261 | B31: Factura B | C31: 0001-00008027 | D31: Consultora Río (FICTICIA) | F31: Menú ejecutivo | G31: 3 | H31: 109676 | I31: 0.21 | J31: =ROUND(H31*I31,2) -> 23031.96 | K31: =ROUND(H31+J31,2) -> 132707.96 | L31: Efectivo
A32: 46262 | B32: Factura B | C32: 0001-00008028 | D32: Estudio Madero (FICTICIO) | F32: Cortes premium | G32: 4 | H32: 122622 | I32: 0.21 | J32: =ROUND(H32*I32,2) -> 25750.62 | K32: =ROUND(H32+J32,2) -> 148372.62 | L32: Transferencia
A33: 46235 | B33: Factura B | C33: 0001-00008029 | D33: Consumidor final | F33: Bebidas y cubiertos | G33: 5 | H33: 45567 | I33: 0.21 | J33: =ROUND(H33*I33,2) -> 9569.07 | K33: =ROUND(H33+J33,2) -> 55136.07 | L33: Tarjeta de débito
A34: 46236 | B34: Factura B | C34: 0001-00008030 | D34: Consumidor final | F34: Parrilla y cortes | G34: 6 | H34: 58513 | I34: 0.21 | J34: =ROUND(H34*I34,2) -> 12287.73 | K34: =ROUND(H34+J34,2) -> 70800.73 | L34: Mercado Pago
A35: 46237 | B35: Factura A | C35: 0001-00008031 | D35: Consumidor final | E35: 30-70068459-4 | F35: Menú ejecutivo | G35: 1 | H35: 71459 | I35: 0.21 | J35: =ROUND(H35*I35,2) -> 15006.39 | K35: =ROUND(H35+J35,2) -> 86465.39 | L35: Tarjeta de crédito
A36: 46238 | B36: Factura B | C36: 0001-00008032 | D36: Consumidor final | F36: Cortes premium | G36: 2 | H36: 84405 | I36: 0.21 | J36: =ROUND(H36*I36,2) -> 17725.05 | K36: =ROUND(H36+J36,2) -> 102130.05 | L36: Efectivo
A37: 46239 | B37: Factura B | C37: 0001-00008033 | D37: Empresa de Eventos Sur (FICTICIA) | F37: Bebidas y cubiertos | G37: 3 | H37: 97351 | I37: 0.21 | J37: =ROUND(H37*I37,2) -> 20443.71 | K37: =ROUND(H37+J37,2) -> 117794.71 | L37: Transferencia
A38: 46240 | B38: Factura B | C38: 0001-00008034 | D38: Consumidor final | F38: Parrilla y cortes | G38: 4 | H38: 110297 | I38: 0.21 | J38: =ROUND(H38*I38,2) -> 23162.37 | K38: =ROUND(H38+J38,2) -> 133459.37 | L38: Tarjeta de débito
A39: 46241 | B39: Factura B | C39: 0001-00008035 | D39: Agencia Costera (FICTICIA) | F39: Menú ejecutivo | G39: 5 | H39: 123243 | I39: 0.21 | J39: =ROUND(H39*I39,2) -> 25881.03 | K39: =ROUND(H39+J39,2) -> 149124.03 | L39: Mercado Pago
A40: 46242 | B40: Factura B | C40: 0001-00008036 | D40: Consumidor final | F40: Cortes premium | G40: 6 | H40: 46188 | I40: 0.21 | J40: =ROUND(H40*I40,2) -> 9699.48 | K40: =ROUND(H40+J40,2) -> 55887.48 | L40: Tarjeta de crédito
A41: 46243 | B41: Factura B | C41: 0001-00008037 | D41: Hotel Dársena (FICTICIO) | F41: Bebidas y cubiertos | G41: 1 | H41: 59134 | I41: 0.21 | J41: =ROUND(H41*I41,2) -> 12418.14 | K41: =ROUND(H41+J41,2) -> 71552.14 | L41: Efectivo
A42: 46244 | B42: Factura B | C42: 0001-00008038 | D42: Consumidor final | F42: Parrilla y cortes | G42: 2 | H42: 72080 | I42: 0.21 | J42: =ROUND(H42*I42,2) -> 15136.8 | K42: =ROUND(H42+J42,2) -> 87216.8 | L42: Transferencia
A43: 46245 | B43: Factura B | C43: 0001-00008039 | D43: Consultora Río (FICTICIA) | F43: Menú ejecutivo | G43: 3 | H43: 85026 | I43: 0.21 | J43: =ROUND(H43*I43,2) -> 17855.46 | K43: =ROUND(H43+J43,2) -> 102881.46 | L43: Tarjeta de débito
A44: 46246 | B44: Factura B | C44: 0001-00008040 | D44: Estudio Madero (FICTICIO) | F44: Cortes premium | G44: 4 | H44: 97972 | I44: 0.21 | J44: =ROUND(H44*I44,2) -> 20574.12 | K44: =ROUND(H44+J44,2) -> 118546.12 | L44: Mercado Pago
A45: 46247 | B45: Factura A | C45: 0001-00008041 | D45: Consumidor final | E45: 30-70070669-6 | F45: Bebidas y cubiertos | G45: 5 | H45: 110918 | I45: 0.21 | J45: =ROUND(H45*I45,2) -> 23292.78 | K45: =ROUND(H45+J45,2) -> 134210.78 | L45: Tarjeta de crédito
A46: 46248 | B46: Factura B | C46: 0001-00008042 | D46: Consumidor final | F46: Parrilla y cortes | G46: 6 | H46: 123864 | I46: 0.21 | J46: =ROUND(H46*I46,2) -> 26011.44 | K46: =ROUND(H46+J46,2) -> 149875.44 | L46: Efectivo
A47: 46249 | B47: Factura B | C47: 0001-00008043 | D47: Consumidor final | F47: Menú ejecutivo | G47: 1 | H47: 46809 | I47: 0.21 | J47: =ROUND(H47*I47,2) -> 9829.89 | K47: =ROUND(H47+J47,2) -> 56638.89 | L47: Transferencia
A48: 46250 | B48: Factura B | C48: 0001-00008044 | D48: Consumidor final | F48: Cortes premium | G48: 2 | H48: 59755 | I48: 0.21 | J48: =ROUND(H48*I48,2) -> 12548.55 | K48: =ROUND(H48+J48,2) -> 72303.55 | L48: Tarjeta de débito
A49: 46251 | B49: Factura B | C49: 0001-00008045 | D49: Empresa de Eventos Sur (FICTICIA) | F49: Bebidas y cubiertos | G49: 3 | H49: 72701 | I49: 0.21 | J49: =ROUND(H49*I49,2) -> 15267.21 | K49: =ROUND(H49+J49,2) -> 87968.21 | L49: Mercado Pago
A50: 46252 | B50: Factura B | C50: 0001-00008046 | D50: Consumidor final | F50: Parrilla y cortes | G50: 4 | H50: 85647 | I50: 0.21 | J50: =ROUND(H50*I50,2) -> 17985.87 | K50: =ROUND(H50+J50,2) -> 103632.87 | L50: Tarjeta de crédito
A51: 46253 | B51: Factura B | C51: 0001-00008047 | D51: Agencia Costera (FICTICIA) | F51: Menú ejecutivo | G51: 5 | H51: 98593 | I51: 0.21 | J51: =ROUND(H51*I51,2) -> 20704.53 | K51: =ROUND(H51+J51,2) -> 119297.53 | L51: Efectivo
A52: 46254 | B52: Factura B | C52: 0001-00008048 | D52: Consumidor final | F52: Cortes premium | G52: 6 | H52: 111539 | I52: 0.21 | J52: =ROUND(H52*I52,2) -> 23423.19 | K52: =ROUND(H52+J52,2) -> 134962.19 | L52: Transferencia
A53: 46255 | B53: Factura B | C53: 0001-00008049 | D53: Hotel Dársena (FICTICIO) | F53: Bebidas y cubiertos | G53: 1 | H53: 124485 | I53: 0.21 | J53: =ROUND(H53*I53,2) -> 26141.85 | K53: =ROUND(H53+J53,2) -> 150626.85 | L53: Tarjeta de débito
A54: 46256 | B54: Factura B | C54: 0001-00008050 | D54: Consumidor final | F54: Parrilla y cortes | G54: 2 | H54: 47430 | I54: 0.21 | J54: =ROUND(H54*I54,2) -> 9960.3 | K54: =ROUND(H54+J54,2) -> 57390.3 | L54: Mercado Pago
A55: 46257 | B55: Factura A | C55: 0001-00008051 | D55: Consultora Río (FICTICIA) | E55: 30-70072879-8 | F55: Menú ejecutivo | G55: 3 | H55: 60376 | I55: 0.21 | J55: =ROUND(H55*I55,2) -> 12678.96 | K55: =ROUND(H55+J55,2) -> 73054.96 | L55: Tarjeta de crédito
A56: 46258 | B56: Factura B | C56: 0001-00008052 | D56: Estudio Madero (FICTICIO) | F56: Cortes premium | G56: 4 | H56: 73322 | I56: 0.21 | J56: =ROUND(H56*I56,2) -> 15397.62 | K56: =ROUND(H56+J56,2) -> 88719.62 | L56: Efectivo
A57: 46259 | B57: Factura B | C57: 0001-00008053 | D57: Consumidor final | F57: Bebidas y cubiertos | G57: 5 | H57: 86268 | I57: 0.21 | J57: =ROUND(H57*I57,2) -> 18116.28 | K57: =ROUND(H57+J57,2) -> 104384.28 | L57: Transferencia
A58: 46260 | B58: Factura B | C58: 0001-00008054 | D58: Consumidor final | F58: Parrilla y cortes | G58: 6 | H58: 99214 | I58: 0.21 | J58: =ROUND(H58*I58,2) -> 20834.94 | K58: =ROUND(H58+J58,2) -> 120048.94 | L58: Tarjeta de débito

Sheet Agosto Gastos
A1: COSTANERA GRILL · AGOSTO 2026 · REGISTRO DE COMPRAS Y GASTOS (SIMULACIÓN)
A2: Proveedores y comprobantes ficticios. Alícuotas ilustrativas; verificar normativa aplicable en un caso real.
A4: Fecha | B4: Proveedor | C4: CUIT proveedor (ficticio) | D4: Tipo comprobante | E4: Categoría | F4: Detalle | G4: Neto gravado | H4: Alícuota IVA | I4: IVA crédito | J4: Total | K4: Medio de pago
A5: 46236 | B5: Frigorífico La Pampa (FICTICIO) | C5: 30-70123456-1 | D5: Factura A | E5: Carne | F5: Compra de carne para operación | G5: 122579 | H5: 0.105 | I5: =ROUND(G5*H5,2) -> 12870.8 | J5: =ROUND(G5+I5,2) -> 135449.8 | K5: Tarjeta de crédito
A6: 46239 | B6: Carnes del Sur (FICTICIO) | C6: 30-70987654-2 | D6: Factura B | E6: Carne | F6: Compra de carne para operación | G6: 122260 | H6: 0.105 | I6: =ROUND(G6*H6,2) -> 12837.3 | J6: =ROUND(G6+I6,2) -> 135097.3 | K6: Transferencia
A7: 46242 | B7: Bebidas Río (FICTICIO) | C7: 30-71234567-3 | D7: Factura B | E7: Bebidas | F7: Compra de bebidas para operación | G7: 111457 | H7: 0.21 | I7: =ROUND(G7*H7,2) -> 23405.97 | J7: =ROUND(G7+I7,2) -> 134862.97 | K7: Mercado Pago
A8: 46245 | B8: Distribuidora Malbec (FICTICIO) | C8: 30-72345678-4 | D8: Factura A | E8: Bebidas | F8: Compra de bebidas para operación | G8: 73911 | H8: 0.21 | I8: =ROUND(G8*H8,2) -> 15521.31 | J8: =ROUND(G8+I8,2) -> 89432.31 | K8: Efectivo
A9: 46248 | B9: Edenor - ejemplo didáctico | C9: 30-54567891-2 | D9: Factura B | E9: Electricidad | F9: Compra de electricidad para operación | G9: 120752 | H9: 0.21 | I9: =ROUND(G9*H9,2) -> 25357.92 | J9: =ROUND(G9+I9,2) -> 146109.92 | K9: Tarjeta de débito
A10: 46251 | B10: Metrogas - ejemplo didáctico | C10: 30-65789123-4 | D10: Factura B | E10: Gas | F10: Compra de gas para operación | G10: 42081 | H10: 0.21 | I10: =ROUND(G10*H10,2) -> 8837.01 | J10: =ROUND(G10+I10,2) -> 50918.01 | K10: Tarjeta de crédito
A11: 46254 | B11: Fibra Puerto (FICTICIO) | C11: 30-67891234-5 | D11: Factura A | E11: Internet | F11: Compra de internet para operación | G11: 18367 | H11: 0.21 | I11: =ROUND(G11*H11,2) -> 3857.07 | J11: =ROUND(G11+I11,2) -> 22224.07 | K11: Transferencia
A12: 46257 | B12: Limpieza del Puerto (FICTICIO) | C12: 30-68912345-6 | D12: Factura B | E12: Limpieza | F12: Compra de limpieza para operación | G12: 27036 | H12: 0.21 | I12: =ROUND(G12*H12,2) -> 5677.56 | J12: =ROUND(G12+I12,2) -> 32713.56 | K12: Mercado Pago
A13: 46260 | B13: Envases del Plata (FICTICIO) | C13: 30-69123456-7 | D13: Factura B | E13: Insumos | F13: Compra de insumos para operación | G13: 27558 | H13: 0.21 | I13: =ROUND(G13*H13,2) -> 5787.18 | J13: =ROUND(G13+I13,2) -> 33345.18 | K13: Efectivo
A14: 46236 | B14: Alquiler local Puerto Madero (FICTICIO) | C14: 30-61234567-8 | D14: Factura A | E14: Alquiler | F14: Compra de alquiler para operación | G14: 138519 | H14: 0.21 | I14: =ROUND(G14*H14,2) -> 29088.99 | J14: =ROUND(G14+I14,2) -> 167607.99 | K14: Tarjeta de débito
A15: 46239 | B15: Mantenimiento Parrillero (FICTICIO) | C15: 30-63456789-1 | D15: Factura B | E15: Mantenimiento | F15: Compra de mantenimiento para operación | G15: 30455 | H15: 0.21 | I15: =ROUND(G15*H15,2) -> 6395.55 | J15: =ROUND(G15+I15,2) -> 36850.55 | K15: Tarjeta de crédito
A16: 46242 | B16: Panificados del Puerto (FICTICIO) | C16: 30-64567891-3 | D16: Factura B | E16: Alimentos | F16: Compra de alimentos para operación | G16: 50228 | H16: 0.21 | I16: =ROUND(G16*H16,2) -> 10547.88 | J16: =ROUND(G16+I16,2) -> 60775.88 | K16: Transferencia
... A22: 46260 | B22: Papelería Administrativa (FICTICIO) | C22: 30-61234578-9 | D22: Factura B | E22: Administración | F22: Compra de administración para operación | G22: 21102 | H22: 0.21 | I22: =ROUND(G22*H22,2) -> 4431.42 | J22: =ROUND(G22+I22,2) -> 25533.42 | K22: Mercado Pago

Sheet Septiembre Ventas
A1: COSTANERA GRILL · SEPTIEMBRE 2026 · REGISTRO DE VENTAS (SIMULACIÓN)
A2: Datos inventados para capacitación. Sin validez fiscal ni contable. Cargado hasta el 23/09 inclusive; el 24 se trabaja en clase.
A4: Fecha | B4: Tipo comprobante | C4: Número | D4: Cliente | E4: CUIT cliente (ficticio) | F4: Concepto | G4: Cantidad | H4: Neto gravado | I4: Alícuota IVA | J4: IVA débito | K4: Total | L4: Medio de cobro
A5: 46266 | B5: Factura B | C5: 0001-00009001 | D5: Consumidor final | F5: Menú ejecutivo | G5: 2 | H5: 65470 | I5: 0.21 | J5: =ROUND(H5*I5,2) -> 13748.7 | K5: =ROUND(H5+J5,2) -> 79218.7 | L5: Tarjeta de débito
A6: 46266 | B6: Factura B | C6: 0001-00009002 | D6: Consumidor final | F6: Bebidas y cubiertos | G6: 3 | H6: 91414 | I6: 0.21 | J6: =ROUND(H6*I6,2) -> 19196.94 | K6: =ROUND(H6+J6,2) -> 110610.94 | L6: Mercado Pago
A7: 46267 | B7: Factura B | C7: 0001-00009003 | D7: Consumidor final | F7: Cena corporativa | G7: 4 | H7: 74093 | I7: 0.21 | J7: =ROUND(H7*I7,2) -> 15559.53 | K7: =ROUND(H7+J7,2) -> 89652.53 | L7: Efectivo
A8: 46267 | B8: Factura B | C8: 0001-00009004 | D8: Consumidor final | F8: Parrilla y cortes | G8: 5 | H8: 100037 | I8: 0.21 | J8: =ROUND(H8*I8,2) -> 21007.77 | K8: =ROUND(H8+J8,2) -> 121044.77 | L8: Tarjeta de débito
A9: 46268 | B9: Factura B | C9: 0001-00009005 | D9: Consumidor final | F9: Menú ejecutivo | G9: 1 | H9: 82716 | I9: 0.21 | J9: =ROUND(H9*I9,2) -> 17370.36 | K9: =ROUND(H9+J9,2) -> 100086.36 | L9: Tarjeta de crédito
A10: 46268 | B10: Factura B | C10: 0001-00009006 | D10: Consumidor final | F10: Bebidas y cubiertos | G10: 2 | H10: 108660 | I10: 0.21 | J10: =ROUND(H10*I10,2) -> 22818.6 | K10: =ROUND(H10+J10,2) -> 131478.6 | L10: Efectivo
A11: 46269 | B11: Factura B | C11: 0001-00009007 | D11: Consumidor final | F11: Cena corporativa | G11: 3 | H11: 91339 | I11: 0.21 | J11: =ROUND(H11*I11,2) -> 19181.19 | K11: =ROUND(H11+J11,2) -> 110520.19 | L11: Transferencia
A12: 46269 | B12: Factura A | C12: 0001-00009008 | D12: Eventos Costanera (FICTICIO) | E12: 30-70065129-7 | F12: Parrilla y cortes | G12: 4 | H12: 117283 | I12: 0.21 | J12: =ROUND(H12*I12,2) -> 24629.43 | K12: =ROUND(H12+J12,2) -> 141912.43 | L12: Tarjeta de crédito
A13: 46269 | B13: Factura B | C13: 0001-00009009 | D13: Consumidor final | F13: Cortes premium | G13: 5 | H13: 143227 | I13: 0.21 | J13: =ROUND(H13*I13,2) -> 30077.67 | K13: =ROUND(H13+J13,2) -> 173304.67 | L13: Efectivo
A14: 46270 | B14: Factura B | C14: 0001-00009010 | D14: Consumidor final | F14: Bebidas y cubiertos | G14: 1 | H14: 158165 | I14: 0.21 | J14: =ROUND(H14*I14,2) -> 33214.65 | K14: =ROUND(H14+J14,2) -> 191379.65 | L14: Efectivo
A15: 46270 | B15: Factura B | C15: 0001-00009011 | D15: Consumidor final | F15: Almuerzo de equipo | G15: 2 | H15: 195413 | I15: 0.21 | J15: =ROUND(H15*I15,2) -> 41036.73 | K15: =ROUND(H15+J15,2) -> 236449.73 | L15: Tarjeta de débito
A16: 46270 | B16: Factura B | C16: 0001-00009012 | D16: Consumidor final | F16: Cena corporativa | G16: 3 | H16: 232661 | I16: 0.21 | J16: =ROUND(H16*I16,2) -> 48858.81 | K16: =ROUND(H16+J16,2) -> 281519.81 | L16: Mercado Pago
A17: 46271 | B17: Factura A | C17: 0001-00009013 | D17: Estudio Madero (FICTICIO) | E17: 30-70064039-8 | F17: Cortes premium | G17: 4 | H17: 168929 | I17: 0.21 | J17: =ROUND(H17*I17,2) -> 35475.09 | K17: =ROUND(H17+J17,2) -> 204404.09 | L17: Mercado Pago
A18: 46271 | B18: Factura B | C18: 0001-00009014 | D18: Consumidor final | F18: Menú ejecutivo | G18: 5 | H18: 206177 | I18: 0.21 | J18: =ROUND(H18*I18,2) -> 43297.17 | K18: =ROUND(H18+J18,2) -> 249474.17 | L18: Transferencia
A19: 46271 | B19: Factura B | C19: 0001-00009015 | D19: Consumidor final | F19: Bebidas y cubiertos | G19: 1 | H19: 243425 | I19: 0.21 | J19: =ROUND(H19*I19,2) -> 51119.25 | K19: =ROUND(H19+J19,2) -> 294544.25 | L19: Tarjeta de crédito
A20: 46272 | B20: Factura A | C20: 0001-00009016 | D20: Agencia Costera (FICTICIA) | E20: 30-70068459-2 | F20: Cena corporativa | G20: 2 | H20: 120667 | I20: 0.21 | J20: =ROUND(H20*I20,2) -> 25340.07 | K20: =ROUND(H20+J20,2) -> 146007.07 | L20: Tarjeta de crédito
A21: 46272 | B21: Factura B | C21: 0001-00009017 | D21: Consumidor final | F21: Parrilla y cortes | G21: 3 | H21: 146611 | I21: 0.21 | J21: =ROUND(H21*I21,2) -> 30788.31 | K21: =ROUND(H21+J21,2) -> 177399.31 | L21: Efectivo
A22: 46273 | B22: Factura B | C22: 0001-00009018 | D22: Consumidor final | F22: Menú ejecutivo | G22: 4 | H22: 129290 | I22: 0.21 | J22: =ROUND(H22*I22,2) -> 27150.9 | K22: =ROUND(H22+J22,2) -> 156440.9 | L22: Transferencia
A23: 46273 | B23: Factura B | C23: 0001-00009019 | D23: Consumidor final | F23: Bebidas y cubiertos | G23: 5 | H23: 155234 | I23: 0.21 | J23: =ROUND(H23*I23,2) -> 32599.14 | K23: =ROUND(H23+J23,2) -> 187833.14 | L23: Tarjeta de crédito
A24: 46274 | B24: Factura B | C24: 0001-00009020 | D24: Consumidor final | F24: Cena corporativa | G24: 1 | H24: 137913 | I24: 0.21 | J24: =ROUND(H24*I24,2) -> 28961.73 | K24: =ROUND(H24+J24,2) -> 166874.73 | L24: Mercado Pago
A25: 46274 | B25: Factura B | C25: 0001-00009021 | D25: Consumidor final | F25: Parrilla y cortes | G25: 2 | H25: 58857 | I25: 0.21 | J25: =ROUND(H25*I25,2) -> 12359.97 | K25: =ROUND(H25+J25,2) -> 71216.97 | L25: Transferencia
A26: 46275 | B26: Factura B | C26: 0001-00009022 | D26: Consumidor final | F26: Menú ejecutivo | G26: 3 | H26: 146536 | I26: 0.21 | J26: =ROUND(H26*I26,2) -> 30772.56 | K26: =ROUND(H26+J26,2) -> 177308.56 | L26: Tarjeta de débito
A27: 46275 | B27: Factura B | C27: 0001-00009023 | D27: Consumidor final | F27: Bebidas y cubiertos | G27: 4 | H27: 67480 | I27: 0.21 | J27: =ROUND(H27*I27,2) -> 14170.8 | K27: =ROUND(H27+J27,2) -> 81650.8 | L27: Mercado Pago
A28: 46276 | B28: Factura A | C28: 0001-00009024 | D28: Oficinas del Puerto (FICTICIAS) | E28: 30-70060679-4 | F28: Cena corporativa | G28: 5 | H28: 155159 | I28: 0.21 | J28: =ROUND(H28*I28,2) -> 32583.39 | K28: =ROUND(H28+J28,2) -> 187742.39 | L28: Efectivo
A29: 46276 | B29: Factura B | C29: 0001-00009025 | D29: Consumidor final | F29: Parrilla y cortes | G29: 1 | H29: 76103 | I29: 0.21 | J29: =ROUND(H29*I29,2) -> 15981.63 | K29: =ROUND(H29+J29,2) -> 92084.63 | L29: Tarjeta de débito
A30: 46276 | B30: Factura A | C30: 0001-00009026 | D30: Estudio Madero (FICTICIO) | E30: 30-70064039-8 | F30: Cortes premium | G30: 2 | H30: 102047 | I30: 0.21 | J30: =ROUND(H30*I30,2) -> 21429.87 | K30: =ROUND(H30+J30,2) -> 123476.87 | L30: Mercado Pago
A31: 46277 | B31: Factura B | C31: 0001-00009027 | D31: Consumidor final | F31: Bebidas y cubiertos | G31: 3 | H31: 232989 | I31: 0.21 | J31: =ROUND(H31*I31,2) -> 48927.69 | K31: =ROUND(H31+J31,2) -> 281916.69 | L31: Mercado Pago
A32: 46277 | B32: Factura B | C32: 0001-00009028 | D32: Consumidor final | F32: Almuerzo de equipo | G32: 4 | H32: 125237 | I32: 0.21 | J32: =ROUND(H32*I32,2) -> 26299.77 | K32: =ROUND(H32+J32,2) -> 151536.77 | L32: Transferencia
A33: 46277 | B33: Factura B | C33: 0001-00009029 | D33: Consumidor final | F33: Cena corporativa | G33: 5 | H33: 162485 | I33: 0.21 | J33: =ROUND(H33*I33,2) -> 34121.85 | K33: =ROUND(H33+J33,2) -> 196606.85 | L33: Tarjeta de crédito
A34: 46278 | B34: Factura B | C34: 0001-00009030 | D34: Consumidor final | F34: Cortes premium | G34: 1 | H34: 243753 | I34: 0.21 | J34: =ROUND(H34*I34,2) -> 51188.13 | K34: =ROUND(H34+J34,2) -> 294941.13 | L34: Tarjeta de crédito
A35: 46278 | B35: Factura B | C35: 0001-00009031 | D35: Consumidor final | F35: Menú ejecutivo | G35: 2 | H35: 136001 | I35: 0.21 | J35: =ROUND(H35*I35,2) -> 28560.21 | K35: =ROUND(H35+J35,2) -> 164561.21 | L35: Efectivo
A36: 46278 | B36: Factura A | C36: 0001-00009032 | D36: Estudio Madero (FICTICIO) | E36: 30-70064039-8 | F36: Bebidas y cubiertos | G36: 3 | H36: 173249 | I36: 0.21 | J36: =ROUND(H36*I36,2) -> 36382.29 | K36: =ROUND(H36+J36,2) -> 209631.29 | L36: Tarjeta de débito
A37: 46279 | B37: Factura B | C37: 0001-00009033 | D37: Consumidor final | F37: Cena corporativa | G37: 4 | H37: 79487 | I37: 0.21 | J37: =ROUND(H37*I37,2) -> 16692.27 | K37: =ROUND(H37+J37,2) -> 96179.27 | L37: Tarjeta de débito
A38: 46279 | B38: Factura B | C38: 0001-00009034 | D38: Consumidor final | F38: Parrilla y cortes | G38: 5 | H38: 105431 | I38: 0.21 | J38: =ROUND(H38*I38,2) -> 22140.51 | K38: =ROUND(H38+J38,2) -> 127571.51 | L38: Mercado Pago
A39: 46280 | B39: Factura B | C39: 0001-00009035 | D39: Consumidor final | F39: Menú ejecutivo | G39: 1 | H39: 88110 | I39: 0.21 | J39: =ROUND(H39*I39,2) -> 18503.1 | K39: =ROUND(H39+J39,2) -> 106613.1 | L39: Efectivo
A40: 46280 | B40: Factura B | C40: 0001-00009036 | D40: Consumidor final | F40: Bebidas y cubiertos | G40: 2 | H40: 114054 | I40: 0.21 | J40: =ROUND(H40*I40,2) -> 23951.34 | K40: =ROUND(H40+J40,2) -> 138005.34 | L40: Tarjeta de débito
A41: 46281 | B41: Factura B | C41: 0001-00009037 | D41: Consumidor final | F41: Cena corporativa | G41: 3 | H41: 96733 | I41: 0.21 | J41: =ROUND(H41*I41,2) -> 20313.93 | K41: =ROUND(H41+J41,2) -> 117046.93 | L41: Tarjeta de crédito
A42: 46281 | B42: Factura B | C42: 0001-00009038 | D42: Consumidor final | F42: Parrilla y cortes | G42: 4 | H42: 122677 | I42: 0.21 | J42: =ROUND(H42*I42,2) -> 25762.17 | K42: =ROUND(H42+J42,2) -> 148439.17 | L42: Efectivo
A43: 46282 | B43: Factura A | C43: 0001-00009039 | D43: Eventos Costanera (FICTICIO) | E43: 30-70065129-7 | F43: Menú ejecutivo | G43: 5 | H43: 105356 | I43: 0.21 | J43: =ROUND(H43*I43,2) -> 22124.76 | K43: =ROUND(H43+J43,2) -> 127480.76 | L43: Transferencia
A44: 46282 | B44: Factura A | C44: 0001-00009040 | D44: Consultora Río (FICTICIA) | E44: 30-70067349-1 | F44: Bebidas y cubiertos | G44: 1 | H44: 131300 | I44: 0.21 | J44: =ROUND(H44*I44,2) -> 27573 | K44: =ROUND(H44+J44,2) -> 158873 | L44: Tarjeta de crédito
A45: 46283 | B45: Factura B | C45: 0001-00009041 | D45: Consumidor final | F45: Cena corporativa | G45: 2 | H45: 113979 | I45: 0.21 | J45: =ROUND(H45*I45,2) -> 23935.59 | K45: =ROUND(H45+J45,2) -> 137914.59 | L45: Mercado Pago
A46: 46283 | B46: Factura B | C46: 0001-00009042 | D46: Consumidor final | F46: Parrilla y cortes | G46: 3 | H46: 139923 | I46: 0.21 | J46: =ROUND(H46*I46,2) -> 29383.83 | K46: =ROUND(H46+J46,2) -> 169306.83 | L46: Transferencia
A47: 46283 | B47: Factura B | C47: 0001-00009043 | D47: Consumidor final | F47: Cortes premium | G47: 4 | H47: 60867 | I47: 0.21 | J47: =ROUND(H47*I47,2) -> 12782.07 | K47: =ROUND(H47+J47,2) -> 73649.07 | L47: Tarjeta de crédito
A48: 46284 | B48: Factura B | C48: 0001-00009044 | D48: Consumidor final | F48: Bebidas y cubiertos | G48: 5 | H48: 162813 | I48: 0.21 | J48: =ROUND(H48*I48,2) -> 34190.73 | K48: =ROUND(H48+J48,2) -> 197003.73 | L48: Tarjeta de crédito
A49: 46284 | B49: Factura B | C49: 0001-00009045 | D49: Consumidor final | F49: Almuerzo de equipo | G49: 1 | H49: 200061 | I49: 0.21 | J49: =ROUND(H49*I49,2) -> 42012.81 | K49: =ROUND(H49+J49,2) -> 242073.81 | L49: Efectivo
A50: 46284 | B50: Factura B | C50: 0001-00009046 | D50: Consumidor final | F50: Cena corporativa | G50: 2 | H50: 237309 | I50: 0.21 | J50: =ROUND(H50*I50,2) -> 49834.89 | K50: =ROUND(H50+J50,2) -> 287143.89 | L50: Tarjeta de débito
A51: 46285 | B51: Factura B | C51: 0001-00009047 | D51: Consumidor final | F51: Cortes premium | G51: 3 | H51: 173577 | I51: 0.21 | J51: =ROUND(H51*I51,2) -> 36451.17 | K51: =ROUND(H51+J51,2) -> 210028.17 | L51: Tarjeta de débito
A52: 46285 | B52: Factura A | C52: 0001-00009048 | D52: Naviera del Plata (FICTICIA) | E52: 30-70069569-3 | F52: Menú ejecutivo | G52: 4 | H52: 210825 | I52: 0.21 | J52: =ROUND(H52*I52,2) -> 44273.25 | K52: =ROUND(H52+J52,2) -> 255098.25 | L52: Mercado Pago
A53: 46285 | B53: Factura B | C53: 0001-00009049 | D53: Consumidor final | F53: Bebidas y cubiertos | G53: 5 | H53: 248073 | I53: 0.21 | J53: =ROUND(H53*I53,2) -> 52095.33 | K53: =ROUND(H53+J53,2) -> 300168.33 | L53: Transferencia
A54: 46286 | B54: Factura B | C54: 0001-00009050 | D54: Consumidor final | F54: Cena corporativa | G54: 1 | H54: 143307 | I54: 0.21 | J54: =ROUND(H54*I54,2) -> 30094.47 | K54: =ROUND(H54+J54,2) -> 173401.47 | L54: Transferencia
A55: 46286 | B55: Factura B | C55: 0001-00009051 | D55: Consumidor final | F55: Parrilla y cortes | G55: 2 | H55: 64251 | I55: 0.21 | J55: =ROUND(H55*I55,2) -> 13492.71 | K55: =ROUND(H55+J55,2) -> 77743.71 | L55: Tarjeta de crédito
A56: 46287 | B56: Factura A | C56: 0001-00009052 | D56: Consultora Río (FICTICIA) | E56: 30-70067349-1 | F56: Menú ejecutivo | G56: 3 | H56: 151930 | I56: 0.21 | J56: =ROUND(H56*I56,2) -> 31905.3 | K56: =ROUND(H56+J56,2) -> 183835.3 | L56: Mercado Pago
A57: 46287 | B57: Factura B | C57: 0001-00009053 | D57: Consumidor final | F57: Bebidas y cubiertos | G57: 4 | H57: 72874 | I57: 0.21 | J57: =ROUND(H57*I57,2) -> 15303.54 | K57: =ROUND(H57+J57,2) -> 88177.54 | L57: Transferencia
A58: 46288 | B58: Factura B | C58: 0001-00009054 | D58: Consumidor final | F58: Cena corporativa | G58: 5 | H58: 160553 | I58: 0.21 | J58: =ROUND(H58*I58,2) -> 33716.13 | K58: =ROUND(H58+J58,2) -> 194269.13 | L58: Tarjeta de débito
A59: 46288 | B59: Factura B | C59: 0001-00009055 | D59: Consumidor final | F59: Parrilla y cortes | G59: 1 | H59: 81497 | I59: 0.21 | J59: =ROUND(H59*I59,2) -> 17114.37 | K59: =ROUND(H59+J59,2) -> 98611.37 | L59: Mercado Pago

Sheet Septiembre Gastos
A1: COSTANERA GRILL · SEPTIEMBRE 2026 · REGISTRO DE COMPRAS Y GASTOS (SIMULACIÓN)
A2: Proveedores y comprobantes ficticios. Alícuotas ilustrativas. Cargado hasta el 23/09 inclusive; el 24 se trabaja en clase.
A4: Fecha | B4: Proveedor | C4: CUIT proveedor (ficticio) | D4: Tipo comprobante | E4: Categoría | F4: Detalle | G4: Neto gravado | H4: Alícuota IVA | I4: IVA crédito | J4: Total | K4: Medio de pago
A5: 46266 | B5: Frigorífico del Sur (FICTICIO) | C5: 30-70123456-1 | D5: Factura A | E5: Carne | F5: Compra de carne vacuna para operación | G5: 94000 | H5: 0.105 | I5: =ROUND(G5*H5,2) -> 9870 | J5: =ROUND(G5+I5,2) -> 103870 | K5: Transferencia
A6: 46267 | B6: Bebidas Puerto (FICTICIO) | C6: 30-71234567-3 | D6: Factura B | E6: Bebidas | F6: Reposición de bebidas | G6: 68500 | H6: 0.21 | I6: =ROUND(G6*H6,2) -> 14385 | J6: =ROUND(G6+I6,2) -> 82885 | K6: Tarjeta de crédito
A7: 46268 | B7: Fibra Madero (FICTICIO) | C7: 30-67891234-5 | D7: Factura B | E7: Internet | F7: Servicio de internet | G7: 18500 | H7: 0.21 | I7: =ROUND(G7*H7,2) -> 3885 | J7: =ROUND(G7+I7,2) -> 22385 | K7: Débito automático
A8: 46269 | B8: Carnes del Plata (FICTICIO) | C8: 30-70987654-2 | D8: Factura A | E8: Carne | F8: Compra de cortes y achuras | G8: 132000 | H8: 0.105 | I8: =ROUND(G8*H8,2) -> 13860 | J8: =ROUND(G8+I8,2) -> 145860 | K8: Transferencia
A9: 46270 | B9: Energía Puerto (FICTICIO) | C9: 30-54567891-2 | D9: Factura B | E9: Electricidad | F9: Servicio eléctrico | G9: 78000 | H9: 0.21 | I9: =ROUND(G9*H9,2) -> 16380 | J9: =ROUND(G9+I9,2) -> 94380 | K9: Débito automático
A10: 46271 | B10: Envases Puerto (FICTICIO) | C10: 30-69123456-7 | D10: Factura B | E10: Insumos | F10: Envases y descartables | G10: 42500 | H10: 0.21 | I10: =ROUND(G10*H10,2) -> 8925 | J10: =ROUND(G10+I10,2) -> 51425 | K10: Mercado Pago
A11: 46272 | B11: Verdulería Costera (FICTICIO) | C11: 30-65678912-4 | D11: Factura A | E11: Alimentos | F11: Verduras y condimentos | G11: 36700 | H11: 0.105 | I11: =ROUND(G11*H11,2) -> 3853.5 | J11: =ROUND(G11+I11,2) -> 40553.5 | K11: Efectivo
A12: 46273 | B12: Gas Puerto (FICTICIO) | C12: 30-65789123-4 | D12: Factura B | E12: Gas | F12: Servicio de gas | G12: 51500 | H12: 0.21 | I12: =ROUND(G12*H12,2) -> 10815 | J12: =ROUND(G12+I12,2) -> 62315 | K12: Transferencia
A13: 46274 | B13: Frigorífico del Sur (FICTICIO) | C13: 30-70123456-1 | D13: Factura B | E13: Carne | F13: Compra de carne vacuna para operación | G13: 146000 | H13: 0.105 | I13: =ROUND(G13*H13,2) -> 15330 | J13: =ROUND(G13+I13,2) -> 161330 | K13: Transferencia
A14: 46275 | B14: Panificados Madero (FICTICIO) | C14: 30-64567891-3 | D14: Factura A | E14: Alimentos | F14: Panificados para servicio | G14: 29400 | H14: 0.105 | I14: =ROUND(G14*H14,2) -> 3087 | J14: =ROUND(G14+I14,2) -> 32487 | K14: Efectivo
A15: 46276 | B15: Limpieza Sur (FICTICIO) | C15: 30-68912345-6 | D15: Factura B | E15: Limpieza | F15: Artículos de limpieza | G15: 31800 | H15: 0.21 | I15: =ROUND(G15*H15,2) -> 6678 | J15: =ROUND(G15+I15,2) -> 38478 | K15: Tarjeta de débito
A16: 46277 | B16: Alquiler Puerto Madero (FICTICIO) | C16: 30-61234567-8 | D16: Factura B | E16: Alquiler | F16: Alquiler del local | G16: 390000 | H16: 0.21 | I16: =ROUND(G16*H16,2) -> 81900 | J16: =ROUND(G16+I16,2) -> 471900 | K16: Transferencia
... A22: 46283 | B22: Residuos Puerto (FICTICIO) | C22: 30-61827364-9 | D22: Factura B | E22: Servicios | F22: Retiro de residuos comerciales | G22: 23200 | H22: 0.21 | I22: =ROUND(G22*H22,2) -> 4872 | J22: =ROUND(G22+I22,2) -> 28072 | K22: Transferencia

Sheet Cierre de caja 23-09
A1: COSTANERA GRILL · CIERRE DE CAJA · 23/09/2026 (MODELO FICTICIO)
A2: Ejemplo manual previo al ejercicio del 24/09. Importes y operaciones ficticios, sin validez fiscal ni contable. Los cupones de crédito se controlan por separado porque su acreditación es posterior.
A4: Fecha | B4: Movimiento | C4: N.º comprobante | D4: Concepto / contraparte | E4: Importe (ARS) | F4: Factura / vale | G4: Pago / recibo | H4: Control documental | J4: CONTROL INTEGRAL DE CAJA Y COBRANZAS
A5: 23/09/2026 | B5: Saldo inicial | C5: Apertura de turno | D5: Efectivo contado al inicio | E5: 200000 | F5: Nota de apertura | G5: Recuento inicial | H5: Apertura informada | J5: ARQUEO DE EFECTIVO
A6: 23/09/2026 | B6: Ingreso efectivo | C6: Factura B 0001-00000001 | D6: Venta de salón · cobro en efectivo | E6: 250000 | F6: Comprobante simulado | G6: Recibo de caja simulado | H6: Venta ficticia; revisar importe | J6: Saldo inicial de caja | K6: =SUMIF(B5:B26,"Saldo inicial",E5:E26) -> 200000
A7: 23/09/2026 | B7: Ingreso efectivo | C7: Factura A 0001-00000002 | D7: Venta de salón · cobro en efectivo | E7: 315000 | F7: Comprobante simulado | G7: Recibo de caja simulado | H7: Venta ficticia; revisar importe | J7: (+) Ventas cobradas en efectivo | K7: =SUMIF(B5:B26,"Ingreso efectivo",E5:E26) -> 4100000
A8: 23/09/2026 | B8: Ingreso efectivo | C8: Factura B 0001-00000003 | D8: Venta de salón · cobro en efectivo | E8: 198000 | F8: Comprobante simulado | G8: Recibo de caja simulado | H8: Venta ficticia; revisar importe | J8: (-) Pagos en efectivo con factura | K8: =SUMIFS(E5:E26,B5:B26,"Egreso efectivo",H5:H26,"Factura y pago ficticios") -> 2300000
A9: 23/09/2026 | B9: Ingreso efectivo | C9: Factura A 0001-00000004 | D9: Venta de salón · cobro en efectivo | E9: 287000 | F9: Comprobante simulado | G9: Recibo de caja simulado | H9: Venta ficticia; revisar importe | J9: (-) Pagos en efectivo sin factura | K9: =SUMIFS(E5:E26,B5:B26,"Egreso efectivo",H5:H26,"Pendiente de factura proveedor") -> 35000
A10: 23/09/2026 | B10: Ingreso efectivo | C10: Factura B 0001-00000005 | D10: Venta de salón · cobro en efectivo | E10: 340000 | F10: Comprobante simulado | G10: Recibo de caja simulado | H10: Venta ficticia; revisar importe | J10: Saldo teórico de caja al cierre | K10: =K6+K7-K8-K9 -> 1965000
A11: 23/09/2026 | B11: Ingreso efectivo | C11: Factura A 0001-00000006 | D11: Venta de salón · cobro en efectivo | E11: 175000 | F11: Comprobante simulado | G11: Recibo de caja simulado | H11: Venta ficticia; revisar importe | J11: Efectivo contado por la cajera | K11: 1965000
A12: 23/09/2026 | B12: Ingreso efectivo | C12: Factura B 0001-00000007 | D12: Venta de salón · cobro en efectivo | E12: 422000 | F12: Comprobante simulado | G12: Recibo de caja simulado | H12: Venta ficticia; revisar importe | J12: Diferencia de caja | K12: =K11-K10 -> 0
A13: 23/09/2026 | B13: Ingreso efectivo | C13: Factura A 0001-00000008 | D13: Venta de salón · cobro en efectivo | E13: 206000 | F13: Comprobante simulado | G13: Recibo de caja simulado | H13: Venta ficticia; revisar importe | J13: Resultado del arqueo | K13: =IF(K12=0,"Caja conciliada","Revisar diferencia") -> Caja conciliada
A14: 23/09/2026 | B14: Ingreso efectivo | C14: Factura B 0001-00000009 | D14: Venta de salón · cobro en efectivo | E14: 260000 | F14: Comprobante simulado | G14: Recibo de caja simulado | H14: Venta ficticia; revisar importe | J14: CONTROL DE COBRANZAS POR OTROS MEDIOS
A15: 23/09/2026 | B15: Ingreso efectivo | C15: Factura A 0001-00000010 | D15: Venta de salón · cobro en efectivo | E15: 319000 | F15: Comprobante simulado | G15: Recibo de caja simulado | H15: Venta ficticia; revisar importe | J15: Tarjeta de crédito: 15 cupones | K15: =SUMIF(B27:B41,"Venta tarjeta crédito",E27:E41) -> 3390178
A16: 23/09/2026 | B16: Ingreso efectivo | C16: Factura B 0001-00000011 | D16: Venta de salón · cobro en efectivo | E16: 189000 | F16: Comprobante simulado | G16: Recibo de caja simulado | H16: Venta ficticia; revisar importe | J16: Acreditación de tarjeta de crédito visible el 23/09 | K16: 0
A17: 23/09/2026 | B17: Ingreso efectivo | C17: Factura A 0001-00000012 | D17: Venta de salón · cobro en efectivo | E17: 375000 | F17: Comprobante simulado | G17: Recibo de caja simulado | H17: Venta ficticia; revisar importe | J17: Transferencias informadas: 7 operaciones | K17: =SUMIF(B42:B48,"Venta transferencia",E42:E48) -> 2020000
A18: 23/09/2026 | B18: Ingreso efectivo | C18: Factura B 0001-00000013 | D18: Venta de salón · cobro en efectivo | E18: 231000 | F18: Comprobante simulado | G18: Recibo de caja simulado | H18: Venta ficticia; revisar importe | J18: Transferencias acreditadas en extracto: 6 | K18: =SUMIF(H42:H48,"Acreditada en extracto",E42:E48) -> 1775000
A19: 23/09/2026 | B19: Ingreso efectivo | C19: Factura A 0001-00000014 | D19: Venta de salón · cobro en efectivo | E19: 298000 | F19: Comprobante simulado | G19: Recibo de caja simulado | H19: Venta ficticia; revisar importe | J19: Transferencia pendiente de acreditación | K19: =SUMIF(H42:H48,"Pendiente de acreditación",E42:E48) -> 245000
A20: 23/09/2026 | B20: Ingreso efectivo | C20: Factura B 0001-00000015 | D20: Venta de salón · cobro en efectivo | E20: 235000 | F20: Comprobante simulado | G20: Recibo de caja simulado | H20: Venta ficticia; revisar importe | J20: Mercado Pago: 4 operaciones | K20: =SUMIF(B49:B52,"Venta Mercado Pago",E49:E52) -> 479500
A21: 23/09/2026 | B21: Egreso efectivo | C21: Factura A 0004-00001190 | D21: Compra de carne · Frigorífico Río Sur | E21: 1150000 | F21: Factura simulada | G21: Recibo de pago simulado | H21: Factura y pago ficticios | J21: Débitos bancarios del día (pagos a proveedores) | K21: 520000
A22: 23/09/2026 | B22: Egreso efectivo | C22: Factura A 0004-00001191 | D22: Bebidas · Distribuidora del Puerto | E22: 420000 | F22: Factura simulada | G22: Recibo de pago simulado | H22: Factura y pago ficticios | J22: Extracto bancario | K22: Control ficticio; sin archivo adjunto
A23: 23/09/2026 | B23: Egreso efectivo | C23: Factura B 0004-00001192 | D23: Verduras y condimentos · Huerta Fresca | E23: 320000 | F23: Factura simulada | G23: Recibo de pago simulado | H23: Factura y pago ficticios
A24: 23/09/2026 | B24: Egreso efectivo | C24: Factura A 0004-00001193 | D24: Limpieza y descartables · Suministros Delta | E24: 210000 | F24: Factura simulada | G24: Recibo de pago simulado | H24: Factura y pago ficticios
A25: 23/09/2026 | B25: Egreso efectivo | C25: Factura B 0004-00001194 | D25: Gas envasado · Gastronómica Río | E25: 200000 | F25: Factura simulada | G25: Recibo de pago simulado | H25: Factura y pago ficticios
A26: 23/09/2026 | B26: Egreso efectivo | C26: CG-CAJA-023 | D26: Carbón para parrilla · Carbones del Puerto | E26: 35000 | F26: Sin factura | G26: Vale interno simulado | H26: Pendiente de factura proveedor
A27: 23/09/2026 | B27: Venta tarjeta crédito | C27: Cupón simulado 001 | D27: Venta con tarjeta de crédito · operación 1 | E27: 128865 | F27: Comprobante de venta simulado | G27: Cupón simulado | H27: Acreditación posterior; no incluir en banco del día | J27: SÍNTESIS DE CAJA PARA ENVIAR AL DUEÑO
A28: 23/09/2026 | B28: Venta tarjeta crédito | C28: Cupón simulado 002 | D28: Venta con tarjeta de crédito · operación 2 | E28: 211145 | F28: Comprobante de venta simulado | G28: Cupón simulado | H28: Acreditación posterior; no incluir en banco del día | J28: INGRESOS Y COBROS DEL DÍA
A29: 23/09/2026 | B29: Venta tarjeta crédito | C29: Cupón simulado 003 | D29: Venta con tarjeta de crédito · operación 3 | E29: 142780 | F29: Comprobante de venta simulado | G29: Cupón simulado | H29: Acreditación posterior; no incluir en banco del día | J29: (+) Efectivo cobrado en ARS | K29: =K7 -> 4100000
A30: 23/09/2026 | B30: Venta tarjeta crédito | C30: Cupón simulado 004 | D30: Venta con tarjeta de crédito · operación 4 | E30: 360096 | F30: Comprobante de venta simulado | G30: Cupón simulado | H30: Acreditación posterior; no incluir en banco del día | J30: (+) Transferencias acreditadas | K30: =K18 -> 1775000
A31: 23/09/2026 | B31: Venta tarjeta crédito | C31: Cupón simulado 005 | D31: Venta con tarjeta de crédito · operación 5 | E31: 121605 | F31: Comprobante de venta simulado | G31: Cupón simulado | H31: Acreditación posterior; no incluir en banco del día | J31: (+) Cobros por Mercado Pago | K31: =K20 -> 479500
A32: 23/09/2026 | B32: Venta tarjeta crédito | C32: Cupón simulado 006 | D32: Venta con tarjeta de crédito · operación 6 | E32: 195415 | F32: Comprobante de venta simulado | G32: Cupón simulado | H32: Acreditación posterior; no incluir en banco del día | J32: Total ingresos directos del día | K32: =SUM(K29:K31) -> 6354500
A33: 23/09/2026 | B33: Venta tarjeta crédito | C33: Cupón simulado 007 | D33: Venta con tarjeta de crédito · operación 7 | E33: 266926 | F33: Comprobante de venta simulado | G33: Cupón simulado | H33: Acreditación posterior; no incluir en banco del día | J33: EGRESOS Y PAGOS DEL DÍA
A34: 23/09/2026 | B34: Venta tarjeta crédito | C34: Cupón simulado 008 | D34: Venta con tarjeta de crédito · operación 8 | E34: 343640 | F34: Comprobante de venta simulado | G34: Cupón simulado | H34: Acreditación posterior; no incluir en banco del día | J34: (-) Pagos en efectivo | K34: =K8+K9 -> 2335000
A35: 23/09/2026 | B35: Venta tarjeta crédito | C35: Cupón simulado 009 | D35: Venta con tarjeta de crédito · operación 9 | E35: 176055 | F35: Comprobante de venta simulado | G35: Cupón simulado | H35: Acreditación posterior; no incluir en banco del día | J35: (-) Débitos bancarios del día | K35: =K21 -> 520000
A36: 23/09/2026 | B36: Venta tarjeta crédito | C36: Cupón simulado 010 | D36: Venta con tarjeta de crédito · operación 10 | E36: 167585 | F36: Comprobante de venta simulado | G36: Cupón simulado | H36: Acreditación posterior; no incluir en banco del día | J36: (-) Pagos por Mercado Pago | K36: 42500
A37: 23/09/2026 | B37: Venta tarjeta crédito | C37: Cupón simulado 011 | D37: Venta con tarjeta de crédito · operación 11 | E37: 253495 | F37: Comprobante de venta simulado | G37: Cupón simulado | H37: Acreditación posterior; no incluir en banco del día | J37: Total egresos del día | K37: =SUM(K34:K36) -> 2897500
A38: 23/09/2026 | B38: Venta tarjeta crédito | C38: Cupón simulado 012 | D38: Venta con tarjeta de crédito · operación 12 | E38: 261360 | F38: Comprobante de venta simulado | G38: Cupón simulado | H38: Acreditación posterior; no incluir en banco del día | J38: MOVIMIENTO NETO DIRECTO DEL DÍA (ARS) | K38: =K32-K37 -> 3457000
A39: 23/09/2026 | B39: Venta tarjeta crédito | C39: Cupón simulado 013 | D39: Venta con tarjeta de crédito · operación 13 | E39: 343035 | F39: Comprobante de venta simulado | G39: Cupón simulado | H39: Acreditación posterior; no incluir en banco del día | J39: Efectivo contado al cierre (ARS) | K39: =K11 -> 1965000
A40: 23/09/2026 | B40: Venta tarjeta crédito | C40: Cupón simulado 014 | D40: Venta con tarjeta de crédito · operación 14 | E40: 272976 | F40: Comprobante de venta simulado | G40: Cupón simulado | H40: Acreditación posterior; no incluir en banco del día | J40: Cupones de crédito pendientes de acreditación | K40: =K15 -> 3390178
A41: 23/09/2026 | B41: Venta tarjeta crédito | C41: Cupón simulado 015 | D41: Venta con tarjeta de crédito · operación 15 | E41: 145200 | F41: Comprobante de venta simulado | G41: Cupón simulado | H41: Acreditación posterior; no incluir en banco del día | J41: Notas de control | K41: Transferencia pendiente: $245.000. Gasto en carbón sin factura: $35.000.
A42: 23/09/2026 | B42: Venta transferencia | C42: Transferencia simulada 001 | D42: Venta cobrada por transferencia | E42: 350000 | F42: Comprobante simulado | G42: Extracto bancario simulado | H42: Acreditada en extracto | J42: Moneda extranjera
A43: 23/09/2026 | B43: Venta transferencia | C43: Transferencia simulada 002 | D43: Venta cobrada por transferencia | E43: 420000 | F43: Comprobante simulado | G43: Extracto bancario simulado | H43: Acreditada en extracto
A44: 23/09/2026 | B44: Venta transferencia | C44: Transferencia simulada 003 | D44: Venta cobrada por transferencia | E44: 190000 | F44: Comprobante simulado | G44: Extracto bancario simulado | H44: Acreditada en extracto
A45: 23/09/2026 | B45: Venta transferencia | C45: Transferencia simulada 004 | D45: Venta cobrada por transferencia | E45: 275000 | F45: Comprobante simulado | G45: Extracto bancario simulado | H45: Acreditada en extracto
A46: 23/09/2026 | B46: Venta transferencia | C46: Transferencia simulada 005 | D46: Venta cobrada por transferencia | E46: 380000 | F46: Comprobante simulado | G46: Extracto bancario simulado | H46: Acreditada en extracto
A47: 23/09/2026 | B47: Venta transferencia | C47: Transferencia simulada 006 | D47: Venta cobrada por transferencia | E47: 160000 | F47: Comprobante simulado | G47: Extracto bancario simulado | H47: Acreditada en extracto
A48: 23/09/2026 | B48: Venta transferencia | C48: Transferencia simulada 007 | D48: Venta cobrada por transferencia · pendiente de acreditación | E48: 245000 | F48: Comprobante simulado | G48: Sin acreditación al cierre | H48: Pendiente de acreditación
A49: 23/09/2026 | B49: Venta Mercado Pago | C49: MP-2309-001 | D49: Venta cobrada por Mercado Pago · operación 1 | E49: 120000 | F49: Comprobante simulado | G49: Detalle MP simulado | H49: Acreditada en cuenta de Mercado Pago
A50: 23/09/2026 | B50: Venta Mercado Pago | C50: MP-2309-002 | D50: Venta cobrada por Mercado Pago · operación 2 | E50: 94800 | F50: Comprobante simulado | G50: Detalle MP simulado | H50: Acreditada en cuenta de Mercado Pago
A51: 23/09/2026 | B51: Venta Mercado Pago | C51: MP-2309-003 | D51: Venta cobrada por Mercado Pago · operación 3 | E51: 188200 | F51: Comprobante simulado | G51: Detalle MP simulado | H51: Acreditada en cuenta de Mercado Pago
A52: 23/09/2026 | B52: Venta Mercado Pago | C52: MP-2309-004 | D52: Venta cobrada por Mercado Pago · operación 4 | E52: 76500 | F52: Comprobante simulado | G52: Detalle MP simulado | H52: Acreditada en cuenta de Mercado Pago
A53: 46313 | B53: Venta transferencia | C53: Factura A 0001-00000025 | D53: Venta cobrada por transferencia | E53: 453024 | F53: =HYPERLINK("https://drive.google.com/file/d/1GHvF5G_YRoBYxT0vqXphHbgS8Kr4DRuj/view","Abrir factura") -> Abrir factura | G53: =HYPERLINK("https://drive.google.com/file/d/1_sMZSxRjWmynW7ajD-vfvJvLtL_Gg8iz/view","Abrir extracto") -> Abrir extracto | H53: Acreditada en extracto bancario
A54: 46313 | B54: Venta transferencia | C54: Factura B 0001-00000026 | D54: Venta cobrada por transferencia | E54: 220220 | F54: =HYPERLINK("https://drive.google.com/file/d/16Bqy0a_UcBmm3iEmO9OtEFJsjlAMNFmm/view","Abrir factura") -> Abrir factura | G54: =HYPERLINK("https://drive.google.com/file/d/1_sMZSxRjWmynW7ajD-vfvJvLtL_Gg8iz/view","Abrir extracto") -> Abrir extracto | H54: Acreditada en extracto bancario
A55: 46313 | B55: Venta transferencia | C55: Factura A 0001-00000029 | D55: Venta cobrada por transferencia | E55: 544742 | F55: =HYPERLINK("https://drive.google.com/file/d/15HNwYJ__eG3gLgCh200YjvjBvQwt8dWo/view","Abrir factura") -> Abrir factura | G55: =HYPERLINK("https://drive.google.com/file/d/1_sMZSxRjWmynW7ajD-vfvJvLtL_Gg8iz/view","Abrir extracto") -> Abrir extracto | H55: Acreditada en extracto bancario
A56: 46313 | B56: Venta transferencia | C56: Factura B 0001-00000030 | D56: Venta cobrada por transferencia | E56: 93775 | F56: =HYPERLINK("https://drive.google.com/file/d/1Qwj0QSE5PlvoOnxxw6I7wTND2e7OgmBI/view","Abrir factura") -> Abrir factura | G56: =HYPERLINK("https://drive.google.com/file/d/1_sMZSxRjWmynW7ajD-vfvJvLtL_Gg8iz/view","Abrir extracto") -> Abrir extracto | H56: Acreditada en extracto bancario
A57: 46313 | B57: Venta transferencia | C57: Factura A 0001-00000017 | D57: Venta cobrada por transferencia | E57: 496100 | F57: =HYPERLINK("https://drive.google.com/file/d/1_lzJHQQqmequ_24uAuAOrmMNOUmJ9ewX/view","Abrir factura") -> Abrir factura | G57: =HYPERLINK("https://drive.google.com/file/d/1_sMZSxRjWmynW7ajD-vfvJvLtL_Gg8iz/view","Abrir extracto") -> Abrir extracto | H57: Pendiente: no figura en extracto
A58: 46313 | B58: Venta Mercado Pago | C58: Factura A 0001-00000004 | D58: Venta cobrada por Mercado Pago | E58: 116160 | F58: =HYPERLINK("https://drive.google.com/file/d/1LEyY059S2oClkp7kH0z-FG2omQl4tpXn/view","Abrir factura") -> Abrir factura | G58: Constancia en comprobante de venta | H58: Cobro electrónico; no integra efectivo
A59: 46313 | B59: Venta Mercado Pago | C59: Factura A 0001-00000008 | D59: Venta cobrada por Mercado Pago | E59: 165891 | F59: =HYPERLINK("https://drive.google.com/file/d/1Q_b00yMM8fsDJ1-bsddZgg-tcS7HqwSQ/view","Abrir factura") -> Abrir factura | G59: Constancia en comprobante de venta | H59: Cobro electrónico; no integra efectivo
A60: 46313 | B60: Venta Mercado Pago | C60: Factura A 0001-00000012 | D60: Venta cobrada por Mercado Pago | E60: 207515 | F60: =HYPERLINK("https://drive.google.com/file/d/1gubd0ohYh6W2FoCWdoVqP1uVruvvPq1_/view","Abrir factura") -> Abrir factura | G60: Constancia en comprobante de venta | H60: Cobro electrónico; no integra efectivo
A61: 46313 | B61: Venta Mercado Pago | C61: Factura A 0001-00000016 | D61: Venta cobrada por Mercado Pago | E61: 226875 | F61: =HYPERLINK("https://drive.google.com/file/d/1RjiRWuo-r_03v-eyIohyJcRf9Q02RHk0/view","Abrir factura") -> Abrir factura | G61: Constancia en comprobante de venta | H61: Cobro electrónico; no integra efectivo
A62: 46313 | B62: Venta Mercado Pago | C62: Factura A 0001-00000020 | D62: Venta cobrada por Mercado Pago | E62: 259787 | F62: =HYPERLINK("https://drive.google.com/file/d/1aEfwwi5XAG6yK2oTkLSNABOcXObz9Mk9/view","Abrir factura") -> Abrir factura | G62: Constancia en comprobante de venta | H62: Cobro electrónico; no integra efectivo
A63: 46313 | B63: Venta Mercado Pago | C63: Factura A 0001-00000024 | D63: Venta cobrada por Mercado Pago | E63: 220946 | F63: =HYPERLINK("https://drive.google.com/file/d/1vvejhl_jyqSaA5kcC0GCczP4PHOLix79/view","Abrir factura") -> Abrir factura | G63: Constancia en comprobante de venta | H63: Cobro electrónico; no integra efectivo
A64: 46313 | B64: Venta Mercado Pago | C64: Factura A 0001-00000028 | D64: Venta cobrada por Mercado Pago | E64: 251922 | F64: =HYPERLINK("https://drive.google.com/file/d/1h34Ga0a3Q8wF45MwaOKzO-cBYQYoNJIl/view","Abrir factura") -> Abrir factura | G64: Constancia en comprobante de venta | H64: Cobro electrónico; no integra efectivo
A65: 46313 | B65: Venta Mercado Pago | C65: Factura B 0001-00000004 | D65: Venta cobrada por Mercado Pago | E65: 80465 | F65: =HYPERLINK("https://drive.google.com/file/d/1P3rNkcfwD0hZpURJp5A2aBFnBhjfZH7U/view","Abrir factura") -> Abrir factura | G65: Constancia en comprobante de venta | H65: Cobro electrónico; no integra efectivo
A66: 46313 | B66: Venta Mercado Pago | C66: Factura B 0001-00000008 | D66: Venta cobrada por Mercado Pago | E66: 81070 | F66: =HYPERLINK("https://drive.google.com/file/d/16k5JcKBGmHiL8_2TAJz2bWXb6d9kxq4_/view","Abrir factura") -> Abrir factura | G66: Constancia en comprobante de venta | H66: Cobro electrónico; no integra efectivo
A67: 46313 | B67: Venta Mercado Pago | C67: Factura B 0001-00000012 | D67: Venta cobrada por Mercado Pago | E67: 144111 | F67: =HYPERLINK("https://drive.google.com/file/d/1uTHRSwaVermLqXN28EJRvbSBvwSVOdSO/view","Abrir factura") -> Abrir factura | G67: Constancia en comprobante de venta | H67: Cobro electrónico; no integra efectivo
A68: 46313 | B68: Venta Mercado Pago | C68: Factura B 0001-00000016 | D68: Venta cobrada por Mercado Pago | E68: 46585 | F68: =HYPERLINK("https://drive.google.com/file/d/1FmAaZsCRevm-7ZfjiQru4deTc5uLQNX6/view","Abrir factura") -> Abrir factura | G68: Constancia en comprobante de venta | H68: Cobro electrónico; no integra efectivo
A69: 46313 | B69: Venta Mercado Pago | C69: Factura B 0001-00000020 | D69: Venta cobrada por Mercado Pago | E69: 254705 | F69: =HYPERLINK("https://drive.google.com/file/d/1ActtKmfc9-1_RmjyiMgZCXBY3bycMwdg/view","Abrir factura") -> Abrir factura | G69: Constancia en comprobante de venta | H69: Cobro electrónico; no integra efectivo
A70: 46313 | B70: Venta Mercado Pago | C70: Factura B 0001-00000024 | D70: Venta cobrada por Mercado Pago | E70: 129470 | F70: =HYPERLINK("https://drive.google.com/file/d/13NZMhurSrceIMLkBQA7A9VU08TF2Nj1G/view","Abrir factura") -> Abrir factura | G70: Constancia en comprobante de venta | H70: Cobro electrónico; no integra efectivo
A71: 46313 | B71: Venta Mercado Pago | C71: Factura B 0001-00000028 | D71: Venta cobrada por Mercado Pago | E71: 91355 | F71: =HYPERLINK("https://drive.google.com/file/d/1wFlR5cT7lqYTI1lQEWnToNGNxNX6Q3Ap/view","Abrir factura") -> Abrir factura | G71: Constancia en comprobante de venta | H71: Cobro electrónico; no integra efectivo
A72: 24/09/2026 | B72: Egreso bancario | C72: Factura A 0004-00001201 | D72: Pago a Frigorífico del Sur · proveedor de carnes | E72: 230000 | G72: =HYPERLINK("https://drive.google.com/file/d/1_sMZSxRjWmynW7ajD-vfvJvLtL_Gg8iz/view","Abrir extracto") -> Abrir extracto | H72: Anotado en nota y extracto
A73: 24/09/2026 | B73: Egreso bancario | C73: Factura A 0004-00001202 | D73: Pago a Distribuidora Río de la Plata · bebidas | E73: 78500 | G73: =HYPERLINK("https://drive.google.com/file/d/1_sMZSxRjWmynW7ajD-vfvJvLtL_Gg8iz/view","Abrir extracto") -> Abrir extracto | H73: Anotado en nota y extracto
A74: 24/09/2026 | B74: Egreso bancario | C74: Factura A 0004-00001203 | D74: Pago de Energía Metropolitana | E74: 90420 | G74: =HYPERLINK("https://drive.google.com/file/d/1_sMZSxRjWmynW7ajD-vfvJvLtL_Gg8iz/view","Abrir extracto") -> Abrir extracto | H74: Anotado en nota y extracto
A75: 24/09/2026 | B75: Egreso bancario | C75: Factura A 0004-00001204 | D75: Pago a Descartables Puerto · insumos | E75: 31200 | G75: =HYPERLINK("https://drive.google.com/file/d/1_sMZSxRjWmynW7ajD-vfvJvLtL_Gg8iz/view","Abrir extracto") -> Abrir extracto | H75: Anotado en nota y extracto
A76: 24/09/2026 | B76: Egreso bancario | C76: Débito 17:48 | D76: Servicio de internet | E76: 22900 | G76: =HYPERLINK("https://drive.google.com/file/d/1_sMZSxRjWmynW7ajD-vfvJvLtL_Gg8iz/view","Abrir extracto") -> Abrir extracto | H76: Solo extracto; no consta en nota de caja
A77: 24/09/2026 | B77: Egreso bancario | C77: Débito 19:02 | D77: Limpieza del local | E77: 19800 | G77: =HYPERLINK("https://drive.google.com/file/d/1_sMZSxRjWmynW7ajD-vfvJvLtL_Gg8iz/view","Abrir extracto") -> Abrir extracto | H77: Solo extracto; no consta en nota de caja
A78: 24/09/2026 | B78: Egreso bancario | C78: Débito 20:34 | D78: Servicio de gas | E78: 42300 | G78: =HYPERLINK("https://drive.google.com/file/d/1_sMZSxRjWmynW7ajD-vfvJvLtL_Gg8iz/view","Abrir extracto") -> Abrir extracto | H78: Solo extracto; no consta en nota de caja
A79: 24/09/2026 | B79: Egreso bancario | C79: Débito 22:05 | D79: Comisión y mantenimiento de cuenta | E79: 14750 | G79: =HYPERLINK("https://drive.google.com/file/d/1_sMZSxRjWmynW7ajD-vfvJvLtL_Gg8iz/view","Abrir extracto") -> Abrir extracto | H79: Solo extracto; no consta en nota de caja

Sheet Resumen mensual
A1: COSTANERA GRILL · RESUMEN MENSUAL 2026 (SIMULACIÓN)
A2: Ventas facturadas e IVA estimado. Septiembre contiene datos hasta el 23/09 inclusive.
A4: Mes | B4: Ventas facturadas (total) | C4: IVA débito | D4: IVA crédito | E4: Estimación IVA del mes
A5: Enero | B5: =SUM('Enero Ventas'!K5:K1000) -> 5780525.7 | C5: =SUM('Enero Ventas'!J5:J1000) -> 1003231.7 | D5: =SUM('Enero Gastos'!I5:I1000) -> 218268.02 | E5: =C5-D5 -> 784963.72
A6: Febrero | B6: =SUM('Febrero Ventas'!K5:K1000) -> 5143761.2 | C6: =SUM('Febrero Ventas'!J5:J1000) -> 892718.89 | D6: =SUM('Febrero Gastos'!I5:I1000) -> 1319925.3 | E6: =C6-D6 -> -427206.4
A7: Marzo | B7: =SUM('Marzo Ventas'!K5:K1000) -> 5643875.6 | C7: =SUM('Marzo Ventas'!J5:J1000) -> 979515.6 | D7: =SUM('Marzo Gastos'!I5:I1000) -> 223369.45 | E7: =C7-D7 -> 756146.15
A8: Abril | B8: =SUM('Abril Ventas'!K5:K1000) -> 5575550.5 | C8: =SUM('Abril Ventas'!J5:J1000) -> 967657.53 | D8: =SUM('Abril Gastos'!I5:I1000) -> 211902.18 | E8: =C8-D8 -> 755755.35
A9: Mayo | B9: =SUM('Mayo Ventas'!K5:K1000) -> 5507225.5 | C9: =SUM('Mayo Ventas'!J5:J1000) -> 955799.46 | D9: =SUM('Mayo Gastos'!I5:I1000) -> 212930.55 | E9: =C9-D9 -> 742868.91
A10: Junio | B10: =SUM('Junio Ventas'!K5:K1000) -> 5438900.4 | C10: =SUM('Junio Ventas'!J5:J1000) -> 943941.39 | D10: =SUM('Junio Gastos'!I5:I1000) -> 212173.72 | E10: =C10-D10 -> 731767.67
A11: Julio | B11: =SUM('Julio Ventas'!K5:K1000) -> 5370575.3 | C11: =SUM('Julio Ventas'!J5:J1000) -> 932083.32 | D11: =SUM('Julio Gastos'!I5:I1000) -> 207111.56 | E11: =C11-D11 -> 724971.76
A12: Agosto | B12: =SUM('Agosto Ventas'!K5:K1000) -> 5411151.5 | C12: =SUM('Agosto Ventas'!J5:J1000) -> 939125.46 | D12: =SUM('Agosto Gastos'!I5:I1000) -> 207824.72 | E12: =C12-D12 -> 731300.74
A13: Septiembre | B13: =SUM('Septiembre Ventas'!K5:K1000) -> 9091464.5 | C13: =SUM('Septiembre Ventas'!J5:J1000) -> 1577857.5 | D13: =SUM('Septiembre Gastos'!I5:I1000) -> 258961.5 | E13: =C13-D13 -> 1318896
A14: Estimación de práctica: IVA débito menos IVA crédito. No es una liquidación fiscal ni reemplaza controles profesionales.
A15: Enero-agosto: meses completos simulados. Septiembre: período parcial al 23/09; al cargar las operaciones del 24, las fórmulas y el gráfico se actualizarán.
